Workbook

Sheet Raw Data
A1: idstd | B1: a2 | C1: a6a | D1: a6c | E1: d1a2_v4 | F1: b5 | G1: b7 | H1: wmedian | I1: d2 | J1: n3 | K1: f1 | L1: l1 | M1: l2 | N1: n2a | O1: n2e | P1: n7a | Q1: d3c | R1: r2 | S1: h1 | T1: h5 | U1: k3a | V1: k3bc | W1: k3f | X1: k4 | Y1: n5a | Z1: k82a | AA1: k162a | AB1: c6 | AC1: c7 | AD1: c30a | AE1: k30 | AF1: l30b | AG1: e30 | AH1: m1a | AI1: a17
A2: 1614120 | B2: 3 | C2: 3 | D2: 1000 | E2: 1073 | F2: 1986 | G2: 24 | H2: 1 | I2: 1200000000 | J2: 900000000 | K2: 20 | L2: 250 | M2: 180 | N2: 500000000 | O2: 200000000 | P2: 350000000 | Q2: 25 | R2: 1 | S2: 2 | T2: 2 | U2: 85 | V2: 0 | W2: 0 | X2: 2 | Z2: 2 | AA2: 2 | AB2: 1 | AC2: 6 | AD2: 2 | AE2: 3 | AF2: 2 | AG2: 2 | AH2: 14 | AI2: 4
A3: 1614122 | B3: 3 | C3: 1 | D3: 10 | E3: 1410 | F3: 1970 | G3: 30 | H3: 55.69917 | I3: 45000000 | J3: 40000000 | K3: 70 | L3: 6 | M3: 5 | N3: 7200000 | O3: 6000000 | P3: 30000000 | Q3: 0 | S3: 2 | T3: 2 | U3: 100 | V3: 0 | W3: 0 | X3: 2 | Z3: 2 | AA3: 2 | AB3: 1 | AC3: 2 | AD3: 4 | AE3: 2 | AF3: 0 | AG3: 0 | AH3: 8 | AI3: 1
A4: 1614124 | B4: 1 | C4: 2 | D4: 100 | E4: 1073 | F4: 2007 | G4: 20 | H4: 24.842424 | I4: 3000000000 | J4: 2000000000 | K4: 70 | L4: 50 | M4: 50 | N4: 700000000 | O4: 400000000 | P4: 5000000000 | Q4: 0 | R4: 1 | S4: 2 | T4: 2 | U4: 80 | V4: 0 | W4: 0 | X4: 2 | Z4: 2 | AA4: 2 | AB4: 2 | AD4: 2 | AE4: 1 | AF4: 1 | AG4: 2 | AH4: 4 | AI4: 1
A5: 1614125 | B5: 1 | C5: 3 | D5: 110 | E5: 2100 | F5: 1981 | G5: 44 | H5: 1 | I5: 13000000000 | J5: 13000000000 | K5: 90 | L5: 57 | M5: 44 | N5: 1500000000 | O5: 6000000000 | P5: 12000000000 | Q5: 1 | R5: 1 | S5: 2 | T5: 2 | U5: 100 | V5: 0 | W5: 0 | X5: 1 | Y5: 600000000 | Z5: 1 | AA5: 2 | AB5: 1 | AC5: 10 | AD5: 3 | AE5: 1 | AF5: 3 | AG5: 3 | AH5: 1 | AI5: 1
A6: 1614130 | B6: 1 | C6: 1 | D6: 7 | E6: 3100 | F6: 2020 | G6: 15 | H6: 143.61815 | I6: 24000000 | J6: 17000000 | K6: 70 | L6: 5 | M6: 4 | N6: 4100000 | O6: 12000000 | P6: 11000000 | Q6: 0 | S6: 1 | T6: 1 | U6: 60 | V6: 10 | W6: 30 | X6: 1 | Y6: 500000 | Z6: 1 | AA6: 2 | AB6: 1 | AC6: 6 | AD6: 1 | AE6: 0 | AF6: 0 | AG6: 1 | AH6: 14 | AI6: 4
A7: 1614131 | B7: 1 | C7: 1 | D7: 16 | E7: 1811 | F7: 1985 | G7: 30 | H7: 157.86736 | I7: 100000000 | J7: 80000000 | K7: 20 | L7: 16 | M7: 16 | N7: 5000000 | O7: 20000000 | P7: 350000000 | Q7: 0 | S7: 2 | T7: 2 | U7: 80 | V7: 0 | W7: 0 | X7: 2 | Z7: 2 | AA7: 2 | AB7: 2 | AD7: 1 | AE7: 0 | AF7: 0 | AG7: 0 | AH7: 8 | AI7: 4
A8: 1614136 | B8: 1 | C8: 3 | D8: 1850 | E8: 2410 | F8: 1983 | G8: 42 | H8: 1 | I8: 6000000000000 | J8: 4000000000000 | K8: 92 | L8: 2000 | M8: 1800 | N8: 1000000000000 | O8: 3000000000000 | P8: 1000000000000 | Q8: 35 | R8: 1 | S8: 1 | T8: 1 | U8: 35 | V8: 30 | W8: 25 | X8: 1 | Y8: 1000000000000 | Z8: 1 | AA8: 1 | AB8: 1 | AC8: 2 | AD8: 2 | AE8: 2 | AF8: 1 | AG8: 2 | AH8: 14 | AI8: 1
A9: 1614138 | B9: 3 | C9: 1 | D9: 9 | E9: 1079 | F9: 1992 | G9: 30 | H9: 1.7886078 | I9: 38000000 | J9: 6000000 | K9: 100 | L9: 9 | M9: 9 | N9: 10000000 | O9: -9 | P9: 15000000 | Q9: 0 | S9: 2 | T9: 2 | U9: 40 | V9: 0 | W9: 0 | X9: 2 | Z9: 2 | AA9: 2 | AB9: 1 | AC9: 8 | AD9: 4 | AE9: 2 | AF9: 0 | AG9: 4 | AH9: 1 | AI9: 4
A10: 1614139 | B10: 2 | C10: 1 | D10: 5 | E10: 3100 | F10: 2002 | G10: 24 | H10: 68.62606 | I10: 40000000 | J10: 22000000 | K10: 4 | L10: 5 | M10: 5 | N10: 12000000 | O10: 16000000 | P10: 24200000 | Q10: 0 | S10: 2 | T10: 2 | U10: 20 | V10: 60 | W10: 0 | X10: 1 | Y10: 1000000 | Z10: 1 | AA10: 2 | AB10: 1 | AC10: 5 | AD10: 3 | AE10: 4 | AF10: 0 | AG10: 1 | AH10: 1 | AI10: 2
A11: 1614143 | B11: 1 | C11: 1 | D11: 6 | E11: 2599 | F11: 1987 | G11: 35 | H11: 157.86736 | I11: 10000000 | J11: 10000000 | K11: 100 | L11: 6 | M11: 6 | N11: 6000000 | O11: 3000000 | P11: 7000000 | Q11: 0 | S11: 2 | T11: 2 | U11: 80 | V11: 10 | W11: 0 | X11: 2 | Z11: 2 | AA11: 1 | AB11: 1 | AC11: 2 | AD11: 1 | AE11: 3 | AF11: 0 | AG11: 1 | AH11: 1 | AI11: 4
A12: 1614144 | B12: 1 | C12: 1 | D12: 50 | E12: 1812 | F12: 1995 | G12: 17 | H12: 585.9553 | I12: 300000000 | J12: 110000000 | K12: 95 | L12: 40 | M12: 20 | N12: 30000000 | O12: 40000000 | P12: 1000000000 | Q12: 10 | R12: 1 | S12: 2 | T12: 1 | U12: 80 | V12: 10 | W12: 0 | X12: 1 | Y12: 300000000 | Z12: 1 | AA12: 2 | AB12: 1 | AC12: 6 | AD12: 1 | AE12: 0 | AF12: 0 | AG12: 1 | AH12: 7 | AI12: 2
A13: 1614146 | B13: 1 | C13: 1 | D13: 80 | E13: 2023 | F13: 2005 | G13: 20 | H13: 585.9553 | I13: 2000000000 | J13: 1000000000 | K13: 70 | L13: 80 | M13: 40 | N13: 200000000 | O13: 800000000 | P13: 700000000 | Q13: 30 | R13: 1 | S13: 1 | T13: 1 | U13: 40 | V13: 5 | W13: 0 | X13: 1 | Y13: 80000000 | Z13: 1 | AA13: 2 | AB13: 1 | AC13: 4 | AD13: 3 | AE13: 0 | AF13: 0 | AG13: 0 | AH13: 14 | AI13: 4
A14: 1614147 | B14: 3 | C14: 3 | D14: 100 | E14: 1079 | F14: 1982 | G14: 43 | H14: 1 | I14: 3000000000 | J14: 2500000000 | K14: 30 | L14: 35 | M14: 35 | N14: 300000000 | O14: 900000000 | P14: 600000000 | Q14: 10 | R14: 1 | S14: 2 | T14: 1 | U14: 100 | V14: 0 | W14: 0 | X14: 2 | Z14: 2 | AA14: 2 | AB14: 1 | AC14: 5 | AD14: 3 | AE14: 1 | AF14: 2 | AG14: 4 | AH14: 12 | AI14: 4
A15: 1614149 | B15: 4 | C15: 2 | D15: 10 | E15: 1040 | F15: 2013 | G15: 10 | H15: 1.826539 | I15: 300000000 | J15: 250000000 | K15: 100 | L15: 15 | M15: 10 | N15: 70000000 | O15: 100000000 | P15: 400000000 | Q15: 0 | S15: 2 | T15: 2 | U15: 40 | V15: 0 | W15: 40 | X15: 2 | Z15: 2 | AA15: 2 | AB15: 1 | AC15: 7 | AD15: 2 | AE15: 1 | AF15: 0 | AG15: 4 | AH15: 12 | AI15: 4
A16: 1614151 | B16: 1 | C16: 3 | D16: 355 | E16: 1079 | F16: 1994 | G16: 25 | H16: 1 | I16: 68000000000 | J16: 67000000000 | K16: 69 | L16: 124 | M16: 118 | N16: 4140000000 | O16: 37820000000 | P16: 95000000000 | Q16: 1 | R16: 1 | S16: 1 | T16: 2 | U16: 100 | V16: 0 | W16: 0 | X16: 2 | Z16: 2 | AA16: 2 | AB16: 1 | AC16: 10 | AD16: 4 | AE16: 1 | AF16: 1 | AG16: 4 | AH16: 8 | AI16: 4
A17: 1614153 | B17: 3 | C17: 2 | D17: 8 | E17: 3100 | F17: 2021 | G17: 5 | H17: 3.0692382 | I17: 60000000 | J17: 30000000 | K17: 70 | L17: 8 | M17: 8 | N17: 20000000 | O17: 35000000 | P17: -9 | Q17: 0 | S17: 2 | T17: 2 | U17: 30 | V17: 25 | W17: 20 | X17: 2 | Z17: 1 | AA17: 2 | AB17: 1 | AC17: 6 | AD17: 1 | AE17: 3 | AF17: 0 | AG17: 3 | AH17: 14 | AI17: 1
A18: 1614155 | B18: 2 | C18: 2 | D18: 16 | E18: 1410 | F18: 1990 | G18: 35 | H18: 2.4641058 | I18: 57242000 | J18: 35000000 | K18: 13 | L18: 6 | M18: 6 | N18: 18000000 | O18: 22500000 | P18: 26500000 | Q18: 0 | S18: 2 | T18: 2 | U18: 50 | V18: 10 | W18: 10 | X18: 2 | Z18: 1 | AA18: 1 | AB18: 1 | AC18: 0 | AD18: 1 | AE18: 3 | AF18: 0 | AG18: 1 | AH18: 1 | AI18: 4
A19: 1614157 | B19: 3 | C19: 1 | D19: 7 | E19: 1061 | F19: 2015 | G19: 10 | H19: 26.253841 | I19: 32000000 | J19: 28000000 | K19: 65 | L19: 7 | M19: 7 | N19: 12000000 | O19: 18000000 | P19: 20000000 | Q19: 0 | S19: 2 | T19: 2 | U19: 80 | V19: 0 | W19: 0 | X19: 2 | Z19: 2 | AA19: 2 | AB19: 1 | AC19: 8 | AD19: 2 | AE19: 3 | AF19: 0 | AG19: 3 | AH19: 14 | AI19: 2
A20: 1614160 | B20: 2 | C20: 1 | D20: 16 | E20: 3100 | F20: 2009 | G20: 20 | H20: 68.62606 | I20: 45000000 | J20: 18000000 | K20: 60 | L20: 12 | M20: 8 | N20: -9 | O20: 30000000 | P20: 50000000 | Q20: 0 | S20: 2 | T20: 1 | U20: 50 | V20: 25 | W20: 0 | X20: 2 | Z20: 1 | AA20: 1 | AB20: 1 | AC20: 30 | AD20: 3 | AE20: 2 | AF20: 1 | AG20: 3 | AH20: 8 | AI20: 2
A21: 1614161 | B21: 3 | C21: 1 | D21: 7 | E21: 1061 | F21: 2000 | G21: 25 | H21: 118.82497 | I21: 154000000 | J21: 144000000 | K21: 100 | L21: 7 | M21: 7 | N21: 21600000 | O21: 35000000 | P21: 300000000 | Q21: 0 | S21: 2 | T21: 2 | U21: 70 | V21: 0 | W21: 0 | X21: 2 | Z21: 2 | AA21: 2 | AB21: 1 | AC21: 1 | AD21: 2 | AE21: 4 | AF21: 0 | AG21: 3 | AH21: 8 | AI21: 1
A22: 1614163 | B22: 4 | C22: 1 | D22: 30 | E22: 1040 | F22: 1994 | G22: 4 | H22: 1 | I22: 2165000000 | J22: 1800000000 | K22: 100 | L22: 15 | M22: 10 | N22: 720000000 | O22: 900000000 | P22: 10000000000 | Q22: 0 | R22: 1 | S22: 1 | T22: 2 | U22: 0 | V22: 0 | W22: 30 | X22: 1 | Y22: 100000000 | Z22: 2 | AA22: 2 | AB22: 1 | AC22: 3 | AD22: 1 | AE22: 0 | AF22: 0 | AG22: 3 | AH22: 2 | AI22: 1
A23: 1614165 | B23: 3 | C23: 2 | D23: 13 | E23: 1061 | F23: 2006 | G23: 22 | H23: 2.7846396 | I23: 600000000 | J23: 400000000 | K23: 90 | L23: 7 | M23: 8 | N23: 62400000 | O23: 40000000 | P23: 90000000 | Q23: 0 | S23: 1 | T23: 2 | U23: 100 | V23: 0 | W23: 0 | X23: 2 | Z23: 2 | AA23: 1 | AB23: 1 | AC23: 3 | AD23: 3 | AE23: 3 | AF23: 1 | AG23: 2 | AH23: 12 | AI23: 1
A24: 1614170 | B24: 1 | C24: 1 | D24: 15 | E24: 2511 | F24: 2009 | G24: 22 | H24: 316.3196 | I24: 800000000 | J24: 500000000 | K24: 90 | L24: 15 | M24: 7 | N24: 25000000 | O24: -9 | P24: -9 | Q24: 20 | S24: 1 | T24: 2 | U24: 60 | V24: 20 | W24: 0 | X24: 2 | Z24: 1 | AA24: 2 | AB24: 1 | AC24: 8 | AD24: 1 | AE24: 0 | AF24: 0 | AG24: 0 | AH24: 4 | AI24: 4
A25: 1614171 | B25: 3 | C25: 1 | D25: 10 | E25: 2511 | F25: 2007 | G25: 20 | H25: 90.16523 | I25: 70000000 | J25: 10000000 | K25: 70 | L25: 10 | M25: 3 | N25: 10000000 | O25: 30000000 | P25: 170000000 | Q25: 0 | S25: 2 | T25: 2 | U25: 90 | V25: 0 | W25: 0 | X25: 2 | Z25: 2 | AA25: 2 | AB25: 1 | AC25: 3 | AD25: 2 | AE25: 0 | AF25: 0 | AG25: 0 | AH25: 8 | AI25: 1
A26: 1614174 | B26: 4 | C26: 1 | D26: 6 | E26: 1811 | F26: 1997 | G26: 30 | H26: 18.668732 | I26: 15000000 | J26: 12000000 | K26: 100 | L26: 6 | M26: 6 | N26: 4000000 | O26: 5000000 | P26: 100000000 | Q26: 0 | S26: 2 | T26: 2 | U26: 50 | V26: 50 | W26: 0 | X26: 2 | Z26: 2 | AA26: 2 | AB26: 1 | AC26: 5 | AD26: 3 | AE26: 1 | AF26: 1 | AG26: 1 | AH26: 3 | AI26: 4
A27: 1614175 | B27: 4 | C27: 1 | D27: 8 | E27: 1811 | F27: 2006 | G27: 19 | H27: 18.668732 | I27: 29430000 | J27: 22570000 | K27: 70 | L27: 4 | M27: 4 | N27: 8046000 | O27: 17000000 | P27: 49570000 | Q27: 0 | S27: 2 | T27: 2 | U27: 60 | V27: 0 | W27: 10 | X27: 1 | Y27: 2460000 | Z27: 2 | AA27: 2 | AB27: 1 | AC27: 6 | AD27: 2 | AE27: 1 | AF27: 0 | AG27: 0 | AH27: 14 | AI27: 2
A28: 1614176 | B28: 1 | C28: 3 | D28: 100 | E28: 3100 | F28: 1987 | G28: 30 | H28: 2.6891484 | I28: 15000000000 | J28: 10000000000 | K28: 40 | L28: 40 | M28: 35 | N28: 2000000000 | O28: 500000000 | P28: 4000000000 | Q28: 0 | R28: 2 | S28: 2 | T28: 2 | U28: 100 | V28: 0 | W28: 0 | X28: 2 | Z28: 2 | AA28: 2 | AB28: 2 | AD28: 0 | AE28: 1 | AF28: 0 | AG28: 2 | AH28: 12 | AI28: 4
A29: 1614178 | B29: 1 | C29: 3 | D29: 10 | E29: 2599 | F29: 1984 | G29: 41 | H29: 1 | I29: 30000000 | J29: 40000000 | K29: 85 | L29: 7 | M29: 10 | N29: 4000000 | O29: 13000000 | P29: 35000000 | Q29: 0 | S29: 1 | T29: 2 | U29: 70 | V29: 30 | W29: 0 | X29: 2 | Z29: 1 | AA29: 2 | AB29: 1 | AC29: 3 | AD29: 1 | AE29: 1 | AF29: 1 | AG29: 2 | AH29: 14 | AI29: 1
A30: 1614179 | B30: 1 | C30: 3 | D30: 94 | E30: 2395 | F30: 2004 | G30: 20 | H30: 1.5225753 | I30: 2000000000 | J30: 1600000000 | K30: 76 | L30: 92 | M30: 76 | N30: -9 | O30: 500000000 | P30: 1800000000 | Q30: 0 | R30: 1 | S30: 1 | T30: 1 | U30: 100 | V30: 0 | W30: 0 | X30: 1 | Y30: 1800000000 | Z30: 2 | AA30: 2 | AB30: 1 | AC30: 10 | AD30: 3 | AE30: 1 | AF30: 0 | AG30: 2 | AH30: 8 | AI30: 1
A31: 1614180 | B31: 2 | C31: 2 | D31: 30 | E31: 1071 | F31: 2000 | G31: 30 | H31: 1.9028108 | I31: 800000000 | J31: 760000000 | K31: 10 | L31: 25 | M31: 27 | N31: 30000000 | O31: 450000000 | P31: 400000000 | Q31: 0 | R31: 1 | S31: 1 | T31: 1 | U31: 70 | V31: 0 | W31: 30 | X31: 1 | Y31: 200000000 | Z31: 2 | AA31: 2 | AB31: 1 | AC31: 0 | AD31: 2 | AE31: 2 | AF31: 3 | AG31: 2 | AH31: 4 | AI31: 2
A32: 1614182 | B32: 1 | C32: 1 | D32: 15 | E32: 2819 | F32: 2001 | G32: 15 | H32: 143.61815 | I32: -9 | J32: -9 | K32: 60 | L32: 20 | M32: 15 | N32: -9 | O32: -9 | P32: -9 | Q32: 0 | S32: 2 | T32: 2 | U32: 100 | V32: 0 | W32: 0 | X32: 1 | Y32: 0 | Z32: 2 | AA32: 2 | AB32: 1 | AC32: 8 | AD32: 4 | AE32: 4 | AF32: 0 | AG32: 4 | AH32: 1 | AI32: 3
A33: 1614183 | B33: 2 | C33: 2 | D33: 12 | E33: 1071 | F33: 2015 | G33: 10 | H33: 1.5243006 | I33: 217920000 | J33: -9 | K33: 2 | L33: 12 | M33: 24 | N33: 36950400 | O33: 172800000 | P33: 6000000 | Q33: 0 | S33: 1 | T33: 1 | U33: 80 | V33: 0 | W33: 20 | X33: 2 | Z33: 2 | AA33: 2 | AB33: 1 | AC33: 4 | AD33: 1 | AE33: 4 | AF33: 0 | AG33: 0 | AH33: 1 | AI33: 2
A34: 1614185 | B34: 1 | C34: 1 | D34: 7 | E34: 1811 | F34: 2000 | G34: 14 | H34: 157.86736 | I34: 30000000 | J34: 20000000 | K34: 90 | L34: 8 | M34: 2 | N34: 10000000 | O34: 15000000 | P34: 40000000 | Q34: 0 | S34: 2 | T34: 2 | U34: 20 | V34: 0 | W34: 70 | X34: 2 | Z34: 2 | AA34: 2 | AB34: 2 | AD34: 1 | AE34: 1 | AF34: 1 | AG34: 0 | AH34: 14 | AI34: 4
A35: 1614193 | B35: 3 | C35: 3 | D35: 300 | E35: 1061 | F35: 2009 | G35: 30 | H35: 1 | I35: 1200000000 | J35: 1000000000 | K35: 60 | L35: 300 | M35: 250 | N35: 200000000 | O35: 500000000 | P35: 600000000 | Q35: 30 | R35: 1 | S35: 2 | T35: 1 | U35: 60 | V35: 40 | W35: 0 | X35: 2 | Z35: 2 | AA35: 2 | AB35: 1 | AC35: 2 | AD35: 2 | AE35: 2 | AF35: 1 | AG35: 1 | AH35: 14 | AI35: 4
A36: 1614202 | B36: 2 | C36: 1 | D36: 5 | E36: 2511 | F36: 1996 | G36: 40 | H36: 68.62606 | I36: 12000000 | J36: -9 | K36: -9 | L36: 5 | M36: 6 | N36: -9 | O36: -9 | P36: 2500000 | Q36: 0 | S36: 1 | T36: 2 | U36: 20 | V36: 0 | W36: 80 | X36: 2 | Z36: 2 | AA36: 2 | AB36: -9 | AD36: 3 | AE36: 2 | AF36: 1 | AG36: 3 | AH36: 6 | AI36: 2
A37: 1614203 | B37: 1 | C37: 3 | D37: 55 | E37: 2599 | F37: 1956 | G37: 50 | H37: 1 | I37: 750000000 | J37: 500000000 | K37: 65 | L37: 53 | M37: 65 | N37: 50000000 | O37: 300000000 | P37: 350000000 | Q37: 0 | R37: 1 | S37: 1 | T37: 2 | U37: 70 | V37: 0 | W37: 0 | X37: 2 | Z37: 2 | AA37: 2 | AB37: 1 | AC37: 4 | AD37: 2 | AE37: 2 | AF37: 1 | AG37: 2 | AH37: 14 | AI37: 1
A38: 1614206 | B38: 4 | C38: 2 | D38: 6 | E38: 1811 | F38: 2010 | G38: 12 | H38: 1.8398361 | I38: 16450000 | J38: 8210000 | K38: 70 | L38: 4 | M38: 2 | N38: 2165000 | O38: 7000000 | P38: 70500000 | Q38: 0 | S38: 2 | T38: 2 | U38: 70 | V38: 0 | W38: 0 | X38: 2 | Z38: 2 | AA38: 2 | AB38: 1 | AC38: 5 | AD38: 1 | AE38: 2 | AF38: 3 | AG38: 1 | AH38: 13 | AI38: 2
A39: 1614208 | B39: 2 | C39: 1 | D39: 6 | E39: 1410 | F39: 2000 | G39: 25 | H39: 46.711292 | I39: 40000000 | J39: 15000000 | K39: 50 | L39: 6 | M39: 6 | N39: -9 | O39: 30000000 | P39: 11100000 | Q39: 0 | S39: 1 | T39: 1 | U39: 73 | V39: 0 | W39: 7 | X39: 1 | Y39: 2500000 | Z39: 1 | AA39: 1 | AB39: 1 | AC39: 3 | AD39: 3 | AE39: 0 | AF39: 0 | AG39: 0 | AH39: 6 | AI39: 2
A40: 1614212 | B40: 1 | C40: 1 | D40: 10 | E40: 1622 | F40: 2014 | G40: 10 | H40: 157.86736 | I40: 30000000 | J40: 15000000 | K40: 35 | L40: 5 | M40: 3 | N40: 10000000 | O40: 5000000 | P40: 60000000 | Q40: 0 | S40: 2 | T40: 2 | U40: 0 | V40: 0 | W40: 0 | X40: 2 | Z40: 2 | AA40: 2 | AB40: 2 | AD40: 0 | AE40: 0 | AF40: 0 | AG40: 3 | AH40: 12 | AI40: 2
A41: 1614213 | B41: 1 | C41: 3 | D41: 20 | E41: 1061 | F41: 2001 | G41: 15 | H41: 3.8174868 | I41: 2000000 | J41: -7 | K41: 10 | L41: 5 | M41: -7 | N41: -9 | O41: -9 | P41: -9 | Q41: 0 | R41: 2 | S41: 2 | T41: 2 | U41: 100 | V41: 0 | W41: 0 | X41: 2 | Z41: 2 | AA41: 2 | AB41: 1 | AC41: 6 | AD41: 0 | AE41: 3 | AF41: 0 | AG41: 4 | AH41: 1 | AI41: 2
A42: 1614215 | B42: 1 | C42: 3 | D42: 66 | E42: 1811 | F42: 1997 | G42: 13 | H42: 1 | I42: 5000000000 | J42: 2000000000 | K42: 100 | L42: 46 | M42: 38 | N42: 300000000 | O42: 1000000000 | P42: -9 | Q42: 0 | R42: 1 | S42: 2 | T42: 2 | U42: 40 | V42: 50 | W42: 10 | X42: 1 | Y42: 85000000 | Z42: 1 | AA42: 2 | AB42: 1 | AC42: 7 | AD42: 1 | AE42: 2 | AF42: 1 | AG42: 3 | AH42: 14 | AI42: 4
A43: 1614218 | B43: 1 | C43: 3 | D43: 6 | E43: 2511 | F43: 1984 | G43: 39 | H43: 1 | I43: -9 | J43: -9 | K43: 10 | L43: 5 | M43: 30 | N43: -9 | O43: -9 | P43: -9 | Q43: 0 | S43: 1 | T43: 2 | U43: 90 | V43: 0 | W43: 0 | X43: 2 | Z43: 1 | AA43: 2 | AB43: 1 | AC43: 4 | AD43: 4 | AE43: 3 | AF43: 1 | AG43: 3 | AH43: 8 | AI43: 4
A44: 1614219 | B44: 1 | C44: 1 | D44: 6 | E44: 1410 | F44: 1975 | G44: 50 | H44: 5.7243896 | I44: 3600000 | J44: 3000000 | K44: 50 | L44: 6 | M44: 6 | N44: 2000000 | O44: 3500000 | P44: 10000000 | Q44: 0 | S44: 1 | T44: 2 | U44: 60 | V44: 0 | W44: 0 | X44: 2 | Z44: 2 | AA44: 2 | AB44: 1 | AC44: 5 | AD44: 3 | AE44: 1 | AF44: 2 | AG44: 4 | AH44: 13 | AI44: 2
A45: 1614220 | B45: 1 | C45: 3 | D45: 500 | E45: 1103 | F45: 1951 | G45: 25 | H45: 1 | I45: 50000000000 | J45: 35000000000 | K45: 85 | L45: 500 | M45: 500 | N45: 2000000000 | O45: -9 | P45: -9 | Q45: 10 | R45: 1 | S45: 1 | T45: 2 | U45: 100 | V45: 0 | W45: 0 | X45: 2 | Z45: 2 | AA45: 2 | AB45: 1 | AC45: 10 | AD45: 2 | AE45: 0 | AF45: 0 | AG45: 3 | AH45: 14 | AI45: 2
A46: 1614222 | B46: 1 | C46: 3 | D46: 50 | E46: 2511 | F46: 1965 | G46: 17 | H46: 1 | I46: 1200000000 | J46: 3000000000 | K46: 80 | L46: 50 | M46: 60 | N46: 200000000 | O46: 100000000 | P46: -9 | Q46: 0 | R46: 1 | S46: 1 | T46: 2 | U46: 100 | V46: 0 | W46: 0 | X46: 1 | Y46: 109500000 | Z46: 2 | AA46: 2 | AB46: 1 | AC46: 10 | AD46: 1 | AE46: 1 | AF46: 0 | AG46: 2 | AH46: 14 | AI46: 1
A47: 1614223 | B47: 1 | C47: 1 | D47: 6 | E47: 1622 | F47: 2012 | G47: 28 | H47: 143.61815 | I47: -9 | J47: -9 | K47: 90 | L47: 4 | M47: 4 | N47: 1500000 | O47: 7000000 | P47: 1500000 | Q47: 75 | S47: 2 | T47: 2 | U47: 80 | V47: 0 | W47: 0 | X47: 1 | Y47: 450000 | Z47: 2 | AA47: 2 | AB47: 1 | AC47: 2 | AD47: 1 | AE47: 1 | AF47: 2 | AG47: 2 | AH47: 7 | AI47: 3
A48: 1614224 | B48: 3 | C48: 2 | D48: 14 | E48: 3312 | F48: 2005 | G48: 20 | H48: 1.148219 | I48: 50000000 | J48: 36000000 | K48: 10 | L48: 14 | M48: 5 | N48: 10000000 | O48: -9 | P48: 40000000 | Q48: 0 | S48: 2 | T48: 2 | U48: 0 | V48: 0 | W48: 0 | X48: 2 | Z48: 2 | AA48: 2 | AB48: 1 | AC48: 2 | AD48: 1 | AE48: 3 | AF48: 1 | AG48: 1 | AH48: 1 | AI48: 2
A49: 1614225 | B49: 2 | C49: 1 | D49: 6 | E49: 1061 | F49: 2018 | G49: 10 | H49: 11.033947 | I49: 25000000 | J49: 30000000 | K49: 100 | L49: 6 | M49: 6 | N49: 7200000 | O49: 5000000 | P49: 200000000 | Q49: 0 | S49: 2 | T49: 2 | U49: 80 | V49: 0 | W49: 0 | X49: 2 | Z49: 2 | AA49: 2 | AB49: 1 | AC49: 8 | AD49: 0 | AE49: 0 | AF49: 0 | AG49: 0 | AH49: 14 | AI49: 4
A50: 1614227 | B50: 2 | C50: 2 | D50: 15 | E50: 2599 | F50: 1997 | G50: 30 | H50: 5.2876315 | I50: 50000000 | J50: 100000000 | K50: 55 | L50: 7 | M50: 6 | N50: 11160000 | O50: 7000000 | P50: 7000000 | Q50: 0 | S50: 2 | T50: 2 | U50: 80 | V50: 0 | W50: 20 | X50: 2 | Z50: 2 | AA50: 2 | AB50: 1 | AC50: 7 | AD50: 2 | AE50: 1 | AF50: 1 | AG50: 1 | AH50: 2 | AI50: 2
A51: 1614229 | B51: 3 | C51: 1 | D51: 10 | E51: 1061 | F51: 2001 | G51: 24 | H51: 1.7984211 | I51: 182500000 | J51: 180000000 | K51: 100 | L51: 9 | M51: 8 | N51: 48000000 | O51: 70000000 | P51: 120000000 | Q51: 0 | S51: 2 | T51: 2 | U51: 70 | V51: 0 | W51: 0 | X51: 2 | Z51: 2 | AA51: 2 | AB51: 1 | AC51: 5 | AD51: 2 | AE51: 3 | AF51: 0 | AG51: 2 | AH51: 1 | AI51: 1
A52: 1614230 | B52: 1 | C52: 1 | D52: 8 | E52: 1410 | F52: 2010 | G52: 20 | H52: 189.57414 | I52: 34000000 | J52: 15000000 | K52: 30 | L52: 8 | M52: 4 | N52: 12000000 | O52: 30000000 | P52: 25000000 | Q52: 0 | S52: 2 | T52: 2 | U52: 50 | V52: 0 | W52: 20 | X52: 1 | Y52: 550000 | Z52: 2 | AA52: 2 | AB52: 1 | AC52: 3 | AD52: 2 | AE52: 4 | AF52: 0 | AG52: 4 | AH52: 1 | AI52: 2
A53: 1614231 | B53: 3 | C53: 2 | D53: 120 | E53: 1071 | F53: 2002 | G53: 20 | H53: 1.356841 | I53: 700000000 | J53: 600000000 | K53: 70 | L53: 128 | M53: 128 | N53: 460800000 | O53: 300000000 | P53: 1000000000 | Q53: 0 | R53: 1 | S53: 1 | T53: 2 | U53: 80 | V53: 0 | W53: 20 | X53: 2 | Z53: 2 | AA53: 2 | AB53: 1 | AC53: 2 | AD53: 4 | AE53: 0 | AF53: 0 | AG53: 4 | AH53: 12 | AI53: 1
A54: 1614236 | B54: 2 | C54: 1 | D54: 7 | E54: 2511 | F54: 2012 | G54: 10 | H54: 68.62606 | I54: 30000000 | J54: 25000000 | K54: 75 | L54: 6 | M54: 3 | N54: 12000000 | O54: 12000000 | P54: 15000000 | Q54: 0 | S54: 1 | T54: 2 | U54: 30 | V54: 0 | W54: 25 | X54: 1 | Y54: 1500000 | Z54: 1 | AA54: 2 | AB54: 1 | AC54: 15 | AD54: 3 | AE54: 3 | AF54: 3 | AG54: 3 | AH54: 14 | AI54: 4
A55: 1614238 | B55: 1 | C55: 3 | D55: 800 | E55: 1410 | F55: 2014 | G55: 40 | H55: 1 | I55: 26310000000 | J55: 22700000000 | K55: 87 | L55: 800 | M55: 800 | N55: 2000000000 | O55: 1500000000 | P55: 27000000000 | Q55: 15 | R55: 1 | S55: 1 | T55: 1 | U55: 80 | V55: 0 | W55: 0 | X55: 2 | Z55: 2 | AA55: 2 | AB55: 1 | AC55: 25 | AD55: 2 | AE55: 1 | AF55: 3 | AG55: 3 | AH55: 9 | AI55: 1
A56: 1614246 | B56: 3 | C56: 1 | D56: 15 | E56: 3100 | F56: 1986 | G56: 15 | H56: 61.413673 | I56: 45000000 | J56: 33000000 | K56: 70 | L56: 10 | M56: 10 | N56: 15000000 | O56: 20000000 | P56: 100000000 | Q56: 0 | S56: 2 | T56: 2 | U56: 100 | V56: 0 | W56: 0 | X56: 1 | Y56: 15000000 | Z56: 1 | AA56: 1 | AB56: 1 | AC56: 3 | AD56: 3 | AE56: 3 | AF56: 2 | AG56: 3 | AH56: 8 | AI56: 4
A57: 1614254 | B57: 3 | C57: 1 | D57: 7 | E57: 1410 | F57: 1995 | G57: 30 | H57: 55.69917 | I57: 50000000 | J57: 20000000 | K57: 100 | L57: 7 | M57: 4 | N57: 5000000 | O57: 30000000 | P57: 57000000 | Q57: 0 | S57: 2 | T57: 2 | U57: 70 | V57: 0 | W57: 0 | X57: 2 | Z57: 1 | AA57: 2 | AB57: 1 | AC57: 7 | AD57: 0 | AE57: 0 | AF57: 0 | AG57: 2 | AH57: 2 | AI57: 1
A58: 1614255 | B58: 3 | C58: 2 | D58: 25 | E58: 1520 | F58: 2003 | G58: 25 | H58: 1.148219 | I58: 200000000 | J58: 150000000 | K58: 80 | L58: 25 | M58: 25 | N58: 40000000 | O58: 60000000 | P58: 400000000 | Q58: 0 | R58: 1 | S58: 1 | T58: 2 | U58: 40 | V58: 0 | W58: 0 | X58: 1 | Y58: -9 | Z58: 1 | AA58: 1 | AB58: 1 | AC58: 2 | AD58: 2 | AE58: 3 | AF58: 0 | AG58: 3 | AH58: 1 | AI58: 4
A59: 1614256 | B59: 3 | C59: 3 | D59: 262 | E59: 2599 | F59: 1983 | G59: 1 | H59: 1 | I59: 18000000 | J59: 4000000 | K59: 80 | L59: 262 | M59: 262 | N59: -9 | O59: 14000000 | P59: 10000000 | Q59: 0 | R59: 1 | S59: 1 | T59: 2 | U59: 0 | V59: 0 | W59: 0 | X59: 2 | Z59: 2 | AA59: 2 | AB59: 1 | AC59: 10 | AD59: 2 | AE59: 2 | AF59: 0 | AG59: 1 | AH59: 14 | AI59: 4
A60: 1614258 | B60: 1 | C60: 2 | D60: 12 | E60: 3220 | F60: 2005 | G60: 35 | H60: 53.75954 | I60: 20000000 | J60: 15000000 | K60: 50 | L60: 6 | M60: 5 | N60: 8000000 | O60: 3000000 | P60: 50000000 | Q60: 0 | S60: 2 | T60: 1 | U60: 90 | V60: 0 | W60: 0 | X60: 2 | Z60: 2 | AA60: 2 | AB60: 1 | AC60: 5 | AD60: 2 | AE60: 4 | AF60: 1 | AG60: 0 | AH60: 1 | AI60: 2
A61: 1614260 | B61: 3 | C61: 1 | D61: 8 | E61: 1622 | F61: 2012 | G61: 20 | H61: 72.49169 | I61: 40000000 | J61: 30000000 | K61: 40 | L61: 8 | M61: 8 | N61: 19000000 | O61: 15000000 | P61: 10000000 | Q61: 0 | S61: 1 | T61: 2 | U61: 60 | V61: 0 | W61: 0 | X61: 2 | Z61: 1 | AA61: 1 | AB61: 1 | AC61: 10 | AD61: 4 | AE61: 2 | AF61: 1 | AG61: 3 | AH61: 8 | AI61: 4
A62: 1614261 | B62: 3 | C62: 2 | D62: 6 | E62: 1061 | F62: 2009 | G62: 16 | H62: 1.4072497 | I62: 38000000 | J62: 42000000 | K62: 55 | L62: 6 | M62: 6 | N62: 18000000 | O62: 27000000 | P62: 20000000 | Q62: 0 | S62: 2 | T62: 2 | U62: 80 | V62: 0 | W62: 0 | X62: 2 | Z62: 2 | AA62: 2 | AB62: 1 | AC62: 5 | AD62: 3 | AE62: 1 | AF62: 0 | AG62: 1 | AH62: 8 | AI62: 2
A63: 1614267 | B63: 4 | C63: 2 | D63: 16 | E63: 1040 | F63: 2015 | G63: 10 | H63: 24.62111 | I63: 120000000 | J63: 100000000 | K63: 80 | L63: 16 | M63: 5 | N63: 50000000 | O63: 60000000 | P63: 150000000 | Q63: 0 | S63: 2 | T63: 2 | U63: 20 | V63: 0 | W63: 20 | X63: 2 | Z63: 2 | AA63: 2 | AB63: 1 | AC63: 1 | AD63: 1 | AE63: 1 | AF63: 1 | AG63: 3 | AH63: 14 | AI63: 4
A64: 1614268 | B64: 1 | C64: 3 | D64: 250 | E64: 2392 | F64: 2000 | G64: 30 | H64: 1 | I64: 8000000000 | J64: 2000000000 | K64: 80 | L64: 350 | M64: 150 | N64: 500000000 | O64: 2000000000 | P64: 30000000000 | Q64: 0 | R64: 1 | S64: 1 | T64: 2 | U64: 50 | V64: 0 | W64: 50 | X64: 2 | Z64: 2 | AA64: 2 | AB64: 1 | AC64: 4 | AD64: 1 | AE64: 0 | AF64: 0 | AG64: 3 | AH64: 12 | AI64: 4
A65: 1614271 | B65: 4 | C65: 1 | D65: 40 | E65: 1061 | F65: 2009 | G65: 10 | H65: 2.100839 | I65: 150000000 | J65: 100000000 | K65: 100 | L65: 40 | M65: 10 | N65: 48000000 | O65: 24000000 | P65: 10000000 | Q65: 0 | R65: 1 | S65: 2 | T65: 2 | U65: 80 | V65: 20 | W65: 0 | X65: 2 | Z65: 1 | AA65: 1 | AB65: 1 | AC65: 2 | AD65: 3 | AE65: 3 | AF65: 1 | AG65: 3 | AH65: 8 | AI65: 2
A66: 1614276 | B66: 3 | C66: 2 | D66: 30 | E66: 1101 | F66: 2004 | G66: 8 | H66: 1.3494371 | I66: 1000000000 | J66: 900000000 | K66: 90 | L66: 26 | M66: 26 | N66: 180000000 | O66: 150000000 | P66: 200000000 | Q66: 0 | R66: 1 | S66: 2 | T66: 1 | U66: 100 | V66: 0 | W66: 0 | X66: 2 | Z66: 2 | AA66: 2 | AB66: 1 | AC66: 12 | AD66: 2 | AE66: 0 | AF66: 0 | AG66: 0 | AH66: 8 | AI66: 1
A67: 1614277 | B67: 1 | C67: 2 | D67: 115 | E67: 1410 | F67: 1991 | G67: 35 | H67: 42.939556 | I67: 2115600000 | J67: 2227885000 | K67: 100 | L67: 115 | M67: 35 | N67: 170000000 | O67: 1370000000 | P67: 3000000000 | Q67: 0 | R67: 1 | S67: 1 | T67: 2 | U67: 50 | V67: 0 | W67: 0 | X67: 2 | Z67: 1 | AA67: 2 | AB67: 1 | AC67: 7 | AD67: 3 | AE67: 3 | AF67: 1 | AG67: 1 | AH67: 1 | AI67: 1
A68: 1614280 | B68: 3 | C68: 2 | D68: 5 | E68: 1061 | F68: 1987 | G68: 25 | H68: 1.4072497 | I68: 42000000 | J68: 38000000 | K68: 42 | L68: 5 | M68: 5 | N68: 18000000 | O68: 23000000 | P68: 15420000 | Q68: 0 | S68: 2 | T68: 2 | U68: 95 | V68: 0 | W68: 0 | X68: 2 | Z68: 2 | AA68: 2 | AB68: 1 | AC68: 5 | AD68: 2 | AE68: 4 | AF68: 1 | AG68: 4 | AH68: 1 | AI68: 2
A69: 1614283 | B69: 1 | C69: 3 | D69: 200 | E69: 1101 | F69: 2000 | G69: 25 | H69: 1 | I69: 700000000 | J69: 650000000 | K69: 90 | L69: 180 | M69: 50 | N69: 200000000 | O69: 400000000 | P69: 1000000000 | Q69: 0 | R69: 1 | S69: 2 | T69: 2 | U69: 40 | V69: 0 | W69: 50 | X69: 2 | Z69: 2 | AA69: 2 | AB69: 2 | AD69: 1 | AE69: 1 | AF69: 1 | AG69: 1 | AH69: 2 | AI69: 4
A70: 1614286 | B70: 1 | C70: 3 | D70: 50 | E70: 1101 | F70: 2013 | G70: 15 | H70: 1 | I70: 3000000000 | J70: 1500000000 | K70: 45 | L70: 50 | M70: 45 | N70: 500000000 | O70: 300000000 | P70: 1000000000 | Q70: 25 | R70: 2 | S70: 2 | T70: 2 | U70: 80 | V70: 0 | W70: 0 | X70: 2 | Z70: 2 | AA70: 2 | AB70: 2 | AD70: 0 | AE70: 0 | AF70: 0 | AG70: 2 | AH70: 13 | AI70: 2
A71: 1614289 | B71: 3 | C71: 2 | D71: 60 | E71: 1079 | F71: 1954 | G71: 10 | H71: 1.356841 | I71: 6000000000 | J71: 5000000000 | K71: 100 | L71: 45 | M71: 42 | N71: 420000000 | O71: 500000000 | P71: 1000000 | Q71: 80 | R71: 1 | S71: 2 | T71: 2 | U71: 60 | V71: 0 | W71: 10 | X71: 2 | Z71: 2 | AA71: 2 | AB71: 1 | AC71: 3 | AD71: 3 | AE71: 3 | AF71: 0 | AG71: 0 | AH71: 1 | AI71: 1
A72: 1614293 | B72: 2 | C72: 3 | D72: 100 | E72: 1079 | F72: 1994 | G72: 5 | H72: 1.3089461 | I72: 36000000000 | J72: 30000000000 | K72: 100 | L72: 100 | M72: 90 | N72: 3000000000 | O72: 1000000000 | P72: 2000000000 | Q72: 20 | R72: 1 | S72: 2 | T72: 2 | U72: 60 | V72: 20 | W72: 20 | X72: 1 | Y72: 5000000000 | Z72: 1 | AA72: 2 | AB72: 1 | AC72: 5 | AD72: 1 | AE72: 1 | AF72: 1 | AG72: 0 | AH72: 5 | AI72: 4
A73: 1614300 | B73: 4 | C73: 1 | D73: 9 | E73: 2511 | F73: 2010 | G73: 16 | H73: 18.668732 | I73: 86500000 | J73: 41300000 | K73: 60 | L73: 4 | M73: 3 | N73: 8530000 | O73: 39540000 | P73: 200570000 | Q73: 0 | S73: 2 | T73: 2 | U73: 70 | V73: 0 | W73: 10 | X73: 2 | Z73: 2 | AA73: 2 | AB73: 1 | AC73: 7 | AD73: 2 | AE73: 1 | AF73: 0 | AG73: 0 | AH73: 13 | AI73: 2
A74: 1614305 | B74: 1 | C74: 3 | D74: 24 | E74: 1071 | F74: 2008 | G74: -9 | H74: 3.8174868 | I74: 650000000 | J74: 430000000 | K74: 100 | L74: 24 | M74: 21 | N74: 162500000 | O74: 350000000 | P74: -9 | Q74: 0 | R74: 2 | S74: 2 | T74: 2 | U74: 70 | V74: 0 | W74: 30 | X74: 2 | Z74: 2 | AA74: 2 | AB74: 1 | AC74: 1 | AD74: 1 | AE74: 1 | AF74: 0 | AG74: 2 | AH74: 12 | AI74: 4
A75: 1614307 | B75: 1 | C75: 2 | D75: 5 | E75: 3312 | F75: 2002 | G75: 40 | H75: 416.63913 | I75: 600000000 | J75: 700000000 | K75: 70 | L75: 4 | M75: 6 | N75: 50000000 | O75: 200000000 | P75: 500000000 | Q75: 0 | S75: 2 | T75: 2 | U75: 70 | V75: 30 | W75: 0 | X75: 1 | Y75: 100000000 | Z75: 1 | AA75: 1 | AB75: 1 | AC75: 2 | AD75: 1 | AE75: 1 | AF75: 0 | AG75: 1 | AH75: 12 | AI75: 1
A76: 1614309 | B76: 2 | C76: 1 | D76: 9 | E76: 1061 | F76: 2002 | G76: -9 | H76: 11.033947 | I76: 48000000 | J76: -9 | K76: 80 | L76: 9 | M76: -9 | N76: 24000000 | O76: 10000000 | P76: 50000000 | Q76: 0 | S76: 2 | T76: 1 | U76: 90 | V76: 0 | W76: 0 | X76: 2 | Z76: 2 | AA76: 2 | AB76: 1 | AC76: 2 | AD76: 1 | AE76: 1 | AF76: 1 | AG76: 1 | AH76: 14 | AI76: 2
A77: 1614310 | B77: 3 | C77: 2 | D77: 80 | E77: 1511 | F77: 1995 | G77: 20 | H77: 1.289522 | I77: 5483616000 | J77: 2000000000 | K77: 30 | L77: 200 | M77: 150 | N77: 300000000 | O77: 500000000 | P77: 300000000 | Q77: 100 | R77: 2 | S77: 2 | T77: 2 | U77: 0 | V77: 0 | W77: 0 | X77: 2 | Z77: 1 | AA77: 2 | AB77: 1 | AC77: 5 | AD77: 3 | AE77: 2 | AF77: 3 | AG77: 4 | AH77: 4 | AI77: 4
A78: 1614312 | B78: 3 | C78: 1 | D78: 13 | E78: 1071 | F78: 2010 | G78: 15 | H78: 7.837092 | I78: 400000000 | J78: 350000000 | K78: 90 | L78: 7 | M78: 7 | N78: 39000000 | O78: 80000000 | P78: 90000000 | Q78: 0 | S78: 1 | T78: 2 | U78: 80 | V78: 0 | W78: 0 | X78: 2 | Z78: 2 | AA78: 2 | AB78: 1 | AC78: 5 | AD78: 3 | AE78: 3 | AF78: 2 | AG78: 3 | AH78: 8 | AI78: 1
A79: 1614314 | B79: 1 | C79: 1 | D79: 6 | E79: 2591 | F79: 2004 | G79: 21 | H79: 157.86736 | I79: 10000000 | J79: 4000000 | K79: 100 | L79: 6 | M79: 8 | N79: 4000000 | O79: -9 | P79: 25000000 | Q79: 0 | S79: 1 | T79: 1 | U79: 68 | V79: 0 | W79: 0 | X79: 1 | Y79: 15000000 | Z79: 2 | AA79: 1 | AB79: 1 | AC79: 8 | AD79: 4 | AE79: 3 | AF79: 2 | AG79: 2 | AH79: 1 | AI79: 1
A80: 1614316 | B80: 2 | C80: 2 | D80: 20 | E80: 1050 | F80: 2016 | G80: -9 | H80: 1.5243006 | I80: -9 | J80: -9 | K80: 80 | L80: 15 | M80: -9 | N80: 142800000 | O80: -9 | P80: 500000000 | Q80: 0 | R80: 1 | S80: 1 | T80: 1 | U80: 100 | V80: 0 | W80: 0 | X80: 1 | Y80: 6000000 | Z80: 2 | AA80: 2 | AB80: 1 | AC80: 4 | AD80: 2 | AE80: 1 | AF80: 1 | AG80: 3 | AH80: 1 | AI80: 2
A81: 1614317 | B81: 3 | C81: 1 | D81: 7 | E81: 1062 | F81: 2019 | G81: 5 | H81: 1.7984211 | I81: 24000000 | J81: 20000000 | K81: 70 | L81: 7 | M81: 4 | N81: 10000000 | O81: 5000000 | P81: 15000000 | Q81: 0 | S81: 2 | T81: 2 | U81: 30 | V81: 70 | W81: 0 | X81: 2 | Z81: 1 | AA81: 2 | AB81: 1 | AC81: 4 | AD81: 3 | AE81: 3 | AF81: 0 | AG81: 3 | AH81: 8 | AI81: 1
A82: 1614319 | B82: 2 | C82: 2 | D82: 20 | E82: 2022 | F82: 2017 | G82: 6 | H82: 2.6198342 | I82: 210000000 | J82: 180000000 | K82: 40 | L82: 10 | M82: 5 | N82: 50000000 | O82: 150000000 | P82: 100000000 | Q82: 0 | R82: 1 | S82: 1 | T82: 1 | U82: 20 | V82: 20 | W82: 10 | X82: 1 | Y82: 0 | Z82: 1 | AA82: 1 | AB82: 1 | AC82: 3 | AD82: 2 | AE82: 3 | AF82: 2 | AG82: 4 | AH82: 12 | AI82: 2
A83: 1614321 | B83: 3 | C83: 2 | D83: 150 | E83: 1061 | F83: 2005 | G83: 20 | H83: 1.6103765 | I83: 15000000000 | J83: 25000000000 | K83: 50 | L83: 100 | M83: 150 | N83: 300000000 | O83: 11000000000 | P83: 80000000 | Q83: 0 | R83: 1 | S83: 2 | T83: 2 | U83: 100 | V83: 0 | W83: 0 | X83: 2 | Z83: 1 | AA83: 2 | AB83: 1 | AC83: 1 | AD83: 0 | AE83: 1 | AF83: 0 | AG83: 1 | AH83: 7 | AI83: 4
A84: 1614322 | B84: 3 | C84: 3 | D84: 350 | E84: 2394 | F84: 2018 | G84: 37 | H84: 1 | I84: 12000000000 | J84: 10000000000 | K84: 40 | L84: 350 | M84: 350 | N84: 1000000000 | O84: 2500000000 | P84: 4000000000 | Q84: 0 | R84: 1 | S84: 2 | T84: 2 | U84: 100 | V84: 0 | W84: 0 | X84: 2 | Z84: 2 | AA84: 2 | AB84: 1 | AC84: 4 | AD84: 3 | AE84: 1 | AF84: 0 | AG84: 0 | AH84: 8 | AI84: 2
A85: 1614327 | B85: 1 | C85: 2 | D85: 10 | E85: 1811 | F85: 2000 | G85: 20 | H85: 48.349552 | I85: 30000000 | J85: 8000000 | K85: 89 | L85: 8 | M85: 2 | N85: 15000000 | O85: 6000000 | P85: 50000000 | Q85: 0 | S85: 1 | T85: 2 | U85: 50 | V85: 0 | W85: 2 | X85: 2 | Z85: 2 | AA85: 2 | AB85: 2 | AD85: 0 | AE85: 1 | AF85: 0 | AG85: 1 | AH85: 4 | AI85: 4
A86: 1614329 | B86: 3 | C86: 2 | D86: 6 | E86: 3100 | F86: 2010 | G86: 15 | H86: 1.6637996 | I86: 250000000 | J86: 230000000 | K86: 90 | L86: 5 | M86: 5 | N86: 25200000 | O86: 30000000 | P86: 60000000 | Q86: 0 | S86: 2 | T86: 2 | U86: 90 | V86: 0 | W86: 0 | X86: 2 | Z86: 2 | AA86: 2 | AB86: 2 | AD86: 2 | AE86: 2 | AF86: 0 | AG86: 3 | AH86: 12 | AI86: 1
A87: 1614330 | B87: 2 | C87: 2 | D87: 11 | E87: 2511 | F87: 2007 | G87: 18 | H87: 2.6198342 | I87: 650000000 | J87: 470000000 | K87: 90 | L87: 7 | M87: 7 | N87: 85800000 | O87: 50000000 | P87: 70000000 | Q87: 0 | S87: 1 | T87: 1 | U87: 80 | V87: 0 | W87: 0 | X87: 2 | Z87: 2 | AA87: 2 | AB87: 1 | AC87: 4 | AD87: 4 | AE87: 3 | AF87: 2 | AG87: 2 | AH87: 8 | AI87: 1
A88: 1614332 | B88: 1 | C88: 3 | D88: 51 | E88: 2720 | F88: 1967 | G88: 28 | H88: 1.574964 | I88: 500000000 | J88: 300000000 | K88: 95 | L88: 51 | M88: 15 | N88: 150000000 | O88: 250000000 | P88: 700000000 | Q88: 0 | R88: 1 | S88: 2 | T88: 2 | U88: 50 | V88: 0 | W88: 35 | X88: 2 | Z88: 2 | AA88: 2 | AB88: 1 | AC88: 2 | AD88: 1 | AE88: 1 | AF88: 1 | AG88: 0 | AH88: 14 | AI88: 4
A89: 1614337 | B89: 1 | C89: 3 | D89: 1500 | E89: 1410 | F89: 2015 | G89: 8 | H89: 1.574964 | I89: 32000000000 | J89: 30000000000 | K89: 76 | L89: 1500 | M89: 1350 | N89: 300000000 | O89: 21000000000 | P89: 55000000000 | Q89: 30 | R89: 1 | S89: 1 | T89: 2 | U89: 40 | V89: 20 | W89: 10 | X89: 2 | Z89: 1 | AA89: 2 | AB89: 1 | AC89: 5 | AD89: 4 | AE89: 3 | AF89: 1 | AG89: 0 | AH89: 8 | AI89: 4
A90: 1614340 | B90: 3 | C90: 2 | D90: 40 | E90: 1079 | F90: 1988 | G90: 39 | H90: 1.6103765 | I90: 120000000 | J90: 90000000 | K90: 60 | L90: 30 | M90: 25 | N90: 36000000 | O90: 31000000 | P90: 200000000 | Q90: 0 | R90: 1 | S90: 2 | T90: 2 | U90: 80 | V90: 20 | W90: 0 | X90: 1 | Y90: 20000000 | Z90: 1 | AA90: 2 | AB90: 1 | AC90: 4 | AD90: 4 | AE90: 3 | AF90: 1 | AG90: 3 | AH90: 12 | AI90: 1
A91: 1614341 | B91: 1 | C91: 3 | D91: 43 | E91: 2220 | F91: 1997 | G91: 27 | H91: 1.574964 | I91: 650000000 | J91: 450000000 | K91: 95 | L91: 35 | M91: 20 | N91: 25000000 | O91: 300000000 | P91: 180000000 | Q91: 20 | R91: 1 | S91: 2 | T91: 1 | U91: 60 | V91: 40 | W91: 0 | X91: 1 | Y91: 180000000 | Z91: 1 | AA91: 2 | AB91: 1 | AC91: 9 | AD91: 0 | AE91: 0 | AF91: 0 | AG91: 2 | AH91: 13 | AI91: 1
A92: 1614342 | B92: 2 | C92: 2 | D92: 150 | E92: 1030 | F92: 2008 | G92: 17 | H92: 2.6198342 | I92: 36000000000 | J92: 35000000000 | K92: 80 | L92: 45 | M92: 45 | N92: 900000000 | O92: -9 | P92: -9 | Q92: 0 | R92: 1 | S92: 1 | T92: 2 | U92: -9 | V92: -9 | W92: -9 | X92: 2 | Z92: 1 | AA92: 2 | AB92: 1 | AC92: -9 | AD92: 0 | AE92: -9 | AF92: 1 | AG92: -7 | AH92: 8 | AI92: 4
A93: 1614344 | B93: 1 | C93: 2 | D93: 15 | E93: 1080 | F93: 2013 | G93: 20 | H93: 23.458492 | I93: 80000000 | J93: 65000000 | K93: 75 | L93: 15 | M93: 5 | N93: 25000000 | O93: 40000000 | P93: 200000000 | Q93: 0 | S93: 2 | T93: 2 | U93: 70 | V93: 0 | W93: 30 | X93: 2 | Z93: 2 | AA93: 2 | AB93: 1 | AC93: 3 | AD93: 1 | AE93: 0 | AF93: 0 | AG93: 1 | AH93: 14 | AI93: 4
A94: 1614346 | B94: 2 | C94: 3 | D94: 520 | E94: 1079 | F94: 1969 | G94: 15 | H94: 1.3089461 | I94: 9400000000 | J94: 21000000000 | K94: 100 | L94: 266 | M94: 316 | N94: 750000000 | O94: 2600000000 | P94: 15000000000 | Q94: 90 | R94: 1 | S94: 2 | T94: 2 | U94: 70 | V94: 0 | W94: 30 | X94: 2 | Z94: 1 | AA94: 2 | AB94: 1 | AC94: 8 | AD94: 4 | AE94: 3 | AF94: 1 | AG94: -7 | AH94: 8 | AI94: 1
A95: 1614348 | B95: 2 | C95: 3 | D95: 300 | E95: 1050 | F95: 2014 | G95: 26 | H95: 1.261686 | I95: 82800000000 | J95: -9 | K95: 25 | L95: 20 | M95: 20 | N95: -9 | O95: 46800000000 | P95: 50000000000 | Q95: 20 | R95: 1 | S95: 2 | T95: 1 | U95: 100 | V95: 0 | W95: 0 | X95: 1 | Y95: 0 | Z95: 2 | AA95: 2 | AB95: 1 | AC95: 4 | AD95: 1 | AE95: 1 | AF95: 2 | AG95: -7 | AH95: 14 | AI95: 2
A96: 1614349 | B96: 3 | C96: 1 | D96: 15 | E96: 1629 | F96: 2017 | G96: 17 | H96: 68.51382 | I96: 6000000 | J96: 2000000 | K96: 40 | L96: 15 | M96: 9 | N96: 3000000 | O96: 4000000 | P96: 28000000 | Q96: 0 | S96: 2 | T96: 1 | U96: 100 | V96: 0 | W96: 0 | X96: 2 | Z96: 2 | AA96: 2 | AB96: 1 | AC96: 10 | AD96: 3 | AE96: 2 | AF96: 0 | AG96: 4 | AH96: 8 | AI96: 4
A97: 1614352 | B97: 2 | C97: 2 | D97: 7 | E97: 2511 | F97: 2013 | G97: 12 | H97: 2.6198342 | I97: 575000000 | J97: 300000000 | K97: 90 | L97: 9 | M97: 9 | N97: 42000000 | O97: 45000000 | P97: 30000000 | Q97: 0 | S97: 1 | T97: 2 | U97: 70 | V97: 0 | W97: 0 | X97: 2 | Z97: 2 | AA97: 2 | AB97: 1 | AC97: 3 | AD97: 4 | AE97: 4 | AF97: 2 | AG97: 3 | AH97: 8 | AI97: 1
A98: 1614354 | B98: 3 | C98: 2 | D98: 140 | E98: 2511 | F98: 2010 | G98: 25 | H98: 1.6637996 | I98: 900000000 | J98: 1100000000 | K98: 60 | L98: 140 | M98: 132 | N98: 300000000 | O98: 500000000 | P98: 150000000 | Q98: 0 | R98: 1 | S98: 2 | T98: 2 | U98: 98 | V98: 0 | W98: 2 | X98: 2 | Z98: 2 | AA98: 2 | AB98: 1 | AC98: 8 | AD98: 3 | AE98: 2 | AF98: 0 | AG98: 1 | AH98: 8 | AI98: 4
A99: 1614355 | B99: 4 | C99: 2 | D99: 15 | E99: 2599 | F99: 2013 | G99: 12 | H99: 2.642569 | I99: 2700000000 | J99: 1300000000 | K99: 60 | L99: 15 | M99: 15 | N99: 500000000 | O99: 800000000 | P99: 3000000000 | Q99: 0 | S99: 2 | T99: 2 | U99: 95 | V99: 0 | W99: 0 | X99: 2 | Z99: 2 | AA99: 2 | AB99: 2 | AD99: 2 | AE99: 0 | AF99: 0 | AG99: 0 | AH99: 8 | AI99: 4
A100: 1614359 | B100: 1 | C100: 2 | D100: 500 | E100: 1072 | F100: 2012 | G100: 20 | H100: 23.458492 | I100: 1200000000 | J100: 950000000 | K100: 35 | L100: 205 | M100: 200 | N100: 300000000 | O100: 100000000 | P100: -9 | Q100: 0 | R100: 1 | S100: 1 | T100: 2 | U100: 90 | V100: 5 | W100: 0 | X100: 2 | Z100: 2 | AA100: 2 | AB100: 1 | AC100: 5 | AD100: 2 | AE100: 3 | AF100: 1 | AG100: 1 | AH100: 1 | AI100: 4
...

Sheet Clean_Working
A1: Establishment_ID | B1: Region | C1: Size_Category | D1: Screener_Employees | E1: ISIC_Rev4_Code | F1: ISIC_Division | G1: Manufacturing_Subsector | H1: Year_Started | I1: Manager_Experience_Years | J1: Survey_Weight_Median | K1: Annual_Sales_2024_UGX | L1: Annual_Sales_2022_UGX | M1: Capacity_Utilization_Pct | N1: Permanent_FT_Employees_2024 | O1: Permanent_FT_Employees_2022 | P1: Labor_Cost_2024_UGX | Q1: Raw_Materials_Cost_2024_UGX | R1: Machinery_Replacement_Value_UGX | S1: Direct_Exports_Pct | T1: Monitors_Performance_Indicators | U1: Introduced_New_Product_Service | V1: Introduced_Improved_Process | W1: Working_Capital_Internal_Pct | X1: Working_Capital_Bank_Pct | Y1: Working_Capital_Supplier_Credit_Pct | Z1: Purchased_Fixed_Assets | AA1: Equipment_Investment_Raw_UGX | AB1: Has_Financial_Institution_Loan | AC1: Applied_For_Loan_2024 | AD1: Experienced_Power_Outages | AE1: Power_Outages_Per_Month_Raw | AF1: Electricity_Obstacle | AG1: Access_to_Finance_Obstacle | AH1: Workforce_Skills_Obstacle | AI1: Informal_Competition_Obstacle | AJ1: Biggest_Obstacle | AK1: Figures_Response_Quality | AL1: Establishment_Age_Years | AM1: Equipment_Investment_UGX | AN1: Power_Outages_Per_Month | AO1: Direct_Exporter | AP1: Sales_Growth_2022_2024_Pct | AQ1: Sales_CAGR_2022_2024_Pct | AR1: Employment_Growth_2022_2024_Pct | AS1: Sales_per_Employee_UGX | AT1: Labor_Cost_Pct_of_Sales | AU1: Raw_Materials_Cost_Pct_of_Sales | AV1: Machinery_Value_per_Employee_UGX | AW1: Equipment_Investment_Pct_of_Sales | AX1: Sales_Outlier_Flag | AY1: Firm_Age_Band | AZ1: Performance_Group
A2: 1614120 | B2: Eastern | C2: Large | D2: 1000 | E2: 1073 | F2: 10 | G2: Manufacture of food products | H2: 1986 | I2: 24 | J2: 1 | K2: 1200000000 | L2: 900000000 | M2: 20 | N2: 250 | O2: 180 | P2: 500000000 | Q2: 200000000 | R2: 350000000 | S2: 25 | T2: Yes | U2: No | V2: No | W2: 85 | X2: 0 | Y2: 0 | Z2: No | AB2: No | AC2: No | AD2: Yes | AE2: 6 | AF2: Moderate obstacle | AG2: Major obstacle | AH2: Moderate obstacle | AI2: Moderate obstacle | AJ2: Tax rates | AK2: Are in some case taken from books and in some case estimates | AL2: =IF(H2="","",2024-H2) -> 38 | AM2: =IFERROR(IF(Z2="No",0,IF(Z2="Yes",AA2,"")),"") -> 0 | AN2: =IFERROR(IF(AD2="No",0,IF(AD2="Yes",AE2,"")),"") -> 6 | AO2: =IF(S2>0,"Yes","No") -> Yes | AP2: =IF(OR(K2="",L2="",L2<=0),"",K2/L2-1) -> 0.33333333 | AQ2: =IF(OR(K2="",L2="",L2<=0),"",(K2/L2)^(1/2)-1) -> 0.15470054 | AR2: =IF(OR(N2="",O2="",O2<=0),"",N2/O2-1) -> 0.38888889 | AS2: =IF(OR(K2="",N2="",N2<=0),"",K2/N2) -> 4800000 | AT2: =IF(OR(P2="",K2="",K2<=0),"",P2/K2) -> 0.41666667 | AU2: =IF(OR(Q2="",K2="",K2<=0),"",Q2/K2) -> 0.16666667 | AV2: =IF(OR(R2="",N2="",N2<=0),"",R2/N2) -> 1400000 | AW2: =IFERROR(IF(Z2="No",0,IF(Z2="Yes",AM2/K2,"")),"") -> 0 | AX2: =IF(OR(K2<Outlier_Audit!$H$2,K2>Outlier_Audit!$I$2),"Review","Normal") -> Normal | AY2: =IF(AL2="","Unknown",IF(AL2<10,"<10 years",IF(AL2<20,"10-19 years",IF(AL2<30,"20-29 years","30+ years")))) -> 30+ years | AZ2: =IF(AQ2="","Missing",IF(AQ2>=EDA_Performance!$B$7,"High Growth",IF(AQ2<=EDA_Performance!$B$5,"Low Growth","Middle"))) -> Middle
A3: 1614122 | B3: Eastern | C3: Small | D3: 10 | E3: 1410 | F3: 14 | G3: Manufacture of wearing apparel | H3: 1970 | I3: 30 | J3: 55.699169 | K3: 45000000 | L3: 40000000 | M3: 70 | N3: 6 | O3: 5 | P3: 7200000 | Q3: 6000000 | R3: 30000000 | S3: 0 | T3: Not asked (survey skip: screener employment <20) | U3: No | V3: No | W3: 100 | X3: 0 | Y3: 0 | Z3: No | AB3: No | AC3: No | AD3: Yes | AE3: 2 | AF3: Very severe obstacle | AG3: Moderate obstacle | AH3: No obstacle | AI3: No obstacle | AJ3: Electricity | AK3: Are taken directly from establishment records | AL3: =IF(H3="","",2024-H3) -> 54 | AM3: =IFERROR(IF(Z3="No",0,IF(Z3="Yes",AA3,"")),"") -> 0 | AN3: =IFERROR(IF(AD3="No",0,IF(AD3="Yes",AE3,"")),"") -> 2 | AO3: =IF(S3>0,"Yes","No") -> No | AP3: =IF(OR(K3="",L3="",L3<=0),"",K3/L3-1) -> 0.125 | AQ3: =IF(OR(K3="",L3="",L3<=0),"",(K3/L3)^(1/2)-1) -> 0.060660172 | AR3: =IF(OR(N3="",O3="",O3<=0),"",N3/O3-1) -> 0.2 | AS3: =IF(OR(K3="",N3="",N3<=0),"",K3/N3) -> 7500000 | AT3: =IF(OR(P3="",K3="",K3<=0),"",P3/K3) -> 0.16 | AU3: =IF(OR(Q3="",K3="",K3<=0),"",Q3/K3) -> 0.13333333 | AV3: =IF(OR(R3="",N3="",N3<=0),"",R3/N3) -> 5000000 | AW3: =IFERROR(IF(Z3="No",0,IF(Z3="Yes",AM3/K3,"")),"") -> 0 | AX3: =IF(OR(K3<Outlier_Audit!$H$2,K3>Outlier_Audit!$I$2),"Review","Normal") -> Normal | AY3: =IF(AL3="","Unknown",IF(AL3<10,"<10 years",IF(AL3<20,"10-19 years",IF(AL3<30,"20-29 years","30+ years")))) -> 30+ years | AZ3: =IF(AQ3="","Missing",IF(AQ3>=EDA_Performance!$B$7,"High Growth",IF(AQ3<=EDA_Performance!$B$5,"Low Growth","Middle"))) -> Middle
A4: 1614124 | B4: Central | C4: Medium | D4: 100 | E4: 1073 | F4: 10 | G4: Manufacture of food products | H4: 2007 | I4: 20 | J4: 24.842424 | K4: 3000000000 | L4: 2000000000 | M4: 70 | N4: 50 | O4: 50 | P4: 700000000 | Q4: 400000000 | R4: 5000000000 | S4: 0 | T4: Yes | U4: No | V4: No | W4: 80 | X4: 0 | Y4: 0 | Z4: No | AB4: No | AC4: No | AD4: No | AF4: Moderate obstacle | AG4: Minor obstacle | AH4: Minor obstacle | AI4: Moderate obstacle | AJ4: Corruption | AK4: Are taken directly from establishment records | AL4: =IF(H4="","",2024-H4) -> 17 | AM4: =IFERROR(IF(Z4="No",0,IF(Z4="Yes",AA4,"")),"") -> 0 | AN4: =IFERROR(IF(AD4="No",0,IF(AD4="Yes",AE4,"")),"") -> 0 | AO4: =IF(S4>0,"Yes","No") -> No | AP4: =IF(OR(K4="",L4="",L4<=0),"",K4/L4-1) -> 0.5 | AQ4: =IF(OR(K4="",L4="",L4<=0),"",(K4/L4)^(1/2)-1) -> 0.22474487 | AR4: =IF(OR(N4="",O4="",O4<=0),"",N4/O4-1) -> 0 | AS4: =IF(OR(K4="",N4="",N4<=0),"",K4/N4) -> 60000000 | AT4: =IF(OR(P4="",K4="",K4<=0),"",P4/K4) -> 0.23333333 | AU4: =IF(OR(Q4="",K4="",K4<=0),"",Q4/K4) -> 0.13333333 | AV4: =IF(OR(R4="",N4="",N4<=0),"",R4/N4) -> 100000000 | AW4: =IFERROR(IF(Z4="No",0,IF(Z4="Yes",AM4/K4,"")),"") -> 0 | AX4: =IF(OR(K4<Outlier_Audit!$H$2,K4>Outlier_Audit!$I$2),"Review","Normal") -> Normal | AY4: =IF(AL4="","Unknown",IF(AL4<10,"<10 years",IF(AL4<20,"10-19 years",IF(AL4<30,"20-29 years","30+ years")))) -> 10-19 years | AZ4: =IF(AQ4="","Missing",IF(AQ4>=EDA_Performance!$B$7,"High Growth",IF(AQ4<=EDA_Performance!$B$5,"Low Growth","Middle"))) -> Middle
A5: 1614125 | B5: Central | C5: Large | D5: 110 | E5: 2100 | F5: 21 | G5: Manufacture of basic pharmaceutical products | H5: 1981 | I5: 44 | J5: 1 | K5: 13000000000 | L5: 13000000000 | M5: 90 | N5: 57 | O5: 44 | P5: 1500000000 | Q5: 6000000000 | R5: 12000000000 | S5: 1 | T5: Yes | U5: No | V5: No | W5: 100 | X5: 0 | Y5: 0 | Z5: Yes | AA5: 600000000 | AB5: Yes | AC5: No | AD5: Yes | AE5: 10 | AF5: Major obstacle | AG5: Minor obstacle | AH5: Major obstacle | AI5: Major obstacle | AJ5: Access to finance | AK5: Are taken directly from establishment records | AL5: =IF(H5="","",2024-H5) -> 43 | AM5: =IFERROR(IF(Z5="No",0,IF(Z5="Yes",AA5,"")),"") -> 600000000 | AN5: =IFERROR(IF(AD5="No",0,IF(AD5="Yes",AE5,"")),"") -> 10 | AO5: =IF(S5>0,"Yes","No") -> Yes | AP5: =IF(OR(K5="",L5="",L5<=0),"",K5/L5-1) -> 0 | AQ5: =IF(OR(K5="",L5="",L5<=0),"",(K5/L5)^(1/2)-1) -> 0 | AR5: =IF(OR(N5="",O5="",O5<=0),"",N5/O5-1) -> 0.29545455 | AS5: =IF(OR(K5="",N5="",N5<=0),"",K5/N5) -> 2.2807018e+08 | AT5: =IF(OR(P5="",K5="",K5<=0),"",P5/K5) -> 0.11538462 | AU5: =IF(OR(Q5="",K5="",K5<=0),"",Q5/K5) -> 0.46153846 | AV5: =IF(OR(R5="",N5="",N5<=0),"",R5/N5) -> 2.1052632e+08 | AW5: =IFERROR(IF(Z5="No",0,IF(Z5="Yes",AM5/K5,"")),"") -> 0.046153846 | AX5: =IF(OR(K5<Outlier_Audit!$H$2,K5>Outlier_Audit!$I$2),"Review","Normal") -> Review | AY5: =IF(AL5="","Unknown",IF(AL5<10,"<10 years",IF(AL5<20,"10-19 years",IF(AL5<30,"20-29 years","30+ years")))) -> 30+ years | AZ5: =IF(AQ5="","Missing",IF(AQ5>=EDA_Performance!$B$7,"High Growth",IF(AQ5<=EDA_Performance!$B$5,"Low Growth","Middle"))) -> Low Growth
A6: 1614130 | B6: Central | C6: Small | D6: 7 | E6: 3100 | F6: 31 | G6: Manufacture of furniture | H6: 2020 | I6: 15 | J6: 143.61815 | K6: 24000000 | L6: 17000000 | M6: 70 | N6: 5 | O6: 4 | P6: 4100000 | Q6: 12000000 | R6: 11000000 | S6: 0 | T6: Not asked (survey skip: screener employment <20) | U6: Yes | V6: Yes | W6: 60 | X6: 10 | Y6: 30 | Z6: Yes | AA6: 500000 | AB6: Yes | AC6: No | AD6: Yes | AE6: 6 | AF6: Minor obstacle | AG6: No obstacle | AH6: No obstacle | AI6: Minor obstacle | AJ6: Tax rates | AK6: Are in some case taken from books and in some case estimates | AL6: =IF(H6="","",2024-H6) -> 4 | AM6: =IFERROR(IF(Z6="No",0,IF(Z6="Yes",AA6,"")),"") -> 500000 | AN6: =IFERROR(IF(AD6="No",0,IF(AD6="Yes",AE6,"")),"") -> 6 | AO6: =IF(S6>0,"Yes","No") -> No | AP6: =IF(OR(K6="",L6="",L6<=0),"",K6/L6-1) -> 0.41176471 | AQ6: =IF(OR(K6="",L6="",L6<=0),"",(K6/L6)^(1/2)-1) -> 0.18817705 | AR6: =IF(OR(N6="",O6="",O6<=0),"",N6/O6-1) -> 0.25 | AS6: =IF(OR(K6="",N6="",N6<=0),"",K6/N6) -> 4800000 | AT6: =IF(OR(P6="",K6="",K6<=0),"",P6/K6) -> 0.17083333 | AU6: =IF(OR(Q6="",K6="",K6<=0),"",Q6/K6) -> 0.5 | AV6: =IF(OR(R6="",N6="",N6<=0),"",R6/N6) -> 2200000 | AW6: =IFERROR(IF(Z6="No",0,IF(Z6="Yes",AM6/K6,"")),"") -> 0.020833333 | AX6: =IF(OR(K6<Outlier_Audit!$H$2,K6>Outlier_Audit!$I$2),"Review","Normal") -> Normal | AY6: =IF(AL6="","Unknown",IF(AL6<10,"<10 years",IF(AL6<20,"10-19 years",IF(AL6<30,"20-29 years","30+ years")))) -> <10 years | AZ6: =IF(AQ6="","Missing",IF(AQ6>=EDA_Performance!$B$7,"High Growth",IF(AQ6<=EDA_Performance!$B$5,"Low Growth","Middle"))) -> Middle
A7: 1614131 | B7: Central | C7: Small | D7: 16 | E7: 1811 | F7: 18 | G7: Printing and reproduction of recorded media | H7: 1985 | I7: 30 | J7: 157.86736 | K7: 100000000 | L7: 80000000 | M7: 20 | N7: 16 | O7: 16 | P7: 5000000 | Q7: 20000000 | R7: 350000000 | S7: 0 | T7: Not asked (survey skip: screener employment <20) | U7: No | V7: No | W7: 80 | X7: 0 | Y7: 0 | Z7: No | AB7: No | AC7: No | AD7: No | AF7: Minor obstacle | AG7: No obstacle | AH7: No obstacle | AI7: No obstacle | AJ7: Electricity | AK7: Are in some case taken from books and in some case estimates | AL7: =IF(H7="","",2024-H7) -> 39 | AM7: =IFERROR(IF(Z7="No",0,IF(Z7="Yes",AA7,"")),"") -> 0 | AN7: =IFERROR(IF(AD7="No",0,IF(AD7="Yes",AE7,"")),"") -> 0 | AO7: =IF(S7>0,"Yes","No") -> No | AP7: =IF(OR(K7="",L7="",L7<=0),"",K7/L7-1) -> 0.25 | AQ7: =IF(OR(K7="",L7="",L7<=0),"",(K7/L7)^(1/2)-1) -> 0.11803399 | AR7: =IF(OR(N7="",O7="",O7<=0),"",N7/O7-1) -> 0 | AS7: =IF(OR(K7="",N7="",N7<=0),"",K7/N7) -> 6250000 | AT7: =IF(OR(P7="",K7="",K7<=0),"",P7/K7) -> 0.05 | AU7: =IF(OR(Q7="",K7="",K7<=0),"",Q7/K7) -> 0.2 | AV7: =IF(OR(R7="",N7="",N7<=0),"",R7/N7) -> 21875000 | AW7: =IFERROR(IF(Z7="No",0,IF(Z7="Yes",AM7/K7,"")),"") -> 0 | AX7: =IF(OR(K7<Outlier_Audit!$H$2,K7>Outlier_Audit!$I$2),"Review","Normal") -> Normal | AY7: =IF(AL7="","Unknown",IF(AL7<10,"<10 years",IF(AL7<20,"10-19 years",IF(AL7<30,"20-29 years","30+ years")))) -> 30+ years | AZ7: =IF(AQ7="","Missing",IF(AQ7>=EDA_Performance!$B$7,"High Growth",IF(AQ7<=EDA_Performance!$B$5,"Low Growth","Middle"))) -> Middle
A8: 1614136 | B8: Central | C8: Large | D8: 1850 | E8: 2410 | F8: 24 | G8: Manufacture of basic metals | H8: 1983 | I8: 42 | J8: 1 | K8: 6000000000000 | L8: 4000000000000 | M8: 92 | N8: 2000 | O8: 1800 | P8: 1000000000000 | Q8: 3000000000000 | R8: 1000000000000 | S8: 35 | T8: Yes | U8: Yes | V8: Yes | W8: 35 | X8: 30 | Y8: 25 | Z8: Yes | AA8: 1000000000000 | AB8: Yes | AC8: Yes | AD8: Yes | AE8: 2 | AF8: Moderate obstacle | AG8: Moderate obstacle | AH8: Minor obstacle | AI8: Moderate obstacle | AJ8: Tax rates | AK8: Are taken directly from establishment records | AL8: =IF(H8="","",2024-H8) -> 41 | AM8: =IFERROR(IF(Z8="No",0,IF(Z8="Yes",AA8,"")),"") -> 1000000000000 | AN8: =IFERROR(IF(AD8="No",0,IF(AD8="Yes",AE8,"")),"") -> 2 | AO8: =IF(S8>0,"Yes","No") -> Yes | AP8: =IF(OR(K8="",L8="",L8<=0),"",K8/L8-1) -> 0.5 | AQ8: =IF(OR(K8="",L8="",L8<=0),"",(K8/L8)^(1/2)-1) -> 0.22474487 | AR8: =IF(OR(N8="",O8="",O8<=0),"",N8/O8-1) -> 0.11111111 | AS8: =IF(OR(K8="",N8="",N8<=0),"",K8/N8) -> 3000000000 | AT8: =IF(OR(P8="",K8="",K8<=0),"",P8/K8) -> 0.16666667 | AU8: =IF(OR(Q8="",K8="",K8<=0),"",Q8/K8) -> 0.5 | AV8: =IF(OR(R8="",N8="",N8<=0),"",R8/N8) -> 500000000 | AW8: =IFERROR(IF(Z8="No",0,IF(Z8="Yes",AM8/K8,"")),"") -> 0.16666667 | AX8: =IF(OR(K8<Outlier_Audit!$H$2,K8>Outlier_Audit!$I$2),"Review","Normal") -> Review | AY8: =IF(AL8="","Unknown",IF(AL8<10,"<10 years",IF(AL8<20,"10-19 years",IF(AL8<30,"20-29 years","30+ years")))) -> 30+ years | AZ8: =IF(AQ8="","Missing",IF(AQ8>=EDA_Performance!$B$7,"High Growth",IF(AQ8<=EDA_Performance!$B$5,"Low Growth","Middle"))) -> Middle
A9: 1614138 | B9: Eastern | C9: Small | D9: 9 | E9: 1079 | F9: 10 | G9: Manufacture of food products | H9: 1992 | I9: 30 | J9: 1.7886078 | K9: 38000000 | L9: 6000000 | M9: 100 | N9: 9 | O9: 9 | P9: 10000000 | R9: 15000000 | S9: 0 | T9: Not asked (survey skip: screener employment <20) | U9: No | V9: No | W9: 40 | X9: 0 | Y9: 0 | Z9: No | AB9: No | AC9: No | AD9: Yes | AE9: 8 | AF9: Very severe obstacle | AG9: Moderate obstacle | AH9: No obstacle | AI9: Very severe obstacle | AJ9: Access to finance | AK9: Are in some case taken from books and in some case estimates | AL9: =IF(H9="","",2024-H9) -> 32 | AM9: =IFERROR(IF(Z9="No",0,IF(Z9="Yes",AA9,"")),"") -> 0 | AN9: =IFERROR(IF(AD9="No",0,IF(AD9="Yes",AE9,"")),"") -> 8 | AO9: =IF(S9>0,"Yes","No") -> No | AP9: =IF(OR(K9="",L9="",L9<=0),"",K9/L9-1) -> 5.3333333 | AQ9: =IF(OR(K9="",L9="",L9<=0),"",(K9/L9)^(1/2)-1) -> 1.5166115 | AR9: =IF(OR(N9="",O9="",O9<=0),"",N9/O9-1) -> 0 | AS9: =IF(OR(K9="",N9="",N9<=0),"",K9/N9) -> 4222222.2 | AT9: =IF(OR(P9="",K9="",K9<=0),"",P9/K9) -> 0.26315789 | AU9: =IF(OR(Q9="",K9="",K9<=0),"",Q9/K9) | AV9: =IF(OR(R9="",N9="",N9<=0),"",R9/N9) -> 1666666.7 | AW9: =IFERROR(IF(Z9="No",0,IF(Z9="Yes",AM9/K9,"")),"") -> 0 | AX9: =IF(OR(K9<Outlier_Audit!$H$2,K9>Outlier_Audit!$I$2),"Review","Normal") -> Normal | AY9: =IF(AL9="","Unknown",IF(AL9<10,"<10 years",IF(AL9<20,"10-19 years",IF(AL9<30,"20-29 years","30+ years")))) -> 30+ years | AZ9: =IF(AQ9="","Missing",IF(AQ9>=EDA_Performance!$B$7,"High Growth",IF(AQ9<=EDA_Performance!$B$5,"Low Growth","Middle"))) -> High Growth
A10: 1614139 | B10: Western | C10: Small | D10: 5 | E10: 3100 | F10: 31 | G10: Manufacture of furniture | H10: 2002 | I10: 24 | J10: 68.62606 | K10: 40000000 | L10: 22000000 | M10: 4 | N10: 5 | O10: 5 | P10: 12000000 | Q10: 16000000 | R10: 24200000 | S10: 0 | T10: Not asked (survey skip: screener employment <20) | U10: No | V10: No | W10: 20 | X10: 60 | Y10: 0 | Z10: Yes | AA10: 1000000 | AB10: Yes | AC10: No | AD10: Yes | AE10: 5 | AF10: Major obstacle | AG10: Very severe obstacle | AH10: No obstacle | AI10: Minor obstacle | AJ10: Access to finance | AK10: Are estimates computed with some precision | AL10: =IF(H10="","",2024-H10) -> 22 | AM10: =IFERROR(IF(Z10="No",0,IF(Z10="Yes",AA10,"")),"") -> 1000000 | AN10: =IFERROR(IF(AD10="No",0,IF(AD10="Yes",AE10,"")),"") -> 5 | AO10: =IF(S10>0,"Yes","No") -> No | AP10: =IF(OR(K10="",L10="",L10<=0),"",K10/L10-1) -> 0.81818182 | AQ10: =IF(OR(K10="",L10="",L10<=0),"",(K10/L10)^(1/2)-1) -> 0.34839972 | AR10: =IF(OR(N10="",O10="",O10<=0),"",N10/O10-1) -> 0 | AS10: =IF(OR(K10="",N10="",N10<=0),"",K10/N10) -> 8000000 | AT10: =IF(OR(P10="",K10="",K10<=0),"",P10/K10) -> 0.3 | AU10: =IF(OR(Q10="",K10="",K10<=0),"",Q10/K10) -> 0.4 | AV10: =IF(OR(R10="",N10="",N10<=0),"",R10/N10) -> 4840000 | AW10: =IFERROR(IF(Z10="No",0,IF(Z10="Yes",AM10/K10,"")),"") -> 0.025 | AX10: =IF(OR(K10<Outlier_Audit!$H$2,K10>Outlier_Audit!$I$2),"Review","Normal") -> Normal | AY10: =IF(AL10="","Unknown",IF(AL10<10,"<10 years",IF(AL10<20,"10-19 years",IF(AL10<30,"20-29 years","30+ years")))) -> 20-29 years | AZ10: =IF(AQ10="","Missing",IF(AQ10>=EDA_Performance!$B$7,"High Growth",IF(AQ10<=EDA_Performance!$B$5,"Low Growth","Middle"))) -> High Growth
A11: 1614143 | B11: Central | C11: Small | D11: 6 | E11: 2599 | F11: 25 | G11: Manufacture of fabricated metal products | H11: 1987 | I11: 35 | J11: 157.86736 | K11: 10000000 | L11: 10000000 | M11: 100 | N11: 6 | O11: 6 | P11: 6000000 | Q11: 3000000 | R11: 7000000 | S11: 0 | T11: Not asked (survey skip: screener employment <20) | U11: No | V11: No | W11: 80 | X11: 10 | Y11: 0 | Z11: No | AB11: No | AC11: Yes | AD11: Yes | AE11: 2 | AF11: Minor obstacle | AG11: Major obstacle | AH11: No obstacle | AI11: Minor obstacle | AJ11: Access to finance | AK11: Are in some case taken from books and in some case estimates | AL11: =IF(H11="","",2024-H11) -> 37 | AM11: =IFERROR(IF(Z11="No",0,IF(Z11="Yes",AA11,"")),"") -> 0 | AN11: =IFERROR(IF(AD11="No",0,IF(AD11="Yes",AE11,"")),"") -> 2 | AO11: =IF(S11>0,"Yes","No") -> No | AP11: =IF(OR(K11="",L11="",L11<=0),"",K11/L11-1) -> 0 | AQ11: =IF(OR(K11="",L11="",L11<=0),"",(K11/L11)^(1/2)-1) -> 0 | AR11: =IF(OR(N11="",O11="",O11<=0),"",N11/O11-1) -> 0 | AS11: =IF(OR(K11="",N11="",N11<=0),"",K11/N11) -> 1666666.7 | AT11: =IF(OR(P11="",K11="",K11<=0),"",P11/K11) -> 0.6 | AU11: =IF(OR(Q11="",K11="",K11<=0),"",Q11/K11) -> 0.3 | AV11: =IF(OR(R11="",N11="",N11<=0),"",R11/N11) -> 1166666.7 | AW11: =IFERROR(IF(Z11="No",0,IF(Z11="Yes",AM11/K11,"")),"") -> 0 | AX11: =IF(OR(K11<Outlier_Audit!$H$2,K11>Outlier_Audit!$I$2),"Review","Normal") -> Normal | AY11: =IF(AL11="","Unknown",IF(AL11<10,"<10 years",IF(AL11<20,"10-19 years",IF(AL11<30,"20-29 years","30+ years")))) -> 30+ years | AZ11: =IF(AQ11="","Missing",IF(AQ11>=EDA_Performance!$B$7,"High Growth",IF(AQ11<=EDA_Performance!$B$5,"Low Growth","Middle"))) -> Low Growth
A12: 1614144 | B12: Central | C12: Small | D12: 50 | E12: 1812 | F12: 18 | G12: Printing and reproduction of recorded media | H12: 1995 | I12: 17 | J12: 585.95532 | K12: 300000000 | L12: 110000000 | M12: 95 | N12: 40 | O12: 20 | P12: 30000000 | Q12: 40000000 | R12: 1000000000 | S12: 10 | T12: Yes | U12: No | V12: Yes | W12: 80 | X12: 10 | Y12: 0 | Z12: Yes | AA12: 300000000 | AB12: Yes | AC12: No | AD12: Yes | AE12: 6 | AF12: Minor obstacle | AG12: No obstacle | AH12: No obstacle | AI12: Minor obstacle | AJ12: Customs and trade regulations | AK12: Are estimates computed with some precision | AL12: =IF(H12="","",2024-H12) -> 29 | AM12: =IFERROR(IF(Z12="No",0,IF(Z12="Yes",AA12,"")),"") -> 300000000 | AN12: =IFERROR(IF(AD12="No",0,IF(AD12="Yes",AE12,"")),"") -> 6 | AO12: =IF(S12>0,"Yes","No") -> Yes | AP12: =IF(OR(K12="",L12="",L12<=0),"",K12/L12-1) -> 1.7272727 | AQ12: =IF(OR(K12="",L12="",L12<=0),"",(K12/L12)^(1/2)-1) -> 0.65144565 | AR12: =IF(OR(N12="",O12="",O12<=0),"",N12/O12-1) -> 1 | AS12: =IF(OR(K12="",N12="",N12<=0),"",K12/N12) -> 7500000 | AT12: =IF(OR(P12="",K12="",K12<=0),"",P12/K12) -> 0.1 | AU12: =IF(OR(Q12="",K12="",K12<=0),"",Q12/K12) -> 0.13333333 | AV12: =IF(OR(R12="",N12="",N12<=0),"",R12/N12) -> 25000000 | AW12: =IFERROR(IF(Z12="No",0,IF(Z12="Yes",AM12/K12,"")),"") -> 1 | AX12: =IF(OR(K12<Outlier_Audit!$H$2,K12>Outlier_Audit!$I$2),"Review","Normal") -> Normal | AY12: =IF(AL12="","Unknown",IF(AL12<10,"<10 years",IF(AL12<20,"10-19 years",IF(AL12<30,"20-29 years","30+ years")))) -> 20-29 years | AZ12: =IF(AQ12="","Missing",IF(AQ12>=EDA_Performance!$B$7,"High Growth",IF(AQ12<=EDA_Performance!$B$5,"Low Growth","Middle"))) -> High Growth
A13: 1614146 | B13: Central | C13: Small | D13: 80 | E13: 2023 | F13: 20 | G13: Manufacture of chemicals and chemical products | H13: 2005 | I13: 20 | J13: 585.95532 | K13: 2000000000 | L13: 1000000000 | M13: 70 | N13: 80 | O13: 40 | P13: 200000000 | Q13: 800000000 | R13: 700000000 | S13: 30 | T13: Yes | U13: Yes | V13: Yes | W13: 40 | X13: 5 | Y13: 0 | Z13: Yes | AA13: 80000000 | AB13: Yes | AC13: No | AD13: Yes | AE13: 4 | AF13: Major obstacle | AG13: No obstacle | AH13: No obstacle | AI13: No obstacle | AJ13: Tax rates | AK13: Are in some case taken from books and in some case estimates | AL13: =IF(H13="","",2024-H13) -> 19 | AM13: =IFERROR(IF(Z13="No",0,IF(Z13="Yes",AA13,"")),"") -> 80000000 | AN13: =IFERROR(IF(AD13="No",0,IF(AD13="Yes",AE13,"")),"") -> 4 | AO13: =IF(S13>0,"Yes","No") -> Yes | AP13: =IF(OR(K13="",L13="",L13<=0),"",K13/L13-1) -> 1 | AQ13: =IF(OR(K13="",L13="",L13<=0),"",(K13/L13)^(1/2)-1) -> 0.41421356 | AR13: =IF(OR(N13="",O13="",O13<=0),"",N13/O13-1) -> 1 | AS13: =IF(OR(K13="",N13="",N13<=0),"",K13/N13) -> 25000000 | AT13: =IF(OR(P13="",K13="",K13<=0),"",P13/K13) -> 0.1 | AU13: =IF(OR(Q13="",K13="",K13<=0),"",Q13/K13) -> 0.4 | AV13: =IF(OR(R13="",N13="",N13<=0),"",R13/N13) -> 8750000 | AW13: =IFERROR(IF(Z13="No",0,IF(Z13="Yes",AM13/K13,"")),"") -> 0.04 | AX13: =IF(OR(K13<Outlier_Audit!$H$2,K13>Outlier_Audit!$I$2),"Review","Normal") -> Normal | AY13: =IF(AL13="","Unknown",IF(AL13<10,"<10 years",IF(AL13<20,"10-19 years",IF(AL13<30,"20-29 years","30+ years")))) -> 10-19 years | AZ13: =IF(AQ13="","Missing",IF(AQ13>=EDA_Performance!$B$7,"High Growth",IF(AQ13<=EDA_Performance!$B$5,"Low Growth","Middle"))) -> High Growth
A14: 1614147 | B14: Eastern | C14: Large | D14: 100 | E14: 1079 | F14: 10 | G14: Manufacture of food products | H14: 1982 | I14: 43 | J14: 1 | K14: 3000000000 | L14: 2500000000 | M14: 30 | N14: 35 | O14: 35 | P14: 300000000 | Q14: 900000000 | R14: 600000000 | S14: 10 | T14: Yes | U14: No | V14: Yes | W14: 100 | X14: 0 | Y14: 0 | Z14: No | AB14: No | AC14: No | AD14: Yes | AE14: 5 | AF14: Major obstacle | AG14: Minor obstacle | AH14: Moderate obstacle | AI14: Very severe obstacle | AJ14: Practices of competitors in the informal sector | AK14: Are in some case taken from books and in some case estimates | AL14: =IF(H14="","",2024-H14) -> 42 | AM14: =IFERROR(IF(Z14="No",0,IF(Z14="Yes",AA14,"")),"") -> 0 | AN14: =IFERROR(IF(AD14="No",0,IF(AD14="Yes",AE14,"")),"") -> 5 | AO14: =IF(S14>0,"Yes","No") -> Yes | AP14: =IF(OR(K14="",L14="",L14<=0),"",K14/L14-1) -> 0.2 | AQ14: =IF(OR(K14="",L14="",L14<=0),"",(K14/L14)^(1/2)-1) -> 0.095445115 | AR14: =IF(OR(N14="",O14="",O14<=0),"",N14/O14-1) -> 0 | AS14: =IF(OR(K14="",N14="",N14<=0),"",K14/N14) -> 85714286 | AT14: =IF(OR(P14="",K14="",K14<=0),"",P14/K14) -> 0.1 | AU14: =IF(OR(Q14="",K14="",K14<=0),"",Q14/K14) -> 0.3 | AV14: =IF(OR(R14="",N14="",N14<=0),"",R14/N14) -> 17142857 | AW14: =IFERROR(IF(Z14="No",0,IF(Z14="Yes",AM14/K14,"")),"") -> 0 | AX14: =IF(OR(K14<Outlier_Audit!$H$2,K14>Outlier_Audit!$I$2),"Review","Normal") -> Normal | AY14: =IF(AL14="","Unknown",IF(AL14<10,"<10 years",IF(AL14<20,"10-19 years",IF(AL14<30,"20-29 years","30+ years")))) -> 30+ years | AZ14: =IF(AQ14="","Missing",IF(AQ14>=EDA_Performance!$B$7,"High Growth",IF(AQ14<=EDA_Performance!$B$5,"Low Growth","Middle"))) -> Middle
A15: 1614149 | B15: Northern | C15: Medium | D15: 10 | E15: 1040 | F15: 10 | G15: Manufacture of food products | H15: 2013 | I15: 10 | J15: 1.826539 | K15: 300000000 | L15: 250000000 | M15: 100 | N15: 15 | O15: 10 | P15: 70000000 | Q15: 100000000 | R15: 400000000 | S15: 0 | T15: Not asked (survey skip: screener employment <20) | U15: No | V15: No | W15: 40 | X15: 0 | Y15: 40 | Z15: No | AB15: No | AC15: No | AD15: Yes | AE15: 7 | AF15: Moderate obstacle | AG15: Minor obstacle | AH15: No obstacle | AI15: Very severe obstacle | AJ15: Practices of competitors in the informal sector | AK15: Are in some case taken from books and in some case estimates | AL15: =IF(H15="","",2024-H15) -> 11 | AM15: =IFERROR(IF(Z15="No",0,IF(Z15="Yes",AA15,"")),"") -> 0 | AN15: =IFERROR(IF(AD15="No",0,IF(AD15="Yes",AE15,"")),"") -> 7 | AO15: =IF(S15>0,"Yes","No") -> No | AP15: =IF(OR(K15="",L15="",L15<=0),"",K15/L15-1) -> 0.2 | AQ15: =IF(OR(K15="",L15="",L15<=0),"",(K15/L15)^(1/2)-1) -> 0.095445115 | AR15: =IF(OR(N15="",O15="",O15<=0),"",N15/O15-1) -> 0.5 | AS15: =IF(OR(K15="",N15="",N15<=0),"",K15/N15) -> 20000000 | AT15: =IF(OR(P15="",K15="",K15<=0),"",P15/K15) -> 0.23333333 | AU15: =IF(OR(Q15="",K15="",K15<=0),"",Q15/K15) -> 0.33333333 | AV15: =IF(OR(R15="",N15="",N15<=0),"",R15/N15) -> 26666667 | AW15: =IFERROR(IF(Z15="No",0,IF(Z15="Yes",AM15/K15,"")),"") -> 0 | AX15: =IF(OR(K15<Outlier_Audit!$H$2,K15>Outlier_Audit!$I$2),"Review","Normal") -> Normal | AY15: =IF(AL15="","Unknown",IF(AL15<10,"<10 years",IF(AL15<20,"10-19 years",IF(AL15<30,"20-29 years","30+ years")))) -> 10-19 years | AZ15: =IF(AQ15="","Missing",IF(AQ15>=EDA_Performance!$B$7,"High Growth",IF(AQ15<=EDA_Performance!$B$5,"Low Growth","Middle"))) -> Middle
A16: 1614151 | B16: Central | C16: Large | D16: 355 | E16: 1079 | F16: 10 | G16: Manufacture of food products | H16: 1994 | I16: 25 | J16: 1 | K16: 68000000000 | L16: 67000000000 | M16: 69 | N16: 124 | O16: 118 | P16: 4140000000 | Q16: 37820000000 | R16: 95000000000 | S16: 1 | T16: Yes | U16: Yes | V16: No | W16: 100 | X16: 0 | Y16: 0 | Z16: No | AB16: No | AC16: No | AD16: Yes | AE16: 10 | AF16: Very severe obstacle | AG16: Minor obstacle | AH16: Minor obstacle | AI16: Very severe obstacle | AJ16: Electricity | AK16: Are in some case taken from books and in some case estimates | AL16: =IF(H16="","",2024-H16) -> 30 | AM16: =IFERROR(IF(Z16="No",0,IF(Z16="Yes",AA16,"")),"") -> 0 | AN16: =IFERROR(IF(AD16="No",0,IF(AD16="Yes",AE16,"")),"") -> 10 | AO16: =IF(S16>0,"Yes","No") -> Yes | AP16: =IF(OR(K16="",L16="",L16<=0),"",K16/L16-1) -> 0.014925373 | AQ16: =IF(OR(K16="",L16="",L16<=0),"",(K16/L16)^(1/2)-1) -> 0.0074350466 | AR16: =IF(OR(N16="",O16="",O16<=0),"",N16/O16-1) -> 0.050847458 | AS16: =IF(OR(K16="",N16="",N16<=0),"",K16/N16) -> 5.483871e+08 | AT16: =IF(OR(P16="",K16="",K16<=0),"",P16/K16) -> 0.060882353 | AU16: =IF(OR(Q16="",K16="",K16<=0),"",Q16/K16) -> 0.55617647 | AV16: =IF(OR(R16="",N16="",N16<=0),"",R16/N16) -> 7.6612903e+08 | AW16: =IFERROR(IF(Z16="No",0,IF(Z16="Yes",AM16/K16,"")),"") -> 0 | AX16: =IF(OR(K16<Outlier_Audit!$H$2,K16>Outlier_Audit!$I$2),"Review","Normal") -> Review | AY16: =IF(AL16="","Unknown",IF(AL16<10,"<10 years",IF(AL16<20,"10-19 years",IF(AL16<30,"20-29 years","30+ years")))) -> 30+ years | AZ16: =IF(AQ16="","Missing",IF(AQ16>=EDA_Performance!$B$7,"High Growth",IF(AQ16<=EDA_Performance!$B$5,"Low Growth","Middle"))) -> Low Growth
A17: 1614153 | B17: Eastern | C17: Medium | D17: 8 | E17: 3100 | F17: 31 | G17: Manufacture of furniture | H17: 2021 | I17: 5 | J17: 3.0692382 | K17: 60000000 | L17: 30000000 | M17: 70 | N17: 8 | O17: 8 | P17: 20000000 | Q17: 35000000 | S17: 0 | T17: Not asked (survey skip: screener employment <20) | U17: No | V17: No | W17: 30 | X17: 25 | Y17: 20 | Z17: No | AB17: Yes | AC17: No | AD17: Yes | AE17: 6 | AF17: Minor obstacle | AG17: Major obstacle | AH17: No obstacle | AI17: Major obstacle | AJ17: Tax rates | AK17: Are taken directly from establishment records | AL17: =IF(H17="","",2024-H17) -> 3 | AM17: =IFERROR(IF(Z17="No",0,IF(Z17="Yes",AA17,"")),"") -> 0 | AN17: =IFERROR(IF(AD17="No",0,IF(AD17="Yes",AE17,"")),"") -> 6 | AO17: =IF(S17>0,"Yes","No") -> No | AP17: =IF(OR(K17="",L17="",L17<=0),"",K17/L17-1) -> 1 | AQ17: =IF(OR(K17="",L17="",L17<=0),"",(K17/L17)^(1/2)-1) -> 0.41421356 | AR17: =IF(OR(N17="",O17="",O17<=0),"",N17/O17-1) -> 0 | AS17: =IF(OR(K17="",N17="",N17<=0),"",K17/N17) -> 7500000 | AT17: =IF(OR(P17="",K17="",K17<=0),"",P17/K17) -> 0.33333333 | AU17: =IF(OR(Q17="",K17="",K17<=0),"",Q17/K17) -> 0.58333333 | AV17: =IF(OR(R17="",N17="",N17<=0),"",R17/N17) | AW17: =IFERROR(IF(Z17="No",0,IF(Z17="Yes",AM17/K17,"")),"") -> 0 | AX17: =IF(OR(K17<Outlier_Audit!$H$2,K17>Outlier_Audit!$I$2),"Review","Normal") -> Normal | AY17: =IF(AL17="","Unknown",IF(AL17<10,"<10 years",IF(AL17<20,"10-19 years",IF(AL17<30,"20-29 years","30+ years")))) -> <10 years | AZ17: =IF(AQ17="","Missing",IF(AQ17>=EDA_Performance!$B$7,"High Growth",IF(AQ17<=EDA_Performance!$B$5,"Low Growth","Middle"))) -> High Growth
A18: 1614155 | B18: Western | C18: Medium | D18: 16 | E18: 1410 | F18: 14 | G18: Manufacture of wearing apparel | H18: 1990 | I18: 35 | J18: 2.4641058 | K18: 57242000 | L18: 35000000 | M18: 13 | N18: 6 | O18: 6 | P18: 18000000 | Q18: 22500000 | R18: 26500000 | S18: 0 | T18: Not asked (survey skip: screener employment <20) | U18: No | V18: No | W18: 50 | X18: 10 | Y18: 10 | Z18: No | AB18: Yes | AC18: Yes | AD18: Yes | AE18: 0 | AF18: Minor obstacle | AG18: Major obstacle | AH18: No obstacle | AI18: Minor obstacle | AJ18: Access to finance | AK18: Are in some case taken from books and in some case estimates | AL18: =IF(H18="","",2024-H18) -> 34 | AM18: =IFERROR(IF(Z18="No",0,IF(Z18="Yes",AA18,"")),"") -> 0 | AN18: =IFERROR(IF(AD18="No",0,IF(AD18="Yes",AE18,"")),"") -> 0 | AO18: =IF(S18>0,"Yes","No") -> No | AP18: =IF(OR(K18="",L18="",L18<=0),"",K18/L18-1) -> 0.63548571 | AQ18: =IF(OR(K18="",L18="",L18<=0),"",(K18/L18)^(1/2)-1) -> 0.2788611 | AR18: =IF(OR(N18="",O18="",O18<=0),"",N18/O18-1) -> 0 | AS18: =IF(OR(K18="",N18="",N18<=0),"",K18/N18) -> 9540333.3 | AT18: =IF(OR(P18="",K18="",K18<=0),"",P18/K18) -> 0.31445442 | AU18: =IF(OR(Q18="",K18="",K18<=0),"",Q18/K18) -> 0.39306803 | AV18: =IF(OR(R18="",N18="",N18<=0),"",R18/N18) -> 4416666.7 | AW18: =IFERROR(IF(Z18="No",0,IF(Z18="Yes",AM18/K18,"")),"") -> 0 | AX18: =IF(OR(K18<Outlier_Audit!$H$2,K18>Outlier_Audit!$I$2),"Review","Normal") -> Normal | AY18: =IF(AL18="","Unknown",IF(AL18<10,"<10 years",IF(AL18<20,"10-19 years",IF(AL18<30,"20-29 years","30+ years")))) -> 30+ years | AZ18: =IF(AQ18="","Missing",IF(AQ18>=EDA_Performance!$B$7,"High Growth",IF(AQ18<=EDA_Performance!$B$5,"Low Growth","Middle"))) -> High Growth
A19: 1614157 | B19: Eastern | C19: Small | D19: 7 | E19: 1061 | F19: 10 | G19: Manufacture of food products | H19: 2015 | I19: 10 | J19: 26.253841 | K19: 32000000 | L19: 28000000 | M19: 65 | N19: 7 | O19: 7 | P19: 12000000 | Q19: 18000000 | R19: 20000000 | S19: 0 | T19: Not asked (survey skip: screener employment <20) | U19: No | V19: No | W19: 80 | X19: 0 | Y19: 0 | Z19: No | AB19: No | AC19: No | AD19: Yes | AE19: 8 | AF19: Moderate obstacle | AG19: Major obstacle | AH19: No obstacle | AI19: Major obstacle | AJ19: Tax rates | AK19: Are estimates computed with some precision | AL19: =IF(H19="","",2024-H19) -> 9 | AM19: =IFERROR(IF(Z19="No",0,IF(Z19="Yes",AA19,"")),"") -> 0 | AN19: =IFERROR(IF(AD19="No",0,IF(AD19="Yes",AE19,"")),"") -> 8 | AO19: =IF(S19>0,"Yes","No") -> No | AP19: =IF(OR(K19="",L19="",L19<=0),"",K19/L19-1) -> 0.14285714 | AQ19: =IF(OR(K19="",L19="",L19<=0),"",(K19/L19)^(1/2)-1) -> 0.069044968 | AR19: =IF(OR(N19="",O19="",O19<=0),"",N19/O19-1) -> 0 | AS19: =IF(OR(K19="",N19="",N19<=0),"",K19/N19) -> 4571428.6 | AT19: =IF(OR(P19="",K19="",K19<=0),"",P19/K19) -> 0.375 | AU19: =IF(OR(Q19="",K19="",K19<=0),"",Q19/K19) -> 0.5625 | AV19: =IF(OR(R19="",N19="",N19<=0),"",R19/N19) -> 2857142.9 | AW19: =IFERROR(IF(Z19="No",0,IF(Z19="Yes",AM19/K19,"")),"") -> 0 | AX19: =IF(OR(K19<Outlier_Audit!$H$2,K19>Outlier_Audit!$I$2),"Review","Normal") -> Normal | AY19: =IF(AL19="","Unknown",IF(AL19<10,"<10 years",IF(AL19<20,"10-19 years",IF(AL19<30,"20-29 years","30+ years")))) -> <10 years | AZ19: =IF(AQ19="","Missing",IF(AQ19>=EDA_Performance!$B$7,"High Growth",IF(AQ19<=EDA_Performance!$B$5,"Low Growth","Middle"))) -> Middle
A20: 1614160 | B20: Western | C20: Small | D20: 16 | E20: 3100 | F20: 31 | G20: Manufacture of furniture | H20: 2009 | I20: 20 | J20: 68.62606 | K20: 45000000 | L20: 18000000 | M20: 60 | N20: 12 | O20: 8 | Q20: 30000000 | R20: 50000000 | S20: 0 | T20: Not asked (survey skip: screener employment <20) | U20: No | V20: Yes | W20: 50 | X20: 25 | Y20: 0 | Z20: No | AB20: Yes | AC20: Yes | AD20: Yes | AE20: 30 | AF20: Major obstacle | AG20: Moderate obstacle | AH20: Minor obstacle | AI20: Major obstacle | AJ20: Electricity | AK20: Are estimates computed with some precision | AL20: =IF(H20="","",2024-H20) -> 15 | AM20: =IFERROR(IF(Z20="No",0,IF(Z20="Yes",AA20,"")),"") -> 0 | AN20: =IFERROR(IF(AD20="No",0,IF(AD20="Yes",AE20,"")),"") -> 30 | AO20: =IF(S20>0,"Yes","No") -> No | AP20: =IF(OR(K20="",L20="",L20<=0),"",K20/L20-1) -> 1.5 | AQ20: =IF(OR(K20="",L20="",L20<=0),"",(K20/L20)^(1/2)-1) -> 0.58113883 | AR20: =IF(OR(N20="",O20="",O20<=0),"",N20/O20-1) -> 0.5 | AS20: =IF(OR(K20="",N20="",N20<=0),"",K20/N20) -> 3750000 | AT20: =IF(OR(P20="",K20="",K20<=0),"",P20/K20) | AU20: =IF(OR(Q20="",K20="",K20<=0),"",Q20/K20) -> 0.66666667 | AV20: =IF(OR(R20="",N20="",N20<=0),"",R20/N20) -> 4166666.7 | AW20: =IFERROR(IF(Z20="No",0,IF(Z20="Yes",AM20/K20,"")),"") -> 0 | AX20: =IF(OR(K20<Outlier_Audit!$H$2,K20>Outlier_Audit!$I$2),"Review","Normal") -> Normal | AY20: =IF(AL20="","Unknown",IF(AL20<10,"<10 years",IF(AL20<20,"10-19 years",IF(AL20<30,"20-29 years","30+ years")))) -> 10-19 years | AZ20: =IF(AQ20="","Missing",IF(AQ20>=EDA_Performance!$B$7,"High Growth",IF(AQ20<=EDA_Performance!$B$5,"Low Growth","Middle"))) -> High Growth
A21: 1614161 | B21: Eastern | C21: Small | D21: 7 | E21: 1061 | F21: 10 | G21: Manufacture of food products | H21: 2000 | I21: 25 | J21: 118.82497 | K21: 154000000 | L21: 144000000 | M21: 100 | N21: 7 | O21: 7 | P21: 21600000 | Q21: 35000000 | R21: 300000000 | S21: 0 | T21: Not asked (survey skip: screener employment <20) | U21: No | V21: No | W21: 70 | X21: 0 | Y21: 0 | Z21: No | AB21: No | AC21: No | AD21: Yes | AE21: 1 | AF21: Moderate obstacle | AG21: Very severe obstacle | AH21: No obstacle | AI21: Major obstacle | AJ21: Electricity | AK21: Are taken directly from establishment records | AL21: =IF(H21="","",2024-H21) -> 24 | AM21: =IFERROR(IF(Z21="No",0,IF(Z21="Yes",AA21,"")),"") -> 0 | AN21: =IFERROR(IF(AD21="No",0,IF(AD21="Yes",AE21,"")),"") -> 1 | AO21: =IF(S21>0,"Yes","No") -> No | AP21: =IF(OR(K21="",L21="",L21<=0),"",K21/L21-1) -> 0.069444444 | AQ21: =IF(OR(K21="",L21="",L21<=0),"",(K21/L21)^(1/2)-1) -> 0.03413947 | AR21: =IF(OR(N21="",O21="",O21<=0),"",N21/O21-1) -> 0 | AS21: =IF(OR(K21="",N21="",N21<=0),"",K21/N21) -> 22000000 | AT21: =IF(OR(P21="",K21="",K21<=0),"",P21/K21) -> 0.14025974 | AU21: =IF(OR(Q21="",K21="",K21<=0),"",Q21/K21) -> 0.22727273 | AV21: =IF(OR(R21="",N21="",N21<=0),"",R21/N21) -> 42857143 | AW21: =IFERROR(IF(Z21="No",0,IF(Z21="Yes",AM21/K21,"")),"") -> 0 | AX21: =IF(OR(K21<Outlier_Audit!$H$2,K21>Outlier_Audit!$I$2),"Review","Normal") -> Normal | AY21: =IF(AL21="","Unknown",IF(AL21<10,"<10 years",IF(AL21<20,"10-19 years",IF(AL21<30,"20-29 years","30+ years")))) -> 20-29 years | AZ21: =IF(AQ21="","Missing",IF(AQ21>=EDA_Performance!$B$7,"High Growth",IF(AQ21<=EDA_Performance!$B$5,"Low Growth","Middle"))) -> Low Growth
A22: 1614163 | B22: Northern | C22: Small | D22: 30 | E22: 1040 | F22: 10 | G22: Manufacture of food products | H22: 1994 | I22: 4 | J22: 1 | K22: 2165000000 | L22: 1800000000 | M22: 100 | N22: 15 | O22: 10 | P22: 720000000 | Q22: 900000000 | R22: 10000000000 | S22: 0 | T22: Yes | U22: Yes | V22: No | W22: 0 | X22: 0 | Y22: 30 | Z22: Yes | AA22: 100000000 | AB22: No | AC22: No | AD22: Yes | AE22: 3 | AF22: Minor obstacle | AG22: No obstacle | AH22: No obstacle | AI22: Major obstacle | AJ22: Access to land | AK22: Are taken directly from establishment records | AL22: =IF(H22="","",2024-H22) -> 30 | AM22: =IFERROR(IF(Z22="No",0,IF(Z22="Yes",AA22,"")),"") -> 100000000 | AN22: =IFERROR(IF(AD22="No",0,IF(AD22="Yes",AE22,"")),"") -> 3 | AO22: =IF(S22>0,"Yes","No") -> No | AP22: =IF(OR(K22="",L22="",L22<=0),"",K22/L22-1) -> 0.20277778 | AQ22: =IF(OR(K22="",L22="",L22<=0),"",(K22/L22)^(1/2)-1) -> 0.096712258 | AR22: =IF(OR(N22="",O22="",O22<=0),"",N22/O22-1) -> 0.5 | AS22: =IF(OR(K22="",N22="",N22<=0),"",K22/N22) -> 1.4433333e+08 | AT22: =IF(OR(P22="",K22="",K22<=0),"",P22/K22) -> 0.33256351 | AU22: =IF(OR(Q22="",K22="",K22<=0),"",Q22/K22) -> 0.41570439 | AV22: =IF(OR(R22="",N22="",N22<=0),"",R22/N22) -> 6.6666667e+08 | AW22: =IFERROR(IF(Z22="No",0,IF(Z22="Yes",AM22/K22,"")),"") -> 0.046189376 | AX22: =IF(OR(K22<Outlier_Audit!$H$2,K22>Outlier_Audit!$I$2),"Review","Normal") -> Normal | AY22: =IF(AL22="","Unknown",IF(AL22<10,"<10 years",IF(AL22<20,"10-19 years",IF(AL22<30,"20-29 years","30+ years")))) -> 30+ years | AZ22: =IF(AQ22="","Missing",IF(AQ22>=EDA_Performance!$B$7,"High Growth",IF(AQ22<=EDA_Performance!$B$5,"Low Growth","Middle"))) -> Middle
A23: 1614165 | B23: Eastern | C23: Medium | D23: 13 | E23: 1061 | F23: 10 | G23: Manufacture of food products | H23: 2006 | I23: 22 | J23: 2.7846396 | K23: 600000000 | L23: 400000000 | M23: 90 | N23: 7 | O23: 8 | P23: 62400000 | Q23: 40000000 | R23: 90000000 | S23: 0 | T23: Not asked (survey skip: screener employment <20) | U23: Yes | V23: No | W23: 100 | X23: 0 | Y23: 0 | Z23: No | AB23: No | AC23: Yes | AD23: Yes | AE23: 3 | AF23: Major obstacle | AG23: Major obstacle | AH23: Minor obstacle | AI23: Moderate obstacle | AJ23: Practices of competitors in the informal sector | AK23: Are taken directly from establishment records | AL23: =IF(H23="","",2024-H23) -> 18 | AM23: =IFERROR(IF(Z23="No",0,IF(Z23="Yes",AA23,"")),"") -> 0 | AN23: =IFERROR(IF(AD23="No",0,IF(AD23="Yes",AE23,"")),"") -> 3 | AO23: =IF(S23>0,"Yes","No") -> No | AP23: =IF(OR(K23="",L23="",L23<=0),"",K23/L23-1) -> 0.5 | AQ23: =IF(OR(K23="",L23="",L23<=0),"",(K23/L23)^(1/2)-1) -> 0.22474487 | AR23: =IF(OR(N23="",O23="",O23<=0),"",N23/O23-1) -> -0.125 | AS23: =IF(OR(K23="",N23="",N23<=0),"",K23/N23) -> 85714286 | AT23: =IF(OR(P23="",K23="",K23<=0),"",P23/K23) -> 0.104 | AU23: =IF(OR(Q23="",K23="",K23<=0),"",Q23/K23) -> 0.066666667 | AV23: =IF(OR(R23="",N23="",N23<=0),"",R23/N23) -> 12857143 | AW23: =IFERROR(IF(Z23="No",0,IF(Z23="Yes",AM23/K23,"")),"") -> 0 | AX23: =IF(OR(K23<Outlier_Audit!$H$2,K23>Outlier_Audit!$I$2),"Review","Normal") -> Normal | AY23: =IF(AL23="","Unknown",IF(AL23<10,"<10 years",IF(AL23<20,"10-19 years",IF(AL23<30,"20-29 years","30+ years")))) -> 10-19 years | AZ23: =IF(AQ23="","Missing",IF(AQ23>=EDA_Performance!$B$7,"High Growth",IF(AQ23<=EDA_Performance!$B$5,"Low Growth","Middle"))) -> Middle
A24: 1614170 | B24: Central | C24: Small | D24: 15 | E24: 2511 | F24: 25 | G24: Manufacture of fabricated metal products | H24: 2009 | I24: 22 | J24: 316.31961 | K24: 800000000 | L24: 500000000 | M24: 90 | N24: 15 | O24: 7 | P24: 25000000 | S24: 20 | T24: Not asked (survey skip: screener employment <20) | U24: Yes | V24: No | W24: 60 | X24: 20 | Y24: 0 | Z24: No | AB24: Yes | AC24: No | AD24: Yes | AE24: 8 | AF24: Minor obstacle | AG24: No obstacle | AH24: No obstacle | AI24: No obstacle | AJ24: Corruption | AK24: Are in some case taken from books and in some case estimates | AL24: =IF(H24="","",2024-H24) -> 15 | AM24: =IFERROR(IF(Z24="No",0,IF(Z24="Yes",AA24,"")),"") -> 0 | AN24: =IFERROR(IF(AD24="No",0,IF(AD24="Yes",AE24,"")),"") -> 8 | AO24: =IF(S24>0,"Yes","No") -> Yes | AP24: =IF(OR(K24="",L24="",L24<=0),"",K24/L24-1) -> 0.6 | AQ24: =IF(OR(K24="",L24="",L24<=0),"",(K24/L24)^(1/2)-1) -> 0.26491106 | AR24: =IF(OR(N24="",O24="",O24<=0),"",N24/O24-1) -> 1.1428571 | AS24: =IF(OR(K24="",N24="",N24<=0),"",K24/N24) -> 53333333 | AT24: =IF(OR(P24="",K24="",K24<=0),"",P24/K24) -> 0.03125 | AU24: =IF(OR(Q24="",K24="",K24<=0),"",Q24/K24) | AV24: =IF(OR(R24="",N24="",N24<=0),"",R24/N24) | AW24: =IFERROR(IF(Z24="No",0,IF(Z24="Yes",AM24/K24,"")),"") -> 0 | AX24: =IF(OR(K24<Outlier_Audit!$H$2,K24>Outlier_Audit!$I$2),"Review","Normal") -> Normal | AY24: =IF(AL24="","Unknown",IF(AL24<10,"<10 years",IF(AL24<20,"10-19 years",IF(AL24<30,"20-29 years","30+ years")))) -> 10-19 years | AZ24: =IF(AQ24="","Missing",IF(AQ24>=EDA_Performance!$B$7,"High Growth",IF(AQ24<=EDA_Performance!$B$5,"Low Growth","Middle"))) -> Middle
A25: 1614171 | B25: Eastern | C25: Small | D25: 10 | E25: 2511 | F25: 25 | G25: Manufacture of fabricated metal products | H25: 2007 | I25: 20 | J25: 90.16523 | K25: 70000000 | L25: 10000000 | M25: 70 | N25: 10 | O25: 3 | P25: 10000000 | Q25: 30000000 | R25: 170000000 | S25: 0 | T25: Not asked (survey skip: screener employment <20) | U25: No | V25: No | W25: 90 | X25: 0 | Y25: 0 | Z25: No | AB25: No | AC25: No | AD25: Yes | AE25: 3 | AF25: Moderate obstacle | AG25: No obstacle | AH25: No obstacle | AI25: No obstacle | AJ25: Electricity | AK25: Are taken directly from establishment records | AL25: =IF(H25="","",2024-H25) -> 17 | AM25: =IFERROR(IF(Z25="No",0,IF(Z25="Yes",AA25,"")),"") -> 0 | AN25: =IFERROR(IF(AD25="No",0,IF(AD25="Yes",AE25,"")),"") -> 3 | AO25: =IF(S25>0,"Yes","No") -> No | AP25: =IF(OR(K25="",L25="",L25<=0),"",K25/L25-1) -> 6 | AQ25: =IF(OR(K25="",L25="",L25<=0),"",(K25/L25)^(1/2)-1) -> 1.6457513 | AR25: =IF(OR(N25="",O25="",O25<=0),"",N25/O25-1) -> 2.3333333 | AS25: =IF(OR(K25="",N25="",N25<=0),"",K25/N25) -> 7000000 | AT25: =IF(OR(P25="",K25="",K25<=0),"",P25/K25) -> 0.14285714 | AU25: =IF(OR(Q25="",K25="",K25<=0),"",Q25/K25) -> 0.42857143 | AV25: =IF(OR(R25="",N25="",N25<=0),"",R25/N25) -> 17000000 | AW25: =IFERROR(IF(Z25="No",0,IF(Z25="Yes",AM25/K25,"")),"") -> 0 | AX25: =IF(OR(K25<Outlier_Audit!$H$2,K25>Outlier_Audit!$I$2),"Review","Normal") -> Normal | AY25: =IF(AL25="","Unknown",IF(AL25<10,"<10 years",IF(AL25<20,"10-19 years",IF(AL25<30,"20-29 years","30+ years")))) -> 10-19 years | AZ25: =IF(AQ25="","Missing",IF(AQ25>=EDA_Performance!$B$7,"High Growth",IF(AQ25<=EDA_Performance!$B$5,"Low Growth","Middle"))) -> High Growth
A26: 1614174 | B26: Northern | C26: Small | D26: 6 | E26: 1811 | F26: 18 | G26: Printing and reproduction of recorded media | H26: 1997 | I26: 30 | J26: 18.668732 | K26: 15000000 | L26: 12000000 | M26: 100 | N26: 6 | O26: 6 | P26: 4000000 | Q26: 5000000 | R26: 100000000 | S26: 0 | T26: Not asked (survey skip: screener employment <20) | U26: No | V26: No | W26: 50 | X26: 50 | Y26: 0 | Z26: No | AB26: No | AC26: No | AD26: Yes | AE26: 5 | AF26: Major obstacle | AG26: Minor obstacle | AH26: Minor obstacle | AI26: Minor obstacle | AJ26: Business licensing and permits | AK26: Are in some case taken from books and in some case estimates | AL26: =IF(H26="","",2024-H26) -> 27 | AM26: =IFERROR(IF(Z26="No",0,IF(Z26="Yes",AA26,"")),"") -> 0 | AN26: =IFERROR(IF(AD26="No",0,IF(AD26="Yes",AE26,"")),"") -> 5 | AO26: =IF(S26>0,"Yes","No") -> No | AP26: =IF(OR(K26="",L26="",L26<=0),"",K26/L26-1) -> 0.25 | AQ26: =IF(OR(K26="",L26="",L26<=0),"",(K26/L26)^(1/2)-1) -> 0.11803399 | AR26: =IF(OR(N26="",O26="",O26<=0),"",N26/O26-1) -> 0 | AS26: =IF(OR(K26="",N26="",N26<=0),"",K26/N26) -> 2500000 | AT26: =IF(OR(P26="",K26="",K26<=0),"",P26/K26) -> 0.26666667 | AU26: =IF(OR(Q26="",K26="",K26<=0),"",Q26/K26) -> 0.33333333 | AV26: =IF(OR(R26="",N26="",N26<=0),"",R26/N26) -> 16666667 | AW26: =IFERROR(IF(Z26="No",0,IF(Z26="Yes",AM26/K26,"")),"") -> 0 | AX26: =IF(OR(K26<Outlier_Audit!$H$2,K26>Outlier_Audit!$I$2),"Review","Normal") -> Normal | AY26: =IF(AL26="","Unknown",IF(AL26<10,"<10 years",IF(AL26<20,"10-19 years",IF(AL26<30,"20-29 years","30+ years")))) -> 20-29 years | AZ26: =IF(AQ26="","Missing",IF(AQ26>=EDA_Performance!$B$7,"High Growth",IF(AQ26<=EDA_Performance!$B$5,"Low Growth","Middle"))) -> Middle
A27: 1614175 | B27: Northern | C27: Small | D27: 8 | E27: 1811 | F27: 18 | G27: Printing and reproduction of recorded media | H27: 2006 | I27: 19 | J27: 18.668732 | K27: 29430000 | L27: 22570000 | M27: 70 | N27: 4 | O27: 4 | P27: 8046000 | Q27: 17000000 | R27: 49570000 | S27: 0 | T27: Not asked (survey skip: screener employment <20) | U27: No | V27: No | W27: 60 | X27: 0 | Y27: 10 | Z27: Yes | AA27: 2460000 | AB27: No | AC27: No | AD27: Yes | AE27: 6 | AF27: Moderate obstacle | AG27: Minor obstacle | AH27: No obstacle | AI27: No obstacle | AJ27: Tax rates | AK27: Are estimates computed with some precision | AL27: =IF(H27="","",2024-H27) -> 18 | AM27: =IFERROR(IF(Z27="No",0,IF(Z27="Yes",AA27,"")),"") -> 2460000 | AN27: =IFERROR(IF(AD27="No",0,IF(AD27="Yes",AE27,"")),"") -> 6 | AO27: =IF(S27>0,"Yes","No") -> No | AP27: =IF(OR(K27="",L27="",L27<=0),"",K27/L27-1) -> 0.30394329 | AQ27: =IF(OR(K27="",L27="",L27<=0),"",(K27/L27)^(1/2)-1) -> 0.14190336 | AR27: =IF(OR(N27="",O27="",O27<=0),"",N27/O27-1) -> 0 | AS27: =IF(OR(K27="",N27="",N27<=0),"",K27/N27) -> 7357500 | AT27: =IF(OR(P27="",K27="",K27<=0),"",P27/K27) -> 0.2733945 | AU27: =IF(OR(Q27="",K27="",K27<=0),"",Q27/K27) -> 0.57764186 | AV27: =IF(OR(R27="",N27="",N27<=0),"",R27/N27) -> 12392500 | AW27: =IFERROR(IF(Z27="No",0,IF(Z27="Yes",AM27/K27,"")),"") -> 0.083588175 | AX27: =IF(OR(K27<Outlier_Audit!$H$2,K27>Outlier_Audit!$I$2),"Review","Normal") -> Normal | AY27: =IF(AL27="","Unknown",IF(AL27<10,"<10 years",IF(AL27<20,"10-19 years",IF(AL27<30,"20-29 years","30+ years")))) -> 10-19 years | AZ27: =IF(AQ27="","Missing",IF(AQ27>=EDA_Performance!$B$7,"High Growth",IF(AQ27<=EDA_Performance!$B$5,"Low Growth","Middle"))) -> Middle
A28: 1614176 | B28: Central | C28: Large | D28: 100 | E28: 3100 | F28: 31 | G28: Manufacture of furniture | H28: 1987 | I28: 30 | J28: 2.6891484 | K28: 15000000000 | L28: 10000000000 | M28: 40 | N28: 40 | O28: 35 | P28: 2000000000 | Q28: 500000000 | R28: 4000000000 | S28: 0 | T28: No | U28: No | V28: No | W28: 100 | X28: 0 | Y28: 0 | Z28: No | AB28: No | AC28: No | AD28: No | AF28: No obstacle | AG28: Minor obstacle | AH28: No obstacle | AI28: Moderate obstacle | AJ28: Practices of competitors in the informal sector | AK28: Are in some case taken from books and in some case estimates | AL28: =IF(H28="","",2024-H28) -> 37 | AM28: =IFERROR(IF(Z28="No",0,IF(Z28="Yes",AA28,"")),"") -> 0 | AN28: =IFERROR(IF(AD28="No",0,IF(AD28="Yes",AE28,"")),"") -> 0 | AO28: =IF(S28>0,"Yes","No") -> No | AP28: =IF(OR(K28="",L28="",L28<=0),"",K28/L28-1) -> 0.5 | AQ28: =IF(OR(K28="",L28="",L28<=0),"",(K28/L28)^(1/2)-1) -> 0.22474487 | AR28: =IF(OR(N28="",O28="",O28<=0),"",N28/O28-1) -> 0.14285714 | AS28: =IF(OR(K28="",N28="",N28<=0),"",K28/N28) -> 375000000 | AT28: =IF(OR(P28="",K28="",K28<=0),"",P28/K28) -> 0.13333333 | AU28: =IF(OR(Q28="",K28="",K28<=0),"",Q28/K28) -> 0.033333333 | AV28: =IF(OR(R28="",N28="",N28<=0),"",R28/N28) -> 100000000 | AW28: =IFERROR(IF(Z28="No",0,IF(Z28="Yes",AM28/K28,"")),"") -> 0 | AX28: =IF(OR(K28<Outlier_Audit!$H$2,K28>Outlier_Audit!$I$2),"Review","Normal") -> Review | AY28: =IF(AL28="","Unknown",IF(AL28<10,"<10 years",IF(AL28<20,"10-19 years",IF(AL28<30,"20-29 years","30+ years")))) -> 30+ years | AZ28: =IF(AQ28="","Missing",IF(AQ28>=EDA_Performance!$B$7,"High Growth",IF(AQ28<=EDA_Performance!$B$5,"Low Growth","Middle"))) -> Middle
A29: 1614178 | B29: Central | C29: Large | D29: 10 | E29: 2599 | F29: 25 | G29: Manufacture of fabricated metal products | H29: 1984 | I29: 41 | J29: 1 | K29: 30000000 | L29: 40000000 | M29: 85 | N29: 7 | O29: 10 | P29: 4000000 | Q29: 13000000 | R29: 35000000 | S29: 0 | T29: Not asked (survey skip: screener employment <20) | U29: Yes | V29: No | W29: 70 | X29: 30 | Y29: 0 | Z29: No | AB29: Yes | AC29: No | AD29: Yes | AE29: 3 | AF29: Minor obstacle | AG29: Minor obstacle | AH29: Minor obstacle | AI29: Moderate obstacle | AJ29: Tax rates | AK29: Are taken directly from establishment records | AL29: =IF(H29="","",2024-H29) -> 40 | AM29: =IFERROR(IF(Z29="No",0,IF(Z29="Yes",AA29,"")),"") -> 0 | AN29: =IFERROR(IF(AD29="No",0,IF(AD29="Yes",AE29,"")),"") -> 3 | AO29: =IF(S29>0,"Yes","No") -> No | AP29: =IF(OR(K29="",L29="",L29<=0),"",K29/L29-1) -> -0.25 | AQ29: =IF(OR(K29="",L29="",L29<=0),"",(K29/L29)^(1/2)-1) -> -0.1339746 | AR29: =IF(OR(N29="",O29="",O29<=0),"",N29/O29-1) -> -0.3 | AS29: =IF(OR(K29="",N29="",N29<=0),"",K29/N29) -> 4285714.3 | AT29: =IF(OR(P29="",K29="",K29<=0),"",P29/K29) -> 0.13333333 | AU29: =IF(OR(Q29="",K29="",K29<=0),"",Q29/K29) -> 0.43333333 | AV29: =IF(OR(R29="",N29="",N29<=0),"",R29/N29) -> 5000000 | AW29: =IFERROR(IF(Z29="No",0,IF(Z29="Yes",AM29/K29,"")),"") -> 0 | AX29: =IF(OR(K29<Outlier_Audit!$H$2,K29>Outlier_Audit!$I$2),"Review","Normal") -> Normal | AY29: =IF(AL29="","Unknown",IF(AL29<10,"<10 years",IF(AL29<20,"10-19 years",IF(AL29<30,"20-29 years","30+ years")))) -> 30+ years | AZ29: =IF(AQ29="","Missing",IF(AQ29>=EDA_Performance!$B$7,"High Growth",IF(AQ29<=EDA_Performance!$B$5,"Low Growth","Middle"))) -> Low Growth
A30: 1614179 | B30: Central | C30: Large | D30: 94 | E30: 2395 | F30: 23 | G30: Manufacture of other non-metallic mineral products | H30: 2004 | I30: 20 | J30: 1.5225753 | K30: 2000000000 | L30: 1600000000 | M30: 76 | N30: 92 | O30: 76 | Q30: 500000000 | R30: 1800000000 | S30: 0 | T30: Yes | U30: Yes | V30: Yes | W30: 100 | X30: 0 | Y30: 0 | Z30: Yes | AA30: 1800000000 | AB30: No | AC30: No | AD30: Yes | AE30: 10 | AF30: Major obstacle | AG30: Minor obstacle | AH30: No obstacle | AI30: Moderate obstacle | AJ30: Electricity | AK30: Are taken directly from establishment records | AL30: =IF(H30="","",2024-H30) -> 20 | AM30: =IFERROR(IF(Z30="No",0,IF(Z30="Yes",AA30,"")),"") -> 1800000000 | AN30: =IFERROR(IF(AD30="No",0,IF(AD30="Yes",AE30,"")),"") -> 10 | AO30: =IF(S30>0,"Yes","No") -> No | AP30: =IF(OR(K30="",L30="",L30<=0),"",K30/L30-1) -> 0.25 | AQ30: =IF(OR(K30="",L30="",L30<=0),"",(K30/L30)^(1/2)-1) -> 0.11803399 | AR30: =IF(OR(N30="",O30="",O30<=0),"",N30/O30-1) -> 0.21052632 | AS30: =IF(OR(K30="",N30="",N30<=0),"",K30/N30) -> 21739130 | AT30: =IF(OR(P30="",K30="",K30<=0),"",P30/K30) | AU30: =IF(OR(Q30="",K30="",K30<=0),"",Q30/K30) -> 0.25 | AV30: =IF(OR(R30="",N30="",N30<=0),"",R30/N30) -> 19565217 | AW30: =IFERROR(IF(Z30="No",0,IF(Z30="Yes",AM30/K30,"")),"") -> 0.9 | AX30: =IF(OR(K30<Outlier_Audit!$H$2,K30>Outlier_Audit!$I$2),"Review","Normal") -> Normal | AY30: =IF(AL30="","Unknown",IF(AL30<10,"<10 years",IF(AL30<20,"10-19 years",IF(AL30<30,"20-29 years","30+ years")))) -> 20-29 years | AZ30: =IF(AQ30="","Missing",IF(AQ30>=EDA_Performance!$B$7,"High Growth",IF(AQ30<=EDA_Performance!$B$5,"Low Growth","Middle"))) -> Middle
A31: 1614180 | B31: Western | C31: Medium | D31: 30 | E31: 1071 | F31: 10 | G31: Manufacture of food products | H31: 2000 | I31: 30 | J31: 1.9028108 | K31: 800000000 | L31: 760000000 | M31: 10 | N31: 25 | O31: 27 | P31: 30000000 | Q31: 450000000 | R31: 400000000 | S31: 0 | T31: Yes | U31: Yes | V31: Yes | W31: 70 | X31: 0 | Y31: 30 | Z31: Yes | AA31: 200000000 | AB31: No | AC31: No | AD31: Yes | AE31: 0 | AF31: Moderate obstacle | AG31: Moderate obstacle | AH31: Major obstacle | AI31: Moderate obstacle | AJ31: Corruption | AK31: Are estimates computed with some precision | AL31: =IF(H31="","",2024-H31) -> 24 | AM31: =IFERROR(IF(Z31="No",0,IF(Z31="Yes",AA31,"")),"") -> 200000000 | AN31: =IFERROR(IF(AD31="No",0,IF(AD31="Yes",AE31,"")),"") -> 0 | AO31: =IF(S31>0,"Yes","No") -> No | AP31: =IF(OR(K31="",L31="",L31<=0),"",K31/L31-1) -> 0.052631579 | AQ31: =IF(OR(K31="",L31="",L31<=0),"",(K31/L31)^(1/2)-1) -> 0.025978352 | AR31: =IF(OR(N31="",O31="",O31<=0),"",N31/O31-1) -> -0.074074074 | AS31: =IF(OR(K31="",N31="",N31<=0),"",K31/N31) -> 32000000 | AT31: =IF(OR(P31="",K31="",K31<=0),"",P31/K31) -> 0.0375 | AU31: =IF(OR(Q31="",K31="",K31<=0),"",Q31/K31) -> 0.5625 | AV31: =IF(OR(R31="",N31="",N31<=0),"",R31/N31) -> 16000000 | AW31: =IFERROR(IF(Z31="No",0,IF(Z31="Yes",AM31/K31,"")),"") -> 0.25 | AX31: =IF(OR(K31<Outlier_Audit!$H$2,K31>Outlier_Audit!$I$2),"Review","Normal") -> Normal | AY31: =IF(AL31="","Unknown",IF(AL31<10,"<10 years",IF(AL31<20,"10-19 years",IF(AL31<30,"20-29 years","30+ years")))) -> 20-29 years | AZ31: =IF(AQ31="","Missing",IF(AQ31>=EDA_Performance!$B$7,"High Growth",IF(AQ31<=EDA_Performance!$B$5,"Low Growth","Middle"))) -> Low Growth
A32: 1614182 | B32: Central | C32: Small | D32: 15 | E32: 2819 | F32: 28 | G32: Manufacture of machinery and equipment n.e.c. | H32: 2001 | I32: 15 | J32: 143.61815 | M32: 60 | N32: 20 | O32: 15 | S32: 0 | T32: Not asked (survey skip: screener employment <20) | U32: No | V32: No | W32: 100 | X32: 0 | Y32: 0 | Z32: Yes | AA32: 0 | AB32: No | AC32: No | AD32: Yes | AE32: 8 | AF32: Very severe obstacle | AG32: Very severe obstacle | AH32: No obstacle | AI32: Very severe obstacle | AJ32: Access to finance | AK32: Are arbitrary and unreliable numbers | AL32: =IF(H32="","",2024-H32) -> 23 | AM32: =IFERROR(IF(Z32="No",0,IF(Z32="Yes",AA32,"")),"") -> 0 | AN32: =IFERROR(IF(AD32="No",0,IF(AD32="Yes",AE32,"")),"") -> 8 | AO32: =IF(S32>0,"Yes","No") -> No | AP32: =IF(OR(K32="",L32="",L32<=0),"",K32/L32-1) | AQ32: =IF(OR(K32="",L32="",L32<=0),"",(K32/L32)^(1/2)-1) | AR32: =IF(OR(N32="",O32="",O32<=0),"",N32/O32-1) -> 0.33333333 | AS32: =IF(OR(K32="",N32="",N32<=0),"",K32/N32) | AT32: =IF(OR(P32="",K32="",K32<=0),"",P32/K32) | AU32: =IF(OR(Q32="",K32="",K32<=0),"",Q32/K32) | AV32: =IF(OR(R32="",N32="",N32<=0),"",R32/N32) | AW32: =IFERROR(IF(Z32="No",0,IF(Z32="Yes",AM32/K32,"")),"") | AX32: =IF(OR(K32<Outlier_Audit!$H$2,K32>Outlier_Audit!$I$2),"Review","Normal") -> Normal | AY32: =IF(AL32="","Unknown",IF(AL32<10,"<10 years",IF(AL32<20,"10-19 years",IF(AL32<30,"20-29 years","30+ years")))) -> 20-29 years | AZ32: =IF(AQ32="","Missing",IF(AQ32>=EDA_Performance!$B$7,"High Growth",IF(AQ32<=EDA_Performance!$B$5,"Low Growth","Middle"))) -> Missing
A33: 1614183 | B33: Western | C33: Medium | D33: 12 | E33: 1071 | F33: 10 | G33: Manufacture of food products | H33: 2015 | I33: 10 | J33: 1.5243006 | K33: 217920000 | M33: 2 | N33: 12 | O33: 24 | P33: 36950400 | Q33: 172800000 | R33: 6000000 | S33: 0 | T33: Not asked (survey skip: screener employment <20) | U33: Yes | V33: Yes | W33: 80 | X33: 0 | Y33: 20 | Z33: No | AB33: No | AC33: No | AD33: Yes | AE33: 4 | AF33: Minor obstacle | AG33: Very severe obstacle | AH33: No obstacle | AI33: No obstacle | AJ33: Access to finance | AK33: Are estimates computed with some precision | AL33: =IF(H33="","",2024-H33) -> 9 | AM33: =IFERROR(IF(Z33="No",0,IF(Z33="Yes",AA33,"")),"") -> 0 | AN33: =IFERROR(IF(AD33="No",0,IF(AD33="Yes",AE33,"")),"") -> 4 | AO33: =IF(S33>0,"Yes","No") -> No | AP33: =IF(OR(K33="",L33="",L33<=0),"",K33/L33-1) | AQ33: =IF(OR(K33="",L33="",L33<=0),"",(K33/L33)^(1/2)-1) | AR33: =IF(OR(N33="",O33="",O33<=0),"",N33/O33-1) -> -0.5 | AS33: =IF(OR(K33="",N33="",N33<=0),"",K33/N33) -> 18160000 | AT33: =IF(OR(P33="",K33="",K33<=0),"",P33/K33) -> 0.16955947 | AU33: =IF(OR(Q33="",K33="",K33<=0),"",Q33/K33) -> 0.79295154 | AV33: =IF(OR(R33="",N33="",N33<=0),"",R33/N33) -> 500000 | AW33: =IFERROR(IF(Z33="No",0,IF(Z33="Yes",AM33/K33,"")),"") -> 0 | AX33: =IF(OR(K33<Outlier_Audit!$H$2,K33>Outlier_Audit!$I$2),"Review","Normal") -> Normal | AY33: =IF(AL33="","Unknown",IF(AL33<10,"<10 years",IF(AL33<20,"10-19 years",IF(AL33<30,"20-29 years","30+ years")))) -> <10 years | AZ33: =IF(AQ33="","Missing",IF(AQ33>=EDA_Performance!$B$7,"High Growth",IF(AQ33<=EDA_Performance!$B$5,"Low Growth","Middle"))) -> Missing
A34: 1614185 | B34: Central | C34: Small | D34: 7 | E34: 1811 | F34: 18 | G34: Printing and reproduction of recorded media | H34: 2000 | I34: 14 | J34: 157.86736 | K34: 30000000 | L34: 20000000 | M34: 90 | N34: 8 | O34: 2 | P34: 10000000 | Q34: 15000000 | R34: 40000000 | S34: 0 | T34: Not asked (survey skip: screener employment <20) | U34: No | V34: No | W34: 20 | X34: 0 | Y34: 70 | Z34: No | AB34: No | AC34: No | AD34: No | AF34: Minor obstacle | AG34: Minor obstacle | AH34: Minor obstacle | AI34: No obstacle | AJ34: Tax rates | AK34: Are in some case taken from books and in some case estimates | AL34: =IF(H34="","",2024-H34) -> 24 | AM34: =IFERROR(IF(Z34="No",0,IF(Z34="Yes",AA34,"")),"") -> 0 | AN34: =IFERROR(IF(AD34="No",0,IF(AD34="Yes",AE34,"")),"") -> 0 | AO34: =IF(S34>0,"Yes","No") -> No | AP34: =IF(OR(K34="",L34="",L34<=0),"",K34/L34-1) -> 0.5 | AQ34: =IF(OR(K34="",L34="",L34<=0),"",(K34/L34)^(1/2)-1) -> 0.22474487 | AR34: =IF(OR(N34="",O34="",O34<=0),"",N34/O34-1) -> 3 | AS34: =IF(OR(K34="",N34="",N34<=0),"",K34/N34) -> 3750000 | AT34: =IF(OR(P34="",K34="",K34<=0),"",P34/K34) -> 0.33333333 | AU34: =IF(OR(Q34="",K34="",K34<=0),"",Q34/K34) -> 0.5 | AV34: =IF(OR(R34="",N34="",N34<=0),"",R34/N34) -> 5000000 | AW34: =IFERROR(IF(Z34="No",0,IF(Z34="Yes",AM34/K34,"")),"") -> 0 | AX34: =IF(OR(K34<Outlier_Audit!$H$2,K34>Outlier_Audit!$I$2),"Review","Normal") -> Normal | AY34: =IF(AL34="","Unknown",IF(AL34<10,"<10 years",IF(AL34<20,"10-19 years",IF(AL34<30,"20-29 years","30+ years")))) -> 20-29 years | AZ34: =IF(AQ34="","Missing",IF(AQ34>=EDA_Performance!$B$7,"High Growth",IF(AQ34<=EDA_Performance!$B$5,"Low Growth","Middle"))) -> Middle
A35: 1614193 | B35: Eastern | C35: Large | D35: 300 | E35: 1061 | F35: 10 | G35: Manufacture of food products | H35: 2009 | I35: 30 | J35: 1 | K35: 1200000000 | L35: 1000000000 | M35: 60 | N35: 300 | O35: 250 | P35: 200000000 | Q35: 500000000 | R35: 600000000 | S35: 30 | T35: Yes | U35: No | V35: Yes | W35: 60 | X35: 40 | Y35: 0 | Z35: No | AB35: No | AC35: No | AD35: Yes | AE35: 2 | AF35: Moderate obstacle | AG35: Moderate obstacle | AH35: Minor obstacle | AI35: Minor obstacle | AJ35: Tax rates | AK35: Are in some case taken from books and in some case estimates | AL35: =IF(H35="","",2024-H35) -> 15 | AM35: =IFERROR(IF(Z35="No",0,IF(Z35="Yes",AA35,"")),"") -> 0 | AN35: =IFERROR(IF(AD35="No",0,IF(AD35="Yes",AE35,"")),"") -> 2 | AO35: =IF(S35>0,"Yes","No") -> Yes | AP35: =IF(OR(K35="",L35="",L35<=0),"",K35/L35-1) -> 0.2 | AQ35: =IF(OR(K35="",L35="",L35<=0),"",(K35/L35)^(1/2)-1) -> 0.095445115 | AR35: =IF(OR(N35="",O35="",O35<=0),"",N35/O35-1) -> 0.2 | AS35: =IF(OR(K35="",N35="",N35<=0),"",K35/N35) -> 4000000 | AT35: =IF(OR(P35="",K35="",K35<=0),"",P35/K35) -> 0.16666667 | AU35: =IF(OR(Q35="",K35="",K35<=0),"",Q35/K35) -> 0.41666667 | AV35: =IF(OR(R35="",N35="",N35<=0),"",R35/N35) -> 2000000 | AW35: =IFERROR(IF(Z35="No",0,IF(Z35="Yes",AM35/K35,"")),"") -> 0 | AX35: =IF(OR(K35<Outlier_Audit!$H$2,K35>Outlier_Audit!$I$2),"Review","Normal") -> Normal | AY35: =IF(AL35="","Unknown",IF(AL35<10,"<10 years",IF(AL35<20,"10-19 years",IF(AL35<30,"20-29 years","30+ years")))) -> 10-19 years | AZ35: =IF(AQ35="","Missing",IF(AQ35>=EDA_Performance!$B$7,"High Growth",IF(AQ35<=EDA_Performance!$B$5,"Low Growth","Middle"))) -> Middle
A36: 1614202 | B36: Western | C36: Small | D36: 5 | E36: 2511 | F36: 25 | G36: Manufacture of fabricated metal products | H36: 1996 | I36: 40 | J36: 68.62606 | K36: 12000000 | N36: 5 | O36: 6 | R36: 2500000 | S36: 0 | T36: Not asked (survey skip: screener employment <20) | U36: Yes | V36: No | W36: 20 | X36: 0 | Y36: 80 | Z36: No | AB36: No | AC36: No | AF36: Major obstacle | AG36: Moderate obstacle | AH36: Minor obstacle | AI36: Major obstacle | AJ36: Crime, theft and disorder | AK36: Are estimates computed with some precision | AL36: =IF(H36="","",2024-H36) -> 28 | AM36: =IFERROR(IF(Z36="No",0,IF(Z36="Yes",AA36,"")),"") -> 0 | AN36: =IFERROR(IF(AD36="No",0,IF(AD36="Yes",AE36,"")),"") | AO36: =IF(S36>0,"Yes","No") -> No | AP36: =IF(OR(K36="",L36="",L36<=0),"",K36/L36-1) | AQ36: =IF(OR(K36="",L36="",L36<=0),"",(K36/L36)^(1/2)-1) | AR36: =IF(OR(N36="",O36="",O36<=0),"",N36/O36-1) -> -0.16666667 | AS36: =IF(OR(K36="",N36="",N36<=0),"",K36/N36) -> 2400000 | AT36: =IF(OR(P36="",K36="",K36<=0),"",P36/K36) | AU36: =IF(OR(Q36="",K36="",K36<=0),"",Q36/K36) | AV36: =IF(OR(R36="",N36="",N36<=0),"",R36/N36) -> 500000 | AW36: =IFERROR(IF(Z36="No",0,IF(Z36="Yes",AM36/K36,"")),"") -> 0 | AX36: =IF(OR(K36<Outlier_Audit!$H$2,K36>Outlier_Audit!$I$2),"Review","Normal") -> Normal | AY36: =IF(AL36="","Unknown",IF(AL36<10,"<10 years",IF(AL36<20,"10-19 years",IF(AL36<30,"20-29 years","30+ years")))) -> 20-29 years | AZ36: =IF(AQ36="","Missing",IF(AQ36>=EDA_Performance!$B$7,"High Growth",IF(AQ36<=EDA_Performance!$B$5,"Low Growth","Middle"))) -> Missing
A37: 1614203 | B37: Central | C37: Large | D37: 55 | E37: 2599 | F37: 25 | G37: Manufacture of fabricated metal products | H37: 1956 | I37: 50 | J37: 1 | K37: 750000000 | L37: 500000000 | M37: 65 | N37: 53 | O37: 65 | P37: 50000000 | Q37: 300000000 | R37: 350000000 | S37: 0 | T37: Yes | U37: Yes | V37: No | W37: 70 | X37: 0 | Y37: 0 | Z37: No | AB37: No | AC37: No | AD37: Yes | AE37: 4 | AF37: Moderate obstacle | AG37: Moderate obstacle | AH37: Minor obstacle | AI37: Moderate obstacle | AJ37: Tax rates | AK37: Are taken directly from establishment records | AL37: =IF(H37="","",2024-H37) -> 68 | AM37: =IFERROR(IF(Z37="No",0,IF(Z37="Yes",AA37,"")),"") -> 0 | AN37: =IFERROR(IF(AD37="No",0,IF(AD37="Yes",AE37,"")),"") -> 4 | AO37: =IF(S37>0,"Yes","No") -> No | AP37: =IF(OR(K37="",L37="",L37<=0),"",K37/L37-1) -> 0.5 | AQ37: =IF(OR(K37="",L37="",L37<=0),"",(K37/L37)^(1/2)-1) -> 0.22474487 | AR37: =IF(OR(N37="",O37="",O37<=0),"",N37/O37-1) -> -0.18461538 | AS37: =IF(OR(K37="",N37="",N37<=0),"",K37/N37) -> 14150943 | AT37: =IF(OR(P37="",K37="",K37<=0),"",P37/K37) -> 0.066666667 | AU37: =IF(OR(Q37="",K37="",K37<=0),"",Q37/K37) -> 0.4 | AV37: =IF(OR(R37="",N37="",N37<=0),"",R37/N37) -> 6603773.6 | AW37: =IFERROR(IF(Z37="No",0,IF(Z37="Yes",AM37/K37,"")),"") -> 0 | AX37: =IF(OR(K37<Outlier_Audit!$H$2,K37>Outlier_Audit!$I$2),"Review","Normal") -> Normal | AY37: =IF(AL37="","Unknown",IF(AL37<10,"<10 years",IF(AL37<20,"10-19 years",IF(AL37<30,"20-29 years","30+ years")))) -> 30+ years | AZ37: =IF(AQ37="","Missing",IF(AQ37>=EDA_Performance!$B$7,"High Growth",IF(AQ37<=EDA_Performance!$B$5,"Low Growth","Middle"))) -> Middle
A38: 1614206 | B38: Northern | C38: Medium | D38: 6 | E38: 1811 | F38: 18 | G38: Printing and reproduction of recorded media | H38: 2010 | I38: 12 | J38: 1.8398361 | K38: 16450000 | L38: 8210000 | M38: 70 | N38: 4 | O38: 2 | P38: 2165000 | Q38: 7000000 | R38: 70500000 | S38: 0 | T38: Not asked (survey skip: screener employment <20) | U38: No | V38: No | W38: 70 | X38: 0 | Y38: 0 | Z38: No | AB38: No | AC38: No | AD38: Yes | AE38: 5 | AF38: Minor obstacle | AG38: Moderate obstacle | AH38: Major obstacle | AI38: Minor obstacle | AJ38: Tax administration | AK38: Are estimates computed with some precision | AL38: =IF(H38="","",2024-H38) -> 14 | AM38: =IFERROR(IF(Z38="No",0,IF(Z38="Yes",AA38,"")),"") -> 0 | AN38: =IFERROR(IF(AD38="No",0,IF(AD38="Yes",AE38,"")),"") -> 5 | AO38: =IF(S38>0,"Yes","No") -> No | AP38: =IF(OR(K38="",L38="",L38<=0),"",K38/L38-1) -> 1.0036541 | AQ38: =IF(OR(K38="",L38="",L38<=0),"",(K38/L38)^(1/2)-1) -> 0.41550489 | AR38: =IF(OR(N38="",O38="",O38<=0),"",N38/O38-1) -> 1 | AS38: =IF(OR(K38="",N38="",N38<=0),"",K38/N38) -> 4112500 | AT38: =IF(OR(P38="",K38="",K38<=0),"",P38/K38) -> 0.13161094 | AU38: =IF(OR(Q38="",K38="",K38<=0),"",Q38/K38) -> 0.42553191 | AV38: =IF(OR(R38="",N38="",N38<=0),"",R38/N38) -> 17625000 | AW38: =IFERROR(IF(Z38="No",0,IF(Z38="Yes",AM38/K38,"")),"") -> 0 | AX38: =IF(OR(K38<Outlier_Audit!$H$2,K38>Outlier_Audit!$I$2),"Review","Normal") -> Normal | AY38: =IF(AL38="","Unknown",IF(AL38<10,"<10 years",IF(AL38<20,"10-19 years",IF(AL38<30,"20-29 years","30+ years")))) -> 10-19 years | AZ38: =IF(AQ38="","Missing",IF(AQ38>=EDA_Performance!$B$7,"High Growth",IF(AQ38<=EDA_Performance!$B$5,"Low Growth","Middle"))) -> High Growth
A39: 1614208 | B39: Western | C39: Small | D39: 6 | E39: 1410 | F39: 14 | G39: Manufacture of wearing apparel | H39: 2000 | I39: 25 | J39: 46.711292 | K39: 40000000 | L39: 15000000 | M39: 50 | N39: 6 | O39: 6 | Q39: 30000000 | R39: 11100000 | S39: 0 | T39: Not asked (survey skip: screener employment <20) | U39: Yes | V39: Yes | W39: 73 | X39: 0 | Y39: 7 | Z39: Yes | AA39: 2500000 | AB39: Yes | AC39: Yes | AD39: Yes | AE39: 3 | AF39: Major obstacle | AG39: No obstacle | AH39: No obstacle | AI39: No obstacle | AJ39: Crime, theft and disorder | AK39: Are estimates computed with some precision | AL39: =IF(H39="","",2024-H39) -> 24 | AM39: =IFERROR(IF(Z39="No",0,IF(Z39="Yes",AA39,"")),"") -> 2500000 | AN39: =IFERROR(IF(AD39="No",0,IF(AD39="Yes",AE39,"")),"") -> 3 | AO39: =IF(S39>0,"Yes","No") -> No | AP39: =IF(OR(K39="",L39="",L39<=0),"",K39/L39-1) -> 1.6666667 | AQ39: =IF(OR(K39="",L39="",L39<=0),"",(K39/L39)^(1/2)-1) -> 0.63299316 | AR39: =IF(OR(N39="",O39="",O39<=0),"",N39/O39-1) -> 0 | AS39: =IF(OR(K39="",N39="",N39<=0),"",K39/N39) -> 6666666.7 | AT39: =IF(OR(P39="",K39="",K39<=0),"",P39/K39) | AU39: =IF(OR(Q39="",K39="",K39<=0),"",Q39/K39) -> 0.75 | AV39: =IF(OR(R39="",N39="",N39<=0),"",R39/N39) -> 1850000 | AW39: =IFERROR(IF(Z39="No",0,IF(Z39="Yes",AM39/K39,"")),"") -> 0.0625 | AX39: =IF(OR(K39<Outlier_Audit!$H$2,K39>Outlier_Audit!$I$2),"Review","Normal") -> Normal | AY39: =IF(AL39="","Unknown",IF(AL39<10,"<10 years",IF(AL39<20,"10-19 years",IF(AL39<30,"20-29 years","30+ years")))) -> 20-29 years | AZ39: =IF(AQ39="","Missing",IF(AQ39>=EDA_Performance!$B$7,"High Growth",IF(AQ39<=EDA_Performance!$B$5,"Low Growth","Middle"))) -> High Growth
A40: 1614212 | B40: Central | C40: Small | D40: 10 | E40: 1622 | F40: 16 | G40: Manufacture of wood and products of wood/cork | H40: 2014 | I40: 10 | J40: 157.86736 | K40: 30000000 | L40: 15000000 | M40: 35 | N40: 5 | O40: 3 | P40: 10000000 | Q40: 5000000 | R40: 60000000 | S40: 0 | T40: Not asked (survey skip: screener employment <20) | U40: No | V40: No | W40: 0 | X40: 0 | Y40: 0 | Z40: No | AB40: No | AC40: No | AD40: No | AF40: No obstacle | AG40: No obstacle | AH40: No obstacle | AI40: Major obstacle | AJ40: Practices of competitors in the informal sector | AK40: Are estimates computed with some precision | AL40: =IF(H40="","",2024-H40) -> 10 | AM40: =IFERROR(IF(Z40="No",0,IF(Z40="Yes",AA40,"")),"") -> 0 | AN40: =IFERROR(IF(AD40="No",0,IF(AD40="Yes",AE40,"")),"") -> 0 | AO40: =IF(S40>0,"Yes","No") -> No | AP40: =IF(OR(K40="",L40="",L40<=0),"",K40/L40-1) -> 1 | AQ40: =IF(OR(K40="",L40="",L40<=0),"",(K40/L40)^(1/2)-1) -> 0.41421356 | AR40: =IF(OR(N40="",O40="",O40<=0),"",N40/O40-1) -> 0.66666667 | AS40: =IF(OR(K40="",N40="",N40<=0),"",K40/N40) -> 6000000 | AT40: =IF(OR(P40="",K40="",K40<=0),"",P40/K40) -> 0.33333333 | AU40: =IF(OR(Q40="",K40="",K40<=0),"",Q40/K40) -> 0.16666667 | AV40: =IF(OR(R40="",N40="",N40<=0),"",R40/N40) -> 12000000 | AW40: =IFERROR(IF(Z40="No",0,IF(Z40="Yes",AM40/K40,"")),"") -> 0 | AX40: =IF(OR(K40<Outlier_Audit!$H$2,K40>Outlier_Audit!$I$2),"Review","Normal") -> Normal | AY40: =IF(AL40="","Unknown",IF(AL40<10,"<10 years",IF(AL40<20,"10-19 years",IF(AL40<30,"20-29 years","30+ years")))) -> 10-19 years | AZ40: =IF(AQ40="","Missing",IF(AQ40>=EDA_Performance!$B$7,"High Growth",IF(AQ40<=EDA_Performance!$B$5,"Low Growth","Middle"))) -> High Growth
A41: 1614213 | B41: Central | C41: Large | D41: 20 | E41: 1061 | F41: 10 | G41: Manufacture of food products | H41: 2001 | I41: 15 | J41: 3.8174868 | K41: 2000000 | M41: 10 | N41: 5 | S41: 0 | T41: No | U41: No | V41: No | W41: 100 | X41: 0 | Y41: 0 | Z41: No | AB41: No | AC41: No | AD41: Yes | AE41: 6 | AF41: No obstacle | AG41: Major obstacle | AH41: No obstacle | AI41: Very severe obstacle | AJ41: Access to finance | AK41: Are estimates computed with some precision | AL41: =IF(H41="","",2024-H41) -> 23 | AM41: =IFERROR(IF(Z41="No",0,IF(Z41="Yes",AA41,"")),"") -> 0 | AN41: =IFERROR(IF(AD41="No",0,IF(AD41="Yes",AE41,"")),"") -> 6 | AO41: =IF(S41>0,"Yes","No") -> No | AP41: =IF(OR(K41="",L41="",L41<=0),"",K41/L41-1) | AQ41: =IF(OR(K41="",L41="",L41<=0),"",(K41/L41)^(1/2)-1) | AR41: =IF(OR(N41="",O41="",O41<=0),"",N41/O41-1) | AS41: =IF(OR(K41="",N41="",N41<=0),"",K41/N41) -> 400000 | AT41: =IF(OR(P41="",K41="",K41<=0),"",P41/K41) | AU41: =IF(OR(Q41="",K41="",K41<=0),"",Q41/K41) | AV41: =IF(OR(R41="",N41="",N41<=0),"",R41/N41) | AW41: =IFERROR(IF(Z41="No",0,IF(Z41="Yes",AM41/K41,"")),"") -> 0 | AX41: =IF(OR(K41<Outlier_Audit!$H$2,K41>Outlier_Audit!$I$2),"Review","Normal") -> Normal | AY41: =IF(AL41="","Unknown",IF(AL41<10,"<10 years",IF(AL41<20,"10-19 years",IF(AL41<30,"20-29 years","30+ years")))) -> 20-29 years | AZ41: =IF(AQ41="","Missing",IF(AQ41>=EDA_Performance!$B$7,"High Growth",IF(AQ41<=EDA_Performance!$B$5,"Low Growth","Middle"))) -> Missing
A42: 1614215 | B42: Central | C42: Large | D42: 66 | E42: 1811 | F42: 18 | G42: Printing and reproduction of recorded media | H42: 1997 | I42: 13 | J42: 1 | K42: 5000000000 | L42: 2000000000 | M42: 100 | N42: 46 | O42: 38 | P42: 300000000 | Q42: 1000000000 | S42: 0 | T42: Yes | U42: No | V42: No | W42: 40 | X42: 50 | Y42: 10 | Z42: Yes | AA42: 85000000 | AB42: Yes | AC42: No | AD42: Yes | AE42: 7 | AF42: Minor obstacle | AG42: Moderate obstacle | AH42: Minor obstacle | AI42: Major obstacle | AJ42: Tax rates | AK42: Are in some case taken from books and in some case estimates | AL42: =IF(H42="","",2024-H42) -> 27 | AM42: =IFERROR(IF(Z42="No",0,IF(Z42="Yes",AA42,"")),"") -> 85000000 | AN42: =IFERROR(IF(AD42="No",0,IF(AD42="Yes",AE42,"")),"") -> 7 | AO42: =IF(S42>0,"Yes","No") -> No | AP42: =IF(OR(K42="",L42="",L42<=0),"",K42/L42-1) -> 1.5 | AQ42: =IF(OR(K42="",L42="",L42<=0),"",(K42/L42)^(1/2)-1) -> 0.58113883 | AR42: =IF(OR(N42="",O42="",O42<=0),"",N42/O42-1) -> 0.21052632 | AS42: =IF(OR(K42="",N42="",N42<=0),"",K42/N42) -> 1.0869565e+08 | AT42: =IF(OR(P42="",K42="",K42<=0),"",P42/K42) -> 0.06 | AU42: =IF(OR(Q42="",K42="",K42<=0),"",Q42/K42) -> 0.2 | AV42: =IF(OR(R42="",N42="",N42<=0),"",R42/N42) | AW42: =IFERROR(IF(Z42="No",0,IF(Z42="Yes",AM42/K42,"")),"") -> 0.017 | AX42: =IF(OR(K42<Outlier_Audit!$H$2,K42>Outlier_Audit!$I$2),"Review","Normal") -> Normal | AY42: =IF(AL42="","Unknown",IF(AL42<10,"<10 years",IF(AL42<20,"10-19 years",IF(AL42<30,"20-29 years","30+ years")))) -> 20-29 years | AZ42: =IF(AQ42="","Missing",IF(AQ42>=EDA_Performance!$B$7,"High Growth",IF(AQ42<=EDA_Performance!$B$5,"Low Growth","Middle"))) -> High Growth
A43: 1614218 | B43: Central | C43: Large | D43: 6 | E43: 2511 | F43: 25 | G43: Manufacture of fabricated metal products | H43: 1984 | I43: 39 | J43: 1 | M43: 10 | N43: 5 | O43: 30 | S43: 0 | T43: Not asked (survey skip: screener employment <20) | U43: Yes | V43: No | W43: 90 | X43: 0 | Y43: 0 | Z43: No | AB43: Yes | AC43: No | AD43: Yes | AE43: 4 | AF43: Very severe obstacle | AG43: Major obstacle | AH43: Minor obstacle | AI43: Major obstacle | AJ43: Electricity | AK43: Are in some case taken from books and in some case estimates | AL43: =IF(H43="","",2024-H43) -> 40 | AM43: =IFERROR(IF(Z43="No",0,IF(Z43="Yes",AA43,"")),"") -> 0 | AN43: =IFERROR(IF(AD43="No",0,IF(AD43="Yes",AE43,"")),"") -> 4 | AO43: =IF(S43>0,"Yes","No") -> No | AP43: =IF(OR(K43="",L43="",L43<=0),"",K43/L43-1) | AQ43: =IF(OR(K43="",L43="",L43<=0),"",(K43/L43)^(1/2)-1) | AR43: =IF(OR(N43="",O43="",O43<=0),"",N43/O43-1) -> -0.83333333 | AS43: =IF(OR(K43="",N43="",N43<=0),"",K43/N43) | AT43: =IF(OR(P43="",K43="",K43<=0),"",P43/K43) | AU43: =IF(OR(Q43="",K43="",K43<=0),"",Q43/K43) | AV43: =IF(OR(R43="",N43="",N43<=0),"",R43/N43) | AW43: =IFERROR(IF(Z43="No",0,IF(Z43="Yes",AM43/K43,"")),"") -> 0 | AX43: =IF(OR(K43<Outlier_Audit!$H$2,K43>Outlier_Audit!$I$2),"Review","Normal") -> Normal | AY43: =IF(AL43="","Unknown",IF(AL43<10,"<10 years",IF(AL43<20,"10-19 years",IF(AL43<30,"20-29 years","30+ years")))) -> 30+ years | AZ43: =IF(AQ43="","Missing",IF(AQ43>=EDA_Performance!$B$7,"High Growth",IF(AQ43<=EDA_Performance!$B$5,"Low Growth","Middle"))) -> Missing
A44: 1614219 | B44: Central | C44: Small | D44: 6 | E44: 1410 | F44: 14 | G44: Manufacture of wearing apparel | H44: 1975 | I44: 50 | J44: 5.7243896 | K44: 3600000 | L44: 3000000 | M44: 50 | N44: 6 | O44: 6 | P44: 2000000 | Q44: 3500000 | R44: 10000000 | S44: 0 | T44: Not asked (survey skip: screener employment <20) | U44: Yes | V44: No | W44: 60 | X44: 0 | Y44: 0 | Z44: No | AB44: No | AC44: No | AD44: Yes | AE44: 5 | AF44: Major obstacle | AG44: Minor obstacle | AH44: Moderate obstacle | AI44: Very severe obstacle | AJ44: Tax administration | AK44: Are estimates computed with some precision | AL44: =IF(H44="","",2024-H44) -> 49 | AM44: =IFERROR(IF(Z44="No",0,IF(Z44="Yes",AA44,"")),"") -> 0 | AN44: =IFERROR(IF(AD44="No",0,IF(AD44="Yes",AE44,"")),"") -> 5 | AO44: =IF(S44>0,"Yes","No") -> No | AP44: =IF(OR(K44="",L44="",L44<=0),"",K44/L44-1) -> 0.2 | AQ44: =IF(OR(K44="",L44="",L44<=0),"",(K44/L44)^(1/2)-1) -> 0.095445115 | AR44: =IF(OR(N44="",O44="",O44<=0),"",N44/O44-1) -> 0 | AS44: =IF(OR(K44="",N44="",N44<=0),"",K44/N44) -> 600000 | AT44: =IF(OR(P44="",K44="",K44<=0),"",P44/K44) -> 0.55555556 | AU44: =IF(OR(Q44="",K44="",K44<=0),"",Q44/K44) -> 0.97222222 | AV44: =IF(OR(R44="",N44="",N44<=0),"",R44/N44) -> 1666666.7 | AW44: =IFERROR(IF(Z44="No",0,IF(Z44="Yes",AM44/K44,"")),"") -> 0 | AX44: =IF(OR(K44<Outlier_Audit!$H$2,K44>Outlier_Audit!$I$2),"Review","Normal") -> Normal | AY44: =IF(AL44="","Unknown",IF(AL44<10,"<10 years",IF(AL44<20,"10-19 years",IF(AL44<30,"20-29 years","30+ years")))) -> 30+ years | AZ44: =IF(AQ44="","Missing",IF(AQ44>=EDA_Performance!$B$7,"High Growth",IF(AQ44<=EDA_Performance!$B$5,"Low Growth","Middle"))) -> Middle
A45: 1614220 | B45: Central | C45: Large | D45: 500 | E45: 1103 | F45: 11 | G45: Manufacture of beverages | H45: 1951 | I45: 25 | J45: 1 | K45: 50000000000 | L45: 35000000000 | M45: 85 | N45: 500 | O45: 500 | P45: 2000000000 | S45: 10 | T45: Yes | U45: Yes | V45: No | W45: 100 | X45: 0 | Y45: 0 | Z45: No | AB45: No | AC45: No | AD45: Yes | AE45: 10 | AF45: Moderate obstacle | AG45: No obstacle | AH45: No obstacle | AI45: Major obstacle | AJ45: Tax rates | AK45: Are estimates computed with some precision | AL45: =IF(H45="","",2024-H45) -> 73 | AM45: =IFERROR(IF(Z45="No",0,IF(Z45="Yes",AA45,"")),"") -> 0 | AN45: =IFERROR(IF(AD45="No",0,IF(AD45="Yes",AE45,"")),"") -> 10 | AO45: =IF(S45>0,"Yes","No") -> Yes | AP45: =IF(OR(K45="",L45="",L45<=0),"",K45/L45-1) -> 0.42857143 | AQ45: =IF(OR(K45="",L45="",L45<=0),"",(K45/L45)^(1/2)-1) -> 0.19522861 | AR45: =IF(OR(N45="",O45="",O45<=0),"",N45/O45-1) -> 0 | AS45: =IF(OR(K45="",N45="",N45<=0),"",K45/N45) -> 100000000 | AT45: =IF(OR(P45="",K45="",K45<=0),"",P45/K45) -> 0.04 | AU45: =IF(OR(Q45="",K45="",K45<=0),"",Q45/K45) | AV45: =IF(OR(R45="",N45="",N45<=0),"",R45/N45) | AW45: =IFERROR(IF(Z45="No",0,IF(Z45="Yes",AM45/K45,"")),"") -> 0 | AX45: =IF(OR(K45<Outlier_Audit!$H$2,K45>Outlier_Audit!$I$2),"Review","Normal") -> Review | AY45: =IF(AL45="","Unknown",IF(AL45<10,"<10 years",IF(AL45<20,"10-19 years",IF(AL45<30,"20-29 years","30+ years")))) -> 30+ years | AZ45: =IF(AQ45="","Missing",IF(AQ45>=EDA_Performance!$B$7,"High Growth",IF(AQ45<=EDA_Performance!$B$5,"Low Growth","Middle"))) -> Middle
A46: 1614222 | B46: Central | C46: Large | D46: 50 | E46: 2511 | F46: 25 | G46: Manufacture of fabricated metal products | H46: 1965 | I46: 17 | J46: 1 | K46: 1200000000 | L46: 3000000000 | M46: 80 | N46: 50 | O46: 60 | P46: 200000000 | Q46: 100000000 | S46: 0 | T46: Yes | U46: Yes | V46: No | W46: 100 | X46: 0 | Y46: 0 | Z46: Yes | AA46: 109500000 | AB46: No | AC46: No | AD46: Yes | AE46: 10 | AF46: Minor obstacle | AG46: Minor obstacle | AH46: No obstacle | AI46: Moderate obstacle | AJ46: Tax rates | AK46: Are taken directly from establishment records | AL46: =IF(H46="","",2024-H46) -> 59 | AM46: =IFERROR(IF(Z46="No",0,IF(Z46="Yes",AA46,"")),"") -> 109500000 | AN46: =IFERROR(IF(AD46="No",0,IF(AD46="Yes",AE46,"")),"") -> 10 | AO46: =IF(S46>0,"Yes","No") -> No | AP46: =IF(OR(K46="",L46="",L46<=0),"",K46/L46-1) -> -0.6 | AQ46: =IF(OR(K46="",L46="",L46<=0),"",(K46/L46)^(1/2)-1) -> -0.36754447 | AR46: =IF(OR(N46="",O46="",O46<=0),"",N46/O46-1) -> -0.16666667 | AS46: =IF(OR(K46="",N46="",N46<=0),"",K46/N46) -> 24000000 | AT46: =IF(OR(P46="",K46="",K46<=0),"",P46/K46) -> 0.16666667 | AU46: =IF(OR(Q46="",K46="",K46<=0),"",Q46/K46) -> 0.083333333 | AV46: =IF(OR(R46="",N46="",N46<=0),"",R46/N46) | AW46: =IFERROR(IF(Z46="No",0,IF(Z46="Yes",AM46/K46,"")),"") -> 0.09125 | AX46: =IF(OR(K46<Outlier_Audit!$H$2,K46>Outlier_Audit!$I$2),"Review","Normal") -> Normal | AY46: =IF(AL46="","Unknown",IF(AL46<10,"<10 years",IF(AL46<20,"10-19 years",IF(AL46<30,"20-29 years","30+ years")))) -> 30+ years | AZ46: =IF(AQ46="","Missing",IF(AQ46>=EDA_Performance!$B$7,"High Growth",IF(AQ46<=EDA_Performance!$B$5,"Low Growth","Middle"))) -> Low Growth
A47: 1614223 | B47: Central | C47: Small | D47: 6 | E47: 1622 | F47: 16 | G47: Manufacture of wood and products of wood/cork | H47: 2012 | I47: 28 | J47: 143.61815 | M47: 90 | N47: 4 | O47: 4 | P47: 1500000 | Q47: 7000000 | R47: 1500000 | S47: 75 | T47: Not asked (survey skip: screener employment <20) | U47: No | V47: No | W47: 80 | X47: 0 | Y47: 0 | Z47: Yes | AA47: 450000 | AB47: No | AC47: No | AD47: Yes | AE47: 2 | AF47: Minor obstacle | AG47: Minor obstacle | AH47: Moderate obstacle | AI47: Moderate obstacle | AJ47: Customs and trade regulations | AK47: Are arbitrary and unreliable numbers | AL47: =IF(H47="","",2024-H47) -> 12 | AM47: =IFERROR(IF(Z47="No",0,IF(Z47="Yes",AA47,"")),"") -> 450000 | AN47: =IFERROR(IF(AD47="No",0,IF(AD47="Yes",AE47,"")),"") -> 2 | AO47: =IF(S47>0,"Yes","No") -> Yes | AP47: =IF(OR(K47="",L47="",L47<=0),"",K47/L47-1) | AQ47: =IF(OR(K47="",L47="",L47<=0),"",(K47/L47)^(1/2)-1) | AR47: =IF(OR(N47="",O47="",O47<=0),"",N47/O47-1) -> 0 | AS47: =IF(OR(K47="",N47="",N47<=0),"",K47/N47) | AT47: =IF(OR(P47="",K47="",K47<=0),"",P47/K47) | AU47: =IF(OR(Q47="",K47="",K47<=0),"",Q47/K47) | AV47: =IF(OR(R47="",N47="",N47<=0),"",R47/N47) -> 375000 | AW47: =IFERROR(IF(Z47="No",0,IF(Z47="Yes",AM47/K47,"")),"") | AX47: =IF(OR(K47<Outlier_Audit!$H$2,K47>Outlier_Audit!$I$2),"Review","Normal") -> Normal | AY47: =IF(AL47="","Unknown",IF(AL47<10,"<10 years",IF(AL47<20,"10-19 years",IF(AL47<30,"20-29 years","30+ years")))) -> 10-19 years | AZ47: =IF(AQ47="","Missing",IF(AQ47>=EDA_Performance!$B$7,"High Growth",IF(AQ47<=EDA_Performance!$B$5,"Low Growth","Middle"))) -> Missing
A48: 1614224 | B48: Eastern | C48: Medium | D48: 14 | E48: 3312 | F48: 33 | G48: Repair and installation of machinery and equipment | H48: 2005 | I48: 20 | J48: 1.148219 | K48: 50000000 | L48: 36000000 | M48: 10 | N48: 14 | O48: 5 | P48: 10000000 | R48: 40000000 | S48: 0 | T48: Not asked (survey skip: screener employment <20) | U48: No | V48: No | W48: 0 | X48: 0 | Y48: 0 | Z48: No | AB48: No | AC48: No | AD48: Yes | AE48: 2 | AF48: Minor obstacle | AG48: Major obstacle | AH48: Minor obstacle | AI48: Minor obstacle | AJ48: Access to finance | AK48: Are estimates computed with some precision | AL48: =IF(H48="","",2024-H48) -> 19 | AM48: =IFERROR(IF(Z48="No",0,IF(Z48="Yes",AA48,"")),"") -> 0 | AN48: =IFERROR(IF(AD48="No",0,IF(AD48="Yes",AE48,"")),"") -> 2 | AO48: =IF(S48>0,"Yes","No") -> No | AP48: =IF(OR(K48="",L48="",L48<=0),"",K48/L48-1) -> 0.38888889 | AQ48: =IF(OR(K48="",L48="",L48<=0),"",(K48/L48)^(1/2)-1) -> 0.1785113 | AR48: =IF(OR(N48="",O48="",O48<=0),"",N48/O48-1) -> 1.8 | AS48: =IF(OR(K48="",N48="",N48<=0),"",K48/N48) -> 3571428.6 | AT48: =IF(OR(P48="",K48="",K48<=0),"",P48/K48) -> 0.2 | AU48: =IF(OR(Q48="",K48="",K48<=0),"",Q48/K48) | AV48: =IF(OR(R48="",N48="",N48<=0),"",R48/N48) -> 2857142.9 | AW48: =IFERROR(IF(Z48="No",0,IF(Z48="Yes",AM48/K48,"")),"") -> 0 | AX48: =IF(OR(K48<Outlier_Audit!$H$2,K48>Outlier_Audit!$I$2),"Review","Normal") -> Normal | AY48: =IF(AL48="","Unknown",IF(AL48<10,"<10 years",IF(AL48<20,"10-19 years",IF(AL48<30,"20-29 years","30+ years")))) -> 10-19 years | AZ48: =IF(AQ48="","Missing",IF(AQ48>=EDA_Performance!$B$7,"High Growth",IF(AQ48<=EDA_Performance!$B$5,"Low Growth","Middle"))) -> Middle
A49: 1614225 | B49: Western | C49: Small | D49: 6 | E49: 1061 | F49: 10 | G49: Manufacture of food products | H49: 2018 | I49: 10 | J49: 11.033947 | K49: 25000000 | L49: 30000000 | M49: 100 | N49: 6 | O49: 6 | P49: 7200000 | Q49: 5000000 | R49: 200000000 | S49: 0 | T49: Not asked (survey skip: screener employment <20) | U49: No | V49: No | W49: 80 | X49: 0 | Y49: 0 | Z49: No | AB49: No | AC49: No | AD49: Yes | AE49: 8 | AF49: No obstacle | AG49: No obstacle | AH49: No obstacle | AI49: No obstacle | AJ49: Tax rates | AK49: Are in some case taken from books and in some case estimates | AL49: =IF(H49="","",2024-H49) -> 6 | AM49: =IFERROR(IF(Z49="No",0,IF(Z49="Yes",AA49,"")),"") -> 0 | AN49: =IFERROR(IF(AD49="No",0,IF(AD49="Yes",AE49,"")),"") -> 8 | AO49: =IF(S49>0,"Yes","No") -> No | AP49: =IF(OR(K49="",L49="",L49<=0),"",K49/L49-1) -> -0.16666667 | AQ49: =IF(OR(K49="",L49="",L49<=0),"",(K49/L49)^(1/2)-1) -> -0.087129071 | AR49: =IF(OR(N49="",O49="",O49<=0),"",N49/O49-1) -> 0 | AS49: =IF(OR(K49="",N49="",N49<=0),"",K49/N49) -> 4166666.7 | AT49: =IF(OR(P49="",K49="",K49<=0),"",P49/K49) -> 0.288 | AU49: =IF(OR(Q49="",K49="",K49<=0),"",Q49/K49) -> 0.2 | AV49: =IF(OR(R49="",N49="",N49<=0),"",R49/N49) -> 33333333 | AW49: =IFERROR(IF(Z49="No",0,IF(Z49="Yes",AM49/K49,"")),"") -> 0 | AX49: =IF(OR(K49<Outlier_Audit!$H$2,K49>Outlier_Audit!$I$2),"Review","Normal") -> Normal | AY49: =IF(AL49="","Unknown",IF(AL49<10,"<10 years",IF(AL49<20,"10-19 years",IF(AL49<30,"20-29 years","30+ years")))) -> <10 years | AZ49: =IF(AQ49="","Missing",IF(AQ49>=EDA_Performance!$B$7,"High Growth",IF(AQ49<=EDA_Performance!$B$5,"Low Growth","Middle"))) -> Low Growth
A50: 1614227 | B50: Western | C50: Medium | D50: 15 | E50: 2599 | F50: 25 | G50: Manufacture of fabricated metal products | H50: 1997 | I50: 30 | J50: 5.2876315 | K50: 50000000 | L50: 100000000 | M50: 55 | N50: 7 | O50: 6 | P50: 11160000 | Q50: 7000000 | R50: 7000000 | S50: 0 | T50: Not asked (survey skip: screener employment <20) | U50: No | V50: No | W50: 80 | X50: 0 | Y50: 20 | Z50: No | AB50: No | AC50: No | AD50: Yes | AE50: 7 | AF50: Moderate obstacle | AG50: Minor obstacle | AH50: Minor obstacle | AI50: Minor obstacle | AJ50: Access to land | AK50: Are estimates computed with some precision | AL50: =IF(H50="","",2024-H50) -> 27 | AM50: =IFERROR(IF(Z50="No",0,IF(Z50="Yes",AA50,"")),"") -> 0 | AN50: =IFERROR(IF(AD50="No",0,IF(AD50="Yes",AE50,"")),"") -> 7 | AO50: =IF(S50>0,"Yes","No") -> No | AP50: =IF(OR(K50="",L50="",L50<=0),"",K50/L50-1) -> -0.5 | AQ50: =IF(OR(K50="",L50="",L50<=0),"",(K50/L50)^(1/2)-1) -> -0.29289322 | AR50: =IF(OR(N50="",O50="",O50<=0),"",N50/O50-1) -> 0.16666667 | AS50: =IF(OR(K50="",N50="",N50<=0),"",K50/N50) -> 7142857.1 | AT50: =IF(OR(P50="",K50="",K50<=0),"",P50/K50) -> 0.2232 | AU50: =IF(OR(Q50="",K50="",K50<=0),"",Q50/K50) -> 0.14 | AV50: =IF(OR(R50="",N50="",N50<=0),"",R50/N50) -> 1000000 | AW50: =IFERROR(IF(Z50="No",0,IF(Z50="Yes",AM50/K50,"")),"") -> 0 | AX50: =IF(OR(K50<Outlier_Audit!$H$2,K50>Outlier_Audit!$I$2),"Review","Normal") -> Normal | AY50: =IF(AL50="","Unknown",IF(AL50<10,"<10 years",IF(AL50<20,"10-19 years",IF(AL50<30,"20-29 years","30+ years")))) -> 20-29 years | AZ50: =IF(AQ50="","Missing",IF(AQ50>=EDA_Performance!$B$7,"High Growth",IF(AQ50<=EDA_Performance!$B$5,"Low Growth","Middle"))) -> Low Growth
A51: 1614229 | B51: Eastern | C51: Small | D51: 10 | E51: 1061 | F51: 10 | G51: Manufacture of food products | H51: 2001 | I51: 24 | J51: 1.7984211 | K51: 182500000 | L51: 180000000 | M51: 100 | N51: 9 | O51: 8 | P51: 48000000 | Q51: 70000000 | R51: 120000000 | S51: 0 | T51: Not asked (survey skip: screener employment <20) | U51: No | V51: No | W51: 70 | X51: 0 | Y51: 0 | Z51: No | AB51: No | AC51: No | AD51: Yes | AE51: 5 | AF51: Moderate obstacle | AG51: Major obstacle | AH51: No obstacle | AI51: Moderate obstacle | AJ51: Access to finance | AK51: Are taken directly from establishment records | AL51: =IF(H51="","",2024-H51) -> 23 | AM51: =IFERROR(IF(Z51="No",0,IF(Z51="Yes",AA51,"")),"") -> 0 | AN51: =IFERROR(IF(AD51="No",0,IF(AD51="Yes",AE51,"")),"") -> 5 | AO51: =IF(S51>0,"Yes","No") -> No | AP51: =IF(OR(K51="",L51="",L51<=0),"",K51/L51-1) -> 0.013888889 | AQ51: =IF(OR(K51="",L51="",L51<=0),"",(K51/L51)^(1/2)-1) -> 0.0069204978 | AR51: =IF(OR(N51="",O51="",O51<=0),"",N51/O51-1) -> 0.125 | AS51: =IF(OR(K51="",N51="",N51<=0),"",K51/N51) -> 20277778 | AT51: =IF(OR(P51="",K51="",K51<=0),"",P51/K51) -> 0.2630137 | AU51: =IF(OR(Q51="",K51="",K51<=0),"",Q51/K51) -> 0.38356164 | AV51: =IF(OR(R51="",N51="",N51<=0),"",R51/N51) -> 13333333 | AW51: =IFERROR(IF(Z51="No",0,IF(Z51="Yes",AM51/K51,"")),"") -> 0 | AX51: =IF(OR(K51<Outlier_Audit!$H$2,K51>Outlier_Audit!$I$2),"Review","Normal") -> Normal | AY51: =IF(AL51="","Unknown",IF(AL51<10,"<10 years",IF(AL51<20,"10-19 years",IF(AL51<30,"20-29 years","30+ years")))) -> 20-29 years | AZ51: =IF(AQ51="","Missing",IF(AQ51>=EDA_Performance!$B$7,"High Growth",IF(AQ51<=EDA_Performance!$B$5,"Low Growth","Middle"))) -> Low Growth
A52: 1614230 | B52: Central | C52: Small | D52: 8 | E52: 1410 | F52: 14 | G52: Manufacture of wearing apparel | H52: 2010 | I52: 20 | J52: 189.57414 | K52: 34000000 | L52: 15000000 | M52: 30 | N52: 8 | O52: 4 | P52: 12000000 | Q52: 30000000 | R52: 25000000 | S52: 0 | T52: Not asked (survey skip: screener employment <20) | U52: No | V52: No | W52: 50 | X52: 0 | Y52: 20 | Z52: Yes | AA52: 550000 | AB52: No | AC52: No | AD52: Yes | AE52: 3 | AF52: Moderate obstacle | AG52: Very severe obstacle | AH52: No obstacle | AI52: Very severe obstacle | AJ52: Access to finance | AK52: Are estimates computed with some precision | AL52: =IF(H52="","",2024-H52) -> 14 | AM52: =IFERROR(IF(Z52="No",0,IF(Z52="Yes",AA52,"")),"") -> 550000 | AN52: =IFERROR(IF(AD52="No",0,IF(AD52="Yes",AE52,"")),"") -> 3 | AO52: =IF(S52>0,"Yes","No") -> No | AP52: =IF(OR(K52="",L52="",L52<=0),"",K52/L52-1) -> 1.2666667 | AQ52: =IF(OR(K52="",L52="",L52<=0),"",(K52/L52)^(1/2)-1) -> 0.50554531 | AR52: =IF(OR(N52="",O52="",O52<=0),"",N52/O52-1) -> 1 | AS52: =IF(OR(K52="",N52="",N52<=0),"",K52/N52) -> 4250000 | AT52: =IF(OR(P52="",K52="",K52<=0),"",P52/K52) -> 0.35294118 | AU52: =IF(OR(Q52="",K52="",K52<=0),"",Q52/K52) -> 0.88235294 | AV52: =IF(OR(R52="",N52="",N52<=0),"",R52/N52) -> 3125000 | AW52: =IFERROR(IF(Z52="No",0,IF(Z52="Yes",AM52/K52,"")),"") -> 0.016176471 | AX52: =IF(OR(K52<Outlier_Audit!$H$2,K52>Outlier_Audit!$I$2),"Review","Normal") -> Normal | AY52: =IF(AL52="","Unknown",IF(AL52<10,"<10 years",IF(AL52<20,"10-19 years",IF(AL52<30,"20-29 years","30+ years")))) -> 10-19 years | AZ52: =IF(AQ52="","Missing",IF(AQ52>=EDA_Performance!$B$7,"High Growth",IF(AQ52<=EDA_Performance!$B$5,"Low Growth","Middle"))) -> High Growth
A53: 1614231 | B53: Eastern | C53: Medium | D53: 120 | E53: 1071 | F53: 10 | G53: Manufacture of food products | H53: 2002 | I53: 20 | J53: 1.356841 | K53: 700000000 | L53: 600000000 | M53: 70 | N53: 128 | O53: 128 | P53: 460800000 | Q53: 300000000 | R53: 1000000000 | S53: 0 | T53: Yes | U53: Yes | V53: No | W53: 80 | X53: 0 | Y53: 20 | Z53: No | AB53: No | AC53: No | AD53: Yes | AE53: 2 | AF53: Very severe obstacle | AG53: No obstacle | AH53: No obstacle | AI53: Very severe obstacle | AJ53: Practices of competitors in the informal sector | AK53: Are taken directly from establishment records | AL53: =IF(H53="","",2024-H53) -> 22 | AM53: =IFERROR(IF(Z53="No",0,IF(Z53="Yes",AA53,"")),"") -> 0 | AN53: =IFERROR(IF(AD53="No",0,IF(AD53="Yes",AE53,"")),"") -> 2 | AO53: =IF(S53>0,"Yes","No") -> No | AP53: =IF(OR(K53="",L53="",L53<=0),"",K53/L53-1) -> 0.16666667 | AQ53: =IF(OR(K53="",L53="",L53<=0),"",(K53/L53)^(1/2)-1) -> 0.08012345 | AR53: =IF(OR(N53="",O53="",O53<=0),"",N53/O53-1) -> 0 | AS53: =IF(OR(K53="",N53="",N53<=0),"",K53/N53) -> 5468750 | AT53: =IF(OR(P53="",K53="",K53<=0),"",P53/K53) -> 0.65828571 | AU53: =IF(OR(Q53="",K53="",K53<=0),"",Q53/K53) -> 0.42857143 | AV53: =IF(OR(R53="",N53="",N53<=0),"",R53/N53) -> 7812500 | AW53: =IFERROR(IF(Z53="No",0,IF(Z53="Yes",AM53/K53,"")),"") -> 0 | AX53: =IF(OR(K53<Outlier_Audit!$H$2,K53>Outlier_Audit!$I$2),"Review","Normal") -> Normal | AY53: =IF(AL53="","Unknown",IF(AL53<10,"<10 years",IF(AL53<20,"10-19 years",IF(AL53<30,"20-29 years","30+ years")))) -> 20-29 years | AZ53: =IF(AQ53="","Missing",IF(AQ53>=EDA_Performance!$B$7,"High Growth",IF(AQ53<=EDA_Performance!$B$5,"Low Growth","Middle"))) -> Middle
A54: 1614236 | B54: Western | C54: Small | D54: 7 | E54: 2511 | F54: 25 | G54: Manufacture of fabricated metal products | H54: 2012 | I54: 10 | J54: 68.62606 | K54: 30000000 | L54: 25000000 | M54: 75 | N54: 6 | O54: 3 | P54: 12000000 | Q54: 12000000 | R54: 15000000 | S54: 0 | T54: Not asked (survey skip: screener employment <20) | U54: Yes | V54: No | W54: 30 | X54: 0 | Y54: 25 | Z54: Yes | AA54: 1500000 | AB54: Yes | AC54: No | AD54: Yes | AE54: 15 | AF54: Major obstacle | AG54: Major obstacle | AH54: Major obstacle | AI54: Major obstacle | AJ54: Tax rates | AK54: Are in some case taken from books and in some case estimates | AL54: =IF(H54="","",2024-H54) -> 12 | AM54: =IFERROR(IF(Z54="No",0,IF(Z54="Yes",AA54,"")),"") -> 1500000 | AN54: =IFERROR(IF(AD54="No",0,IF(AD54="Yes",AE54,"")),"") -> 15 | AO54: =IF(S54>0,"Yes","No") -> No | AP54: =IF(OR(K54="",L54="",L54<=0),"",K54/L54-1) -> 0.2 | AQ54: =IF(OR(K54="",L54="",L54<=0),"",(K54/L54)^(1/2)-1) -> 0.095445115 | AR54: =IF(OR(N54="",O54="",O54<=0),"",N54/O54-1) -> 1 | AS54: =IF(OR(K54="",N54="",N54<=0),"",K54/N54) -> 5000000 | AT54: =IF(OR(P54="",K54="",K54<=0),"",P54/K54) -> 0.4 | AU54: =IF(OR(Q54="",K54="",K54<=0),"",Q54/K54) -> 0.4 | AV54: =IF(OR(R54="",N54="",N54<=0),"",R54/N54) -> 2500000 | AW54: =IFERROR(IF(Z54="No",0,IF(Z54="Yes",AM54/K54,"")),"") -> 0.05 | AX54: =IF(OR(K54<Outlier_Audit!$H$2,K54>Outlier_Audit!$I$2),"Review","Normal") -> Normal | AY54: =IF(AL54="","Unknown",IF(AL54<10,"<10 years",IF(AL54<20,"10-19 years",IF(AL54<30,"20-29 years","30+ years")))) -> 10-19 years | AZ54: =IF(AQ54="","Missing",IF(AQ54>=EDA_Performance!$B$7,"High Growth",IF(AQ54<=EDA_Performance!$B$5,"Low Growth","Middle"))) -> Middle
A55: 1614238 | B55: Central | C55: Large | D55: 800 | E55: 1410 | F55: 14 | G55: Manufacture of wearing apparel | H55: 2014 | I55: 40 | J55: 1 | K55: 26310000000 | L55: 22700000000 | M55: 87 | N55: 800 | O55: 800 | P55: 2000000000 | Q55: 1500000000 | R55: 27000000000 | S55: 15 | T55: Yes | U55: Yes | V55: Yes | W55: 80 | X55: 0 | Y55: 0 | Z55: No | AB55: No | AC55: No | AD55: Yes | AE55: 25 | AF55: Moderate obstacle | AG55: Minor obstacle | AH55: Major obstacle | AI55: Major obstacle | AJ55: Inadequately educated workforce | AK55: Are taken directly from establishment records | AL55: =IF(H55="","",2024-H55) -> 10 | AM55: =IFERROR(IF(Z55="No",0,IF(Z55="Yes",AA55,"")),"") -> 0 | AN55: =IFERROR(IF(AD55="No",0,IF(AD55="Yes",AE55,"")),"") -> 25 | AO55: =IF(S55>0,"Yes","No") -> Yes | AP55: =IF(OR(K55="",L55="",L55<=0),"",K55/L55-1) -> 0.15903084 | AQ55: =IF(OR(K55="",L55="",L55<=0),"",(K55/L55)^(1/2)-1) -> 0.076582945 | AR55: =IF(OR(N55="",O55="",O55<=0),"",N55/O55-1) -> 0 | AS55: =IF(OR(K55="",N55="",N55<=0),"",K55/N55) -> 32887500 | AT55: =IF(OR(P55="",K55="",K55<=0),"",P55/K55) -> 0.076016724 | AU55: =IF(OR(Q55="",K55="",K55<=0),"",Q55/K55) -> 0.057012543 | AV55: =IF(OR(R55="",N55="",N55<=0),"",R55/N55) -> 33750000 | AW55: =IFERROR(IF(Z55="No",0,IF(Z55="Yes",AM55/K55,"")),"") -> 0 | AX55: =IF(OR(K55<Outlier_Audit!$H$2,K55>Outlier_Audit!$I$2),"Review","Normal") -> Review | AY55: =IF(AL55="","Unknown",IF(AL55<10,"<10 years",IF(AL55<20,"10-19 years",IF(AL55<30,"20-29 years","30+ years")))) -> 10-19 years | AZ55: =IF(AQ55="","Missing",IF(AQ55>=EDA_Performance!$B$7,"High Growth",IF(AQ55<=EDA_Performance!$B$5,"Low Growth","Middle"))) -> Middle
A56: 1614246 | B56: Eastern | C56: Small | D56: 15 | E56: 3100 | F56: 31 | G56: Manufacture of furniture | H56: 1986 | I56: 15 | J56: 61.413673 | K56: 45000000 | L56: 33000000 | M56: 70 | N56: 10 | O56: 10 | P56: 15000000 | Q56: 20000000 | R56: 100000000 | S56: 0 | T56: Not asked (survey skip: screener employment <20) | U56: No | V56: No | W56: 100 | X56: 0 | Y56: 0 | Z56: Yes | AA56: 15000000 | AB56: Yes | AC56: Yes | AD56: Yes | AE56: 3 | AF56: Major obstacle | AG56: Major obstacle | AH56: Moderate obstacle | AI56: Major obstacle | AJ56: Electricity | AK56: Are in some case taken from books and in some case estimates | AL56: =IF(H56="","",2024-H56) -> 38 | AM56: =IFERROR(IF(Z56="No",0,IF(Z56="Yes",AA56,"")),"") -> 15000000 | AN56: =IFERROR(IF(AD56="No",0,IF(AD56="Yes",AE56,"")),"") -> 3 | AO56: =IF(S56>0,"Yes","No") -> No | AP56: =IF(OR(K56="",L56="",L56<=0),"",K56/L56-1) -> 0.36363636 | AQ56: =IF(OR(K56="",L56="",L56<=0),"",(K56/L56)^(1/2)-1) -> 0.16774842 | AR56: =IF(OR(N56="",O56="",O56<=0),"",N56/O56-1) -> 0 | AS56: =IF(OR(K56="",N56="",N56<=0),"",K56/N56) -> 4500000 | AT56: =IF(OR(P56="",K56="",K56<=0),"",P56/K56) -> 0.33333333 | AU56: =IF(OR(Q56="",K56="",K56<=0),"",Q56/K56) -> 0.44444444 | AV56: =IF(OR(R56="",N56="",N56<=0),"",R56/N56) -> 10000000 | AW56: =IFERROR(IF(Z56="No",0,IF(Z56="Yes",AM56/K56,"")),"") -> 0.33333333 | AX56: =IF(OR(K56<Outlier_Audit!$H$2,K56>Outlier_Audit!$I$2),"Review","Normal") -> Normal | AY56: =IF(AL56="","Unknown",IF(AL56<10,"<10 years",IF(AL56<20,"10-19 years",IF(AL56<30,"20-29 years","30+ years")))) -> 30+ years | AZ56: =IF(AQ56="","Missing",IF(AQ56>=EDA_Performance!$B$7,"High Growth",IF(AQ56<=EDA_Performance!$B$5,"Low Growth","Middle"))) -> Middle
A57: 1614254 | B57: Eastern | C57: Small | D57: 7 | E57: 1410 | F57: 14 | G57: Manufacture of wearing apparel | H57: 1995 | I57: 30 | J57: 55.699169 | K57: 50000000 | L57: 20000000 | M57: 100 | N57: 7 | O57: 4 | P57: 5000000 | Q57: 30000000 | R57: 57000000 | S57: 0 | T57: Not asked (survey skip: screener employment <20) | U57: No | V57: No | W57: 70 | X57: 0 | Y57: 0 | Z57: No | AB57: Yes | AC57: No | AD57: Yes | AE57: 7 | AF57: No obstacle | AG57: No obstacle | AH57: No obstacle | AI57: Moderate obstacle | AJ57: Access to land | AK57: Are taken directly from establishment records | AL57: =IF(H57="","",2024-H57) -> 29 | AM57: =IFERROR(IF(Z57="No",0,IF(Z57="Yes",AA57,"")),"") -> 0 | AN57: =IFERROR(IF(AD57="No",0,IF(AD57="Yes",AE57,"")),"") -> 7 | AO57: =IF(S57>0,"Yes","No") -> No | AP57: =IF(OR(K57="",L57="",L57<=0),"",K57/L57-1) -> 1.5 | AQ57: =IF(OR(K57="",L57="",L57<=0),"",(K57/L57)^(1/2)-1) -> 0.58113883 | AR57: =IF(OR(N57="",O57="",O57<=0),"",N57/O57-1) -> 0.75 | AS57: =IF(OR(K57="",N57="",N57<=0),"",K57/N57) -> 7142857.1 | AT57: =IF(OR(P57="",K57="",K57<=0),"",P57/K57) -> 0.1 | AU57: =IF(OR(Q57="",K57="",K57<=0),"",Q57/K57) -> 0.6 | AV57: =IF(OR(R57="",N57="",N57<=0),"",R57/N57) -> 8142857.1 | AW57: =IFERROR(IF(Z57="No",0,IF(Z57="Yes",AM57/K57,"")),"") -> 0 | AX57: =IF(OR(K57<Outlier_Audit!$H$2,K57>Outlier_Audit!$I$2),"Review","Normal") -> Normal | AY57: =IF(AL57="","Unknown",IF(AL57<10,"<10 years",IF(AL57<20,"10-19 years",IF(AL57<30,"20-29 years","30+ years")))) -> 20-29 years | AZ57: =IF(AQ57="","Missing",IF(AQ57>=EDA_Performance!$B$7,"High Growth",IF(AQ57<=EDA_Performance!$B$5,"Low Growth","Middle"))) -> High Growth
A58: 1614255 | B58: Eastern | C58: Medium | D58: 25 | E58: 1520 | F58: 15 | G58: Manufacture of leather and related products | H58: 2003 | I58: 25 | J58: 1.148219 | K58: 200000000 | L58: 150000000 | M58: 80 | N58: 25 | O58: 25 | P58: 40000000 | Q58: 60000000 | R58: 400000000 | S58: 0 | T58: Yes | U58: Yes | V58: No | W58: 40 | X58: 0 | Y58: 0 | Z58: Yes | AB58: Yes | AC58: Yes | AD58: Yes | AE58: 2 | AF58: Moderate obstacle | AG58: Major obstacle | AH58: No obstacle | AI58: Major obstacle | AJ58: Access to finance | AK58: Are in some case taken from books and in some case estimates | AL58: =IF(H58="","",2024-H58) -> 21 | AM58: =IFERROR(IF(Z58="No",0,IF(Z58="Yes",AA58,"")),"") -> 0 | AN58: =IFERROR(IF(AD58="No",0,IF(AD58="Yes",AE58,"")),"") -> 2 | AO58: =IF(S58>0,"Yes","No") -> No | AP58: =IF(OR(K58="",L58="",L58<=0),"",K58/L58-1) -> 0.33333333 | AQ58: =IF(OR(K58="",L58="",L58<=0),"",(K58/L58)^(1/2)-1) -> 0.15470054 | AR58: =IF(OR(N58="",O58="",O58<=0),"",N58/O58-1) -> 0 | AS58: =IF(OR(K58="",N58="",N58<=0),"",K58/N58) -> 8000000 | AT58: =IF(OR(P58="",K58="",K58<=0),"",P58/K58) -> 0.2 | AU58: =IF(OR(Q58="",K58="",K58<=0),"",Q58/K58) -> 0.3 | AV58: =IF(OR(R58="",N58="",N58<=0),"",R58/N58) -> 16000000 | AW58: =IFERROR(IF(Z58="No",0,IF(Z58="Yes",AM58/K58,"")),"") -> 0 | AX58: =IF(OR(K58<Outlier_Audit!$H$2,K58>Outlier_Audit!$I$2),"Review","Normal") -> Normal | AY58: =IF(AL58="","Unknown",IF(AL58<10,"<10 years",IF(AL58<20,"10-19 years",IF(AL58<30,"20-29 years","30+ years")))) -> 20-29 years | AZ58: =IF(AQ58="","Missing",IF(AQ58>=EDA_Performance!$B$7,"High Growth",IF(AQ58<=EDA_Performance!$B$5,"Low Growth","Middle"))) -> Middle
A59: 1614256 | B59: Eastern | C59: Large | D59: 262 | E59: 2599 | F59: 25 | G59: Manufacture of fabricated metal products | H59: 1983 | I59: 1 | J59: 1 | K59: 18000000 | L59: 4000000 | M59: 80 | N59: 262 | O59: 262 | Q59: 14000000 | R59: 10000000 | S59: 0 | T59: Yes | U59: Yes | V59: No | W59: 0 | X59: 0 | Y59: 0 | Z59: No | AB59: No | AC59: No | AD59: Yes | AE59: 10 | AF59: Moderate obstacle | AG59: Moderate obstacle | AH59: No obstacle | AI59: Minor obstacle | AJ59: Tax rates | AK59: Are in some case taken from books and in some case estimates | AL59: =IF(H59="","",2024-H59) -> 41 | AM59: =IFERROR(IF(Z59="No",0,IF(Z59="Yes",AA59,"")),"") -> 0 | AN59: =IFERROR(IF(AD59="No",0,IF(AD59="Yes",AE59,"")),"") -> 10 | AO59: =IF(S59>0,"Yes","No") -> No | AP59: =IF(OR(K59="",L59="",L59<=0),"",K59/L59-1) -> 3.5 | AQ59: =IF(OR(K59="",L59="",L59<=0),"",(K59/L59)^(1/2)-1) -> 1.1213203 | AR59: =IF(OR(N59="",O59="",O59<=0),"",N59/O59-1) -> 0 | AS59: =IF(OR(K59="",N59="",N59<=0),"",K59/N59) -> 68702.29 | AT59: =IF(OR(P59="",K59="",K59<=0),"",P59/K59) | AU59: =IF(OR(Q59="",K59="",K59<=0),"",Q59/K59) -> 0.77777778 | AV59: =IF(OR(R59="",N59="",N59<=0),"",R59/N59) -> 38167.939 | AW59: =IFERROR(IF(Z59="No",0,IF(Z59="Yes",AM59/K59,"")),"") -> 0 | AX59: =IF(OR(K59<Outlier_Audit!$H$2,K59>Outlier_Audit!$I$2),"Review","Normal") -> Normal | AY59: =IF(AL59="","Unknown",IF(AL59<10,"<10 years",IF(AL59<20,"10-19 years",IF(AL59<30,"20-29 years","30+ years")))) -> 30+ years | AZ59: =IF(AQ59="","Missing",IF(AQ59>=EDA_Performance!$B$7,"High Growth",IF(AQ59<=EDA_Performance!$B$5,"Low Growth","Middle"))) -> High Growth
A60: 1614258 | B60: Central | C60: Medium | D60: 12 | E60: 3220 | F60: 32 | G60: Other manufacturing | H60: 2005 | I60: 35 | J60: 53.759541 | K60: 20000000 | L60: 15000000 | M60: 50 | N60: 6 | O60: 5 | P60: 8000000 | Q60: 3000000 | R60: 50000000 | S60: 0 | T60: Not asked (survey skip: screener employment <20) | U60: No | V60: Yes | W60: 90 | X60: 0 | Y60: 0 | Z60: No | AB60: No | AC60: No | AD60: Yes | AE60: 5 | AF60: Moderate obstacle | AG60: Very severe obstacle | AH60: Minor obstacle | AI60: No obstacle | AJ60: Access to finance | AK60: Are estimates computed with some precision | AL60: =IF(H60="","",2024-H60) -> 19 | AM60: =IFERROR(IF(Z60="No",0,IF(Z60="Yes",AA60,"")),"") -> 0 | AN60: =IFERROR(IF(AD60="No",0,IF(AD60="Yes",AE60,"")),"") -> 5 | AO60: =IF(S60>0,"Yes","No") -> No | AP60: =IF(OR(K60="",L60="",L60<=0),"",K60/L60-1) -> 0.33333333 | AQ60: =IF(OR(K60="",L60="",L60<=0),"",(K60/L60)^(1/2)-1) -> 0.15470054 | AR60: =IF(OR(N60="",O60="",O60<=0),"",N60/O60-1) -> 0.2 | AS60: =IF(OR(K60="",N60="",N60<=0),"",K60/N60) -> 3333333.3 | AT60: =IF(OR(P60="",K60="",K60<=0),"",P60/K60) -> 0.4 | AU60: =IF(OR(Q60="",K60="",K60<=0),"",Q60/K60) -> 0.15 | AV60: =IF(OR(R60="",N60="",N60<=0),"",R60/N60) -> 8333333.3 | AW60: =IFERROR(IF(Z60="No",0,IF(Z60="Yes",AM60/K60,"")),"") -> 0 | AX60: =IF(OR(K60<Outlier_Audit!$H$2,K60>Outlier_Audit!$I$2),"Review","Normal") -> Normal | AY60: =IF(AL60="","Unknown",IF(AL60<10,"<10 years",IF(AL60<20,"10-19 years",IF(AL60<30,"20-29 years","30+ years")))) -> 10-19 years | AZ60: =IF(AQ60="","Missing",IF(AQ60>=EDA_Performance!$B$7,"High Growth",IF(AQ60<=EDA_Performance!$B$5,"Low Growth","Middle"))) -> Middle
A61: 1614260 | B61: Eastern | C61: Small | D61: 8 | E61: 1622 | F61: 16 | G61: Manufacture of wood and products of wood/cork | H61: 2012 | I61: 20 | J61: 72.491692 | K61: 40000000 | L61: 30000000 | M61: 40 | N61: 8 | O61: 8 | P61: 19000000 | Q61: 15000000 | R61: 10000000 | S61: 0 | T61: Not asked (survey skip: screener employment <20) | U61: Yes | V61: No | W61: 60 | X61: 0 | Y61: 0 | Z61: No | AB61: Yes | AC61: Yes | AD61: Yes | AE61: 10 | AF61: Very severe obstacle | AG61: Moderate obstacle | AH61: Minor obstacle | AI61: Major obstacle | AJ61: Electricity | AK61: Are in some case taken from books and in some case estimates | AL61: =IF(H61="","",2024-H61) -> 12 | AM61: =IFERROR(IF(Z61="No",0,IF(Z61="Yes",AA61,"")),"") -> 0 | AN61: =IFERROR(IF(AD61="No",0,IF(AD61="Yes",AE61,"")),"") -> 10 | AO61: =IF(S61>0,"Yes","No") -> No | AP61: =IF(OR(K61="",L61="",L61<=0),"",K61/L61-1) -> 0.33333333 | AQ61: =IF(OR(K61="",L61="",L61<=0),"",(K61/L61)^(1/2)-1) -> 0.15470054 | AR61: =IF(OR(N61="",O61="",O61<=0),"",N61/O61-1) -> 0 | AS61: =IF(OR(K61="",N61="",N61<=0),"",K61/N61) -> 5000000 | AT61: =IF(OR(P61="",K61="",K61<=0),"",P61/K61) -> 0.475 | AU61: =IF(OR(Q61="",K61="",K61<=0),"",Q61/K61) -> 0.375 | AV61: =IF(OR(R61="",N61="",N61<=0),"",R61/N61) -> 1250000 | AW61: =IFERROR(IF(Z61="No",0,IF(Z61="Yes",AM61/K61,"")),"") -> 0 | AX61: =IF(OR(K61<Outlier_Audit!$H$2,K61>Outlier_Audit!$I$2),"Review","Normal") -> Normal | AY61: =IF(AL61="","Unknown",IF(AL61<10,"<10 years",IF(AL61<20,"10-19 years",IF(AL61<30,"20-29 years","30+ years")))) -> 10-19 years | AZ61: =IF(AQ61="","Missing",IF(AQ61>=EDA_Performance!$B$7,"High Growth",IF(AQ61<=EDA_Performance!$B$5,"Low Growth","Middle"))) -> Middle
A62: 1614261 | B62: Eastern | C62: Medium | D62: 6 | E62: 1061 | F62: 10 | G62: Manufacture of food products | H62: 2009 | I62: 16 | J62: 1.4072497 | K62: 38000000 | L62: 42000000 | M62: 55 | N62: 6 | O62: 6 | P62: 18000000 | Q62: 27000000 | R62: 20000000 | S62: 0 | T62: Not asked (survey skip: screener employment <20) | U62: No | V62: No | W62: 80 | X62: 0 | Y62: 0 | Z62: No | AB62: No | AC62: No | AD62: Yes | AE62: 5 | AF62: Major obstacle | AG62: Minor obstacle | AH62: No obstacle | AI62: Minor obstacle | AJ62: Electricity | AK62: Are estimates computed with some precision | AL62: =IF(H62="","",2024-H62) -> 15 | AM62: =IFERROR(IF(Z62="No",0,IF(Z62="Yes",AA62,"")),"") -> 0 | AN62: =IFERROR(IF(AD62="No",0,IF(AD62="Yes",AE62,"")),"") -> 5 | AO62: =IF(S62>0,"Yes","No") -> No | AP62: =IF(OR(K62="",L62="",L62<=0),"",K62/L62-1) -> -0.095238095 | AQ62: =IF(OR(K62="",L62="",L62<=0),"",(K62/L62)^(1/2)-1) -> -0.048810269 | AR62: =IF(OR(N62="",O62="",O62<=0),"",N62/O62-1) -> 0 | AS62: =IF(OR(K62="",N62="",N62<=0),"",K62/N62) -> 6333333.3 | AT62: =IF(OR(P62="",K62="",K62<=0),"",P62/K62) -> 0.47368421 | AU62: =IF(OR(Q62="",K62="",K62<=0),"",Q62/K62) -> 0.71052632 | AV62: =IF(OR(R62="",N62="",N62<=0),"",R62/N62) -> 3333333.3 | AW62: =IFERROR(IF(Z62="No",0,IF(Z62="Yes",AM62/K62,"")),"") -> 0 | AX62: =IF(OR(K62<Outlier_Audit!$H$2,K62>Outlier_Audit!$I$2),"Review","Normal") -> Normal | AY62: =IF(AL62="","Unknown",IF(AL62<10,"<10 years",IF(AL62<20,"10-19 years",IF(AL62<30,"20-29 years","30+ years")))) -> 10-19 years | AZ62: =IF(AQ62="","Missing",IF(AQ62>=EDA_Performance!$B$7,"High Growth",IF(AQ62<=EDA_Performance!$B$5,"Low Growth","Middle"))) -> Low Growth
A63: 1614267 | B63: Northern | C63: Medium | D63: 16 | E63: 1040 | F63: 10 | G63: Manufacture of food products | H63: 2015 | I63: 10 | J63: 24.621111 | K63: 120000000 | L63: 100000000 | M63: 80 | N63: 16 | O63: 5 | P63: 50000000 | Q63: 60000000 | R63: 150000000 | S63: 0 | T63: Not asked (survey skip: screener employment <20) | U63: No | V63: No | W63: 20 | X63: 0 | Y63: 20 | Z63: No | AB63: No | AC63: No | AD63: Yes | AE63: 1 | AF63: Minor obstacle | AG63: Minor obstacle | AH63: Minor obstacle | AI63: Major obstacle | AJ63: Tax rates | AK63: Are in some case taken from books and in some case estimates | AL63: =IF(H63="","",2024-H63) -> 9 | AM63: =IFERROR(IF(Z63="No",0,IF(Z63="Yes",AA63,"")),"") -> 0 | AN63: =IFERROR(IF(AD63="No",0,IF(AD63="Yes",AE63,"")),"") -> 1 | AO63: =IF(S63>0,"Yes","No") -> No | AP63: =IF(OR(K63="",L63="",L63<=0),"",K63/L63-1) -> 0.2 | AQ63: =IF(OR(K63="",L63="",L63<=0),"",(K63/L63)^(1/2)-1) -> 0.095445115 | AR63: =IF(OR(N63="",O63="",O63<=0),"",N63/O63-1) -> 2.2 | AS63: =IF(OR(K63="",N63="",N63<=0),"",K63/N63) -> 7500000 | AT63: =IF(OR(P63="",K63="",K63<=0),"",P63/K63) -> 0.41666667 | AU63: =IF(OR(Q63="",K63="",K63<=0),"",Q63/K63) -> 0.5 | AV63: =IF(OR(R63="",N63="",N63<=0),"",R63/N63) -> 9375000 | AW63: =IFERROR(IF(Z63="No",0,IF(Z63="Yes",AM63/K63,"")),"") -> 0 | AX63: =IF(OR(K63<Outlier_Audit!$H$2,K63>Outlier_Audit!$I$2),"Review","Normal") -> Normal | AY63: =IF(AL63="","Unknown",IF(AL63<10,"<10 years",IF(AL63<20,"10-19 years",IF(AL63<30,"20-29 years","30+ years")))) -> <10 years | AZ63: =IF(AQ63="","Missing",IF(AQ63>=EDA_Performance!$B$7,"High Growth",IF(AQ63<=EDA_Performance!$B$5,"Low Growth","Middle"))) -> Middle
A64: 1614268 | B64: Central | C64: Large | D64: 250 | E64: 2392 | F64: 23 | G64: Manufacture of other non-metallic mineral products | H64: 2000 | I64: 30 | J64: 1 | K64: 8000000000 | L64: 2000000000 | M64: 80 | N64: 350 | O64: 150 | P64: 500000000 | Q64: 2000000000 | R64: 30000000000 | S64: 0 | T64: Yes | U64: Yes | V64: No | W64: 50 | X64: 0 | Y64: 50 | Z64: No | AB64: No | AC64: No | AD64: Yes | AE64: 4 | AF64: Minor obstacle | AG64: No obstacle | AH64: No obstacle | AI64: Major obstacle | AJ64: Practices of competitors in the informal sector | AK64: Are in some case taken from books and in some case estimates | AL64: =IF(H64="","",2024-H64) -> 24 | AM64: =IFERROR(IF(Z64="No",0,IF(Z64="Yes",AA64,"")),"") -> 0 | AN64: =IFERROR(IF(AD64="No",0,IF(AD64="Yes",AE64,"")),"") -> 4 | AO64: =IF(S64>0,"Yes","No") -> No | AP64: =IF(OR(K64="",L64="",L64<=0),"",K64/L64-1) -> 3 | AQ64: =IF(OR(K64="",L64="",L64<=0),"",(K64/L64)^(1/2)-1) -> 1 | AR64: =IF(OR(N64="",O64="",O64<=0),"",N64/O64-1) -> 1.3333333 | AS64: =IF(OR(K64="",N64="",N64<=0),"",K64/N64) -> 22857143 | AT64: =IF(OR(P64="",K64="",K64<=0),"",P64/K64) -> 0.0625 | AU64: =IF(OR(Q64="",K64="",K64<=0),"",Q64/K64) -> 0.25 | AV64: =IF(OR(R64="",N64="",N64<=0),"",R64/N64) -> 85714286 | AW64: =IFERROR(IF(Z64="No",0,IF(Z64="Yes",AM64/K64,"")),"") -> 0 | AX64: =IF(OR(K64<Outlier_Audit!$H$2,K64>Outlier_Audit!$I$2),"Review","Normal") -> Review | AY64: =IF(AL64="","Unknown",IF(AL64<10,"<10 years",IF(AL64<20,"10-19 years",IF(AL64<30,"20-29 years","30+ years")))) -> 20-29 years | AZ64: =IF(AQ64="","Missing",IF(AQ64>=EDA_Performance!$B$7,"High Growth",IF(AQ64<=EDA_Performance!$B$5,"Low Growth","Middle"))) -> High Growth
A65: 1614271 | B65: Northern | C65: Small | D65: 40 | E65: 1061 | F65: 10 | G65: Manufacture of food products | H65: 2009 | I65: 10 | J65: 2.1008389 | K65: 150000000 | L65: 100000000 | M65: 100 | N65: 40 | O65: 10 | P65: 48000000 | Q65: 24000000 | R65: 10000000 | S65: 0 | T65: Yes | U65: No | V65: No | W65: 80 | X65: 20 | Y65: 0 | Z65: No | AB65: Yes | AC65: Yes | AD65: Yes | AE65: 2 | AF65: Major obstacle | AG65: Major obstacle | AH65: Minor obstacle | AI65: Major obstacle | AJ65: Electricity | AK65: Are estimates computed with some precision | AL65: =IF(H65="","",2024-H65) -> 15 | AM65: =IFERROR(IF(Z65="No",0,IF(Z65="Yes",AA65,"")),"") -> 0 | AN65: =IFERROR(IF(AD65="No",0,IF(AD65="Yes",AE65,"")),"") -> 2 | AO65: =IF(S65>0,"Yes","No") -> No | AP65: =IF(OR(K65="",L65="",L65<=0),"",K65/L65-1) -> 0.5 | AQ65: =IF(OR(K65="",L65="",L65<=0),"",(K65/L65)^(1/2)-1) -> 0.22474487 | AR65: =IF(OR(N65="",O65="",O65<=0),"",N65/O65-1) -> 3 | AS65: =IF(OR(K65="",N65="",N65<=0),"",K65/N65) -> 3750000 | AT65: =IF(OR(P65="",K65="",K65<=0),"",P65/K65) -> 0.32 | AU65: =IF(OR(Q65="",K65="",K65<=0),"",Q65/K65) -> 0.16 | AV65: =IF(OR(R65="",N65="",N65<=0),"",R65/N65) -> 250000 | AW65: =IFERROR(IF(Z65="No",0,IF(Z65="Yes",AM65/K65,"")),"") -> 0 | AX65: =IF(OR(K65<Outlier_Audit!$H$2,K65>Outlier_Audit!$I$2),"Review","Normal") -> Normal | AY65: =IF(AL65="","Unknown",IF(AL65<10,"<10 years",IF(AL65<20,"10-19 years",IF(AL65<30,"20-29 years","30+ years")))) -> 10-19 years | AZ65: =IF(AQ65="","Missing",IF(AQ65>=EDA_Performance!$B$7,"High Growth",IF(AQ65<=EDA_Performance!$B$5,"Low Growth","Middle"))) -> Middle
A66: 1614276 | B66: Eastern | C66: Medium | D66: 30 | E66: 1101 | F66: 11 | G66: Manufacture of beverages | H66: 2004 | I66: 8 | J66: 1.3494371 | K66: 1000000000 | L66: 900000000 | M66: 90 | N66: 26 | O66: 26 | P66: 180000000 | Q66: 150000000 | R66: 200000000 | S66: 0 | T66: Yes | U66: No | V66: Yes | W66: 100 | X66: 0 | Y66: 0 | Z66: No | AB66: No | AC66: No | AD66: Yes | AE66: 12 | AF66: Moderate obstacle | AG66: No obstacle | AH66: No obstacle | AI66: No obstacle | AJ66: Electricity | AK66: Are taken directly from establishment records | AL66: =IF(H66="","",2024-H66) -> 20 | AM66: =IFERROR(IF(Z66="No",0,IF(Z66="Yes",AA66,"")),"") -> 0 | AN66: =IFERROR(IF(AD66="No",0,IF(AD66="Yes",AE66,"")),"") -> 12 | AO66: =IF(S66>0,"Yes","No") -> No | AP66: =IF(OR(K66="",L66="",L66<=0),"",K66/L66-1) -> 0.11111111 | AQ66: =IF(OR(K66="",L66="",L66<=0),"",(K66/L66)^(1/2)-1) -> 0.054092553 | AR66: =IF(OR(N66="",O66="",O66<=0),"",N66/O66-1) -> 0 | AS66: =IF(OR(K66="",N66="",N66<=0),"",K66/N66) -> 38461538 | AT66: =IF(OR(P66="",K66="",K66<=0),"",P66/K66) -> 0.18 | AU66: =IF(OR(Q66="",K66="",K66<=0),"",Q66/K66) -> 0.15 | AV66: =IF(OR(R66="",N66="",N66<=0),"",R66/N66) -> 7692307.7 | AW66: =IFERROR(IF(Z66="No",0,IF(Z66="Yes",AM66/K66,"")),"") -> 0 | AX66: =IF(OR(K66<Outlier_Audit!$H$2,K66>Outlier_Audit!$I$2),"Review","Normal") -> Normal | AY66: =IF(AL66="","Unknown",IF(AL66<10,"<10 years",IF(AL66<20,"10-19 years",IF(AL66<30,"20-29 years","30+ years")))) -> 20-29 years | AZ66: =IF(AQ66="","Missing",IF(AQ66>=EDA_Performance!$B$7,"High Growth",IF(AQ66<=EDA_Performance!$B$5,"Low Growth","Middle"))) -> Middle
A67: 1614277 | B67: Central | C67: Medium | D67: 115 | E67: 1410 | F67: 14 | G67: Manufacture of wearing apparel | H67: 1991 | I67: 35 | J67: 42.939556 | K67: 2115600000 | L67: 2227885000 | M67: 100 | N67: 115 | O67: 35 | P67: 170000000 | Q67: 1370000000 | R67: 3000000000 | S67: 0 | T67: Yes | U67: Yes | V67: No | W67: 50 | X67: 0 | Y67: 0 | Z67: No | AB67: Yes | AC67: No | AD67: Yes | AE67: 7 | AF67: Major obstacle | AG67: Major obstacle | AH67: Minor obstacle | AI67: Minor obstacle | AJ67: Access to finance | AK67: Are taken directly from establishment records | AL67: =IF(H67="","",2024-H67) -> 33 | AM67: =IFERROR(IF(Z67="No",0,IF(Z67="Yes",AA67,"")),"") -> 0 | AN67: =IFERROR(IF(AD67="No",0,IF(AD67="Yes",AE67,"")),"") -> 7 | AO67: =IF(S67>0,"Yes","No") -> No | AP67: =IF(OR(K67="",L67="",L67<=0),"",K67/L67-1) -> -0.050399819 | AQ67: =IF(OR(K67="",L67="",L67<=0),"",(K67/L67)^(1/2)-1) -> -0.02552569 | AR67: =IF(OR(N67="",O67="",O67<=0),"",N67/O67-1) -> 2.2857143 | AS67: =IF(OR(K67="",N67="",N67<=0),"",K67/N67) -> 18396522 | AT67: =IF(OR(P67="",K67="",K67<=0),"",P67/K67) -> 0.080355455 | AU67: =IF(OR(Q67="",K67="",K67<=0),"",Q67/K67) -> 0.64757043 | AV67: =IF(OR(R67="",N67="",N67<=0),"",R67/N67) -> 26086957 | AW67: =IFERROR(IF(Z67="No",0,IF(Z67="Yes",AM67/K67,"")),"") -> 0 | AX67: =IF(OR(K67<Outlier_Audit!$H$2,K67>Outlier_Audit!$I$2),"Review","Normal") -> Normal | AY67: =IF(AL67="","Unknown",IF(AL67<10,"<10 years",IF(AL67<20,"10-19 years",IF(AL67<30,"20-29 years","30+ years")))) -> 30+ years | AZ67: =IF(AQ67="","Missing",IF(AQ67>=EDA_Performance!$B$7,"High Growth",IF(AQ67<=EDA_Performance!$B$5,"Low Growth","Middle"))) -> Low Growth
A68: 1614280 | B68: Eastern | C68: Medium | D68: 5 | E68: 1061 | F68: 10 | G68: Manufacture of food products | H68: 1987 | I68: 25 | J68: 1.4072497 | K68: 42000000 | L68: 38000000 | M68: 42 | N68: 5 | O68: 5 | P68: 18000000 | Q68: 23000000 | R68: 15420000 | S68: 0 | T68: Not asked (survey skip: screener employment <20) | U68: No | V68: No | W68: 95 | X68: 0 | Y68: 0 | Z68: No | AB68: No | AC68: No | AD68: Yes | AE68: 5 | AF68: Moderate obstacle | AG68: Very severe obstacle | AH68: Minor obstacle | AI68: Very severe obstacle | AJ68: Access to finance | AK68: Are estimates computed with some precision | AL68: =IF(H68="","",2024-H68) -> 37 | AM68: =IFERROR(IF(Z68="No",0,IF(Z68="Yes",AA68,"")),"") -> 0 | AN68: =IFERROR(IF(AD68="No",0,IF(AD68="Yes",AE68,"")),"") -> 5 | AO68: =IF(S68>0,"Yes","No") -> No | AP68: =IF(OR(K68="",L68="",L68<=0),"",K68/L68-1) -> 0.10526316 | AQ68: =IF(OR(K68="",L68="",L68<=0),"",(K68/L68)^(1/2)-1) -> 0.051314966 | AR68: =IF(OR(N68="",O68="",O68<=0),"",N68/O68-1) -> 0 | AS68: =IF(OR(K68="",N68="",N68<=0),"",K68/N68) -> 8400000 | AT68: =IF(OR(P68="",K68="",K68<=0),"",P68/K68) -> 0.42857143 | AU68: =IF(OR(Q68="",K68="",K68<=0),"",Q68/K68) -> 0.54761905 | AV68: =IF(OR(R68="",N68="",N68<=0),"",R68/N68) -> 3084000 | AW68: =IFERROR(IF(Z68="No",0,IF(Z68="Yes",AM68/K68,"")),"") -> 0 | AX68: =IF(OR(K68<Outlier_Audit!$H$2,K68>Outlier_Audit!$I$2),"Review","Normal") -> Normal | AY68: =IF(AL68="","Unknown",IF(AL68<10,"<10 years",IF(AL68<20,"10-19 years",IF(AL68<30,"20-29 years","30+ years")))) -> 30+ years | AZ68: =IF(AQ68="","Missing",IF(AQ68>=EDA_Performance!$B$7,"High Growth",IF(AQ68<=EDA_Performance!$B$5,"Low Growth","Middle"))) -> Middle
A69: 1614283 | B69: Central | C69: Large | D69: 200 | E69: 1101 | F69: 11 | G69: Manufacture of beverages | H69: 2000 | I69: 25 | J69: 1 | K69: 700000000 | L69: 650000000 | M69: 90 | N69: 180 | O69: 50 | P69: 200000000 | Q69: 400000000 | R69: 1000000000 | S69: 0 | T69: Yes | U69: No | V69: No | W69: 40 | X69: 0 | Y69: 50 | Z69: No | AB69: No | AC69: No | AD69: No | AF69: Minor obstacle | AG69: Minor obstacle | AH69: Minor obstacle | AI69: Minor obstacle | AJ69: Access to land | AK69: Are in some case taken from books and in some case estimates | AL69: =IF(H69="","",2024-H69) -> 24 | AM69: =IFERROR(IF(Z69="No",0,IF(Z69="Yes",AA69,"")),"") -> 0 | AN69: =IFERROR(IF(AD69="No",0,IF(AD69="Yes",AE69,"")),"") -> 0 | AO69: =IF(S69>0,"Yes","No") -> No | AP69: =IF(OR(K69="",L69="",L69<=0),"",K69/L69-1) -> 0.076923077 | AQ69: =IF(OR(K69="",L69="",L69<=0),"",(K69/L69)^(1/2)-1) -> 0.037749043 | AR69: =IF(OR(N69="",O69="",O69<=0),"",N69/O69-1) -> 2.6 | AS69: =IF(OR(K69="",N69="",N69<=0),"",K69/N69) -> 3888888.9 | AT69: =IF(OR(P69="",K69="",K69<=0),"",P69/K69) -> 0.28571429 | AU69: =IF(OR(Q69="",K69="",K69<=0),"",Q69/K69) -> 0.57142857 | AV69: =IF(OR(R69="",N69="",N69<=0),"",R69/N69) -> 5555555.6 | AW69: =IFERROR(IF(Z69="No",0,IF(Z69="Yes",AM69/K69,"")),"") -> 0 | AX69: =IF(OR(K69<Outlier_Audit!$H$2,K69>Outlier_Audit!$I$2),"Review","Normal") -> Normal | AY69: =IF(AL69="","Unknown",IF(AL69<10,"<10 years",IF(AL69<20,"10-19 years",IF(AL69<30,"20-29 years","30+ years")))) -> 20-29 years | AZ69: =IF(AQ69="","Missing",IF(AQ69>=EDA_Performance!$B$7,"High Growth",IF(AQ69<=EDA_Performance!$B$5,"Low Growth","Middle"))) -> Low Growth
A70: 1614286 | B70: Central | C70: Large | D70: 50 | E70: 1101 | F70: 11 | G70: Manufacture of beverages | H70: 2013 | I70: 15 | J70: 1 | K70: 3000000000 | L70: 1500000000 | M70: 45 | N70: 50 | O70: 45 | P70: 500000000 | Q70: 300000000 | R70: 1000000000 | S70: 25 | T70: No | U70: No | V70: No | W70: 80 | X70: 0 | Y70: 0 | Z70: No | AB70: No | AC70: No | AD70: No | AF70: No obstacle | AG70: No obstacle | AH70: No obstacle | AI70: Moderate obstacle | AJ70: Tax administration | AK70: Are estimates computed with some precision | AL70: =IF(H70="","",2024-H70) -> 11 | AM70: =IFERROR(IF(Z70="No",0,IF(Z70="Yes",AA70,"")),"") -> 0 | AN70: =IFERROR(IF(AD70="No",0,IF(AD70="Yes",AE70,"")),"") -> 0 | AO70: =IF(S70>0,"Yes","No") -> Yes | AP70: =IF(OR(K70="",L70="",L70<=0),"",K70/L70-1) -> 1 | AQ70: =IF(OR(K70="",L70="",L70<=0),"",(K70/L70)^(1/2)-1) -> 0.41421356 | AR70: =IF(OR(N70="",O70="",O70<=0),"",N70/O70-1) -> 0.11111111 | AS70: =IF(OR(K70="",N70="",N70<=0),"",K70/N70) -> 60000000 | AT70: =IF(OR(P70="",K70="",K70<=0),"",P70/K70) -> 0.16666667 | AU70: =IF(OR(Q70="",K70="",K70<=0),"",Q70/K70) -> 0.1 | AV70: =IF(OR(R70="",N70="",N70<=0),"",R70/N70) -> 20000000 | AW70: =IFERROR(IF(Z70="No",0,IF(Z70="Yes",AM70/K70,"")),"") -> 0 | AX70: =IF(OR(K70<Outlier_Audit!$H$2,K70>Outlier_Audit!$I$2),"Review","Normal") -> Normal | AY70: =IF(AL70="","Unknown",IF(AL70<10,"<10 years",IF(AL70<20,"10-19 years",IF(AL70<30,"20-29 years","30+ years")))) -> 10-19 years | AZ70: =IF(AQ70="","Missing",IF(AQ70>=EDA_Performance!$B$7,"High Growth",IF(AQ70<=EDA_Performance!$B$5,"Low Growth","Middle"))) -> High Growth
A71: 1614289 | B71: Eastern | C71: Medium | D71: 60 | E71: 1079 | F71: 10 | G71: Manufacture of food products | H71: 1954 | I71: 10 | J71: 1.356841 | K71: 6000000000 | L71: 5000000000 | M71: 100 | N71: 45 | O71: 42 | P71: 420000000 | Q71: 500000000 | R71: 1000000 | S71: 80 | T71: Yes | U71: No | V71: No | W71: 60 | X71: 0 | Y71: 10 | Z71: No | AB71: No | AC71: No | AD71: Yes | AE71: 3 | AF71: Major obstacle | AG71: Major obstacle | AH71: No obstacle | AI71: No obstacle | AJ71: Access to finance | AK71: Are taken directly from establishment records | AL71: =IF(H71="","",2024-H71) -> 70 | AM71: =IFERROR(IF(Z71="No",0,IF(Z71="Yes",AA71,"")),"") -> 0 | AN71: =IFERROR(IF(AD71="No",0,IF(AD71="Yes",AE71,"")),"") -> 3 | AO71: =IF(S71>0,"Yes","No") -> Yes | AP71: =IF(OR(K71="",L71="",L71<=0),"",K71/L71-1) -> 0.2 | AQ71: =IF(OR(K71="",L71="",L71<=0),"",(K71/L71)^(1/2)-1) -> 0.095445115 | AR71: =IF(OR(N71="",O71="",O71<=0),"",N71/O71-1) -> 0.071428571 | AS71: =IF(OR(K71="",N71="",N71<=0),"",K71/N71) -> 1.3333333e+08 | AT71: =IF(OR(P71="",K71="",K71<=0),"",P71/K71) -> 0.07 | AU71: =IF(OR(Q71="",K71="",K71<=0),"",Q71/K71) -> 0.083333333 | AV71: =IF(OR(R71="",N71="",N71<=0),"",R71/N71) -> 22222.222 | AW71: =IFERROR(IF(Z71="No",0,IF(Z71="Yes",AM71/K71,"")),"") -> 0 | AX71: =IF(OR(K71<Outlier_Audit!$H$2,K71>Outlier_Audit!$I$2),"Review","Normal") -> Normal | AY71: =IF(AL71="","Unknown",IF(AL71<10,"<10 years",IF(AL71<20,"10-19 years",IF(AL71<30,"20-29 years","30+ years")))) -> 30+ years | AZ71: =IF(AQ71="","Missing",IF(AQ71>=EDA_Performance!$B$7,"High Growth",IF(AQ71<=EDA_Performance!$B$5,"Low Growth","Middle"))) -> Middle
A72: 1614293 | B72: Western | C72: Large | D72: 100 | E72: 1079 | F72: 10 | G72: Manufacture of food products | H72: 1994 | I72: 5 | J72: 1.3089461 | K72: 36000000000 | L72: 30000000000 | M72: 100 | N72: 100 | O72: 90 | P72: 3000000000 | Q72: 1000000000 | R72: 2000000000 | S72: 20 | T72: Yes | U72: No | V72: No | W72: 60 | X72: 20 | Y72: 20 | Z72: Yes | AA72: 5000000000 | AB72: Yes | AC72: No | AD72: Yes | AE72: 5 | AF72: Minor obstacle | AG72: Minor obstacle | AH72: Minor obstacle | AI72: No obstacle | AJ72: Courts | AK72: Are in some case taken from books and in some case estimates | AL72: =IF(H72="","",2024-H72) -> 30 | AM72: =IFERROR(IF(Z72="No",0,IF(Z72="Yes",AA72,"")),"") -> 5000000000 | AN72: =IFERROR(IF(AD72="No",0,IF(AD72="Yes",AE72,"")),"") -> 5 | AO72: =IF(S72>0,"Yes","No") -> Yes | AP72: =IF(OR(K72="",L72="",L72<=0),"",K72/L72-1) -> 0.2 | AQ72: =IF(OR(K72="",L72="",L72<=0),"",(K72/L72)^(1/2)-1) -> 0.095445115 | AR72: =IF(OR(N72="",O72="",O72<=0),"",N72/O72-1) -> 0.11111111 | AS72: =IF(OR(K72="",N72="",N72<=0),"",K72/N72) -> 360000000 | AT72: =IF(OR(P72="",K72="",K72<=0),"",P72/K72) -> 0.083333333 | AU72: =IF(OR(Q72="",K72="",K72<=0),"",Q72/K72) -> 0.027777778 | AV72: =IF(OR(R72="",N72="",N72<=0),"",R72/N72) -> 20000000 | AW72: =IFERROR(IF(Z72="No",0,IF(Z72="Yes",AM72/K72,"")),"") -> 0.13888889 | AX72: =IF(OR(K72<Outlier_Audit!$H$2,K72>Outlier_Audit!$I$2),"Review","Normal") -> Review | AY72: =IF(AL72="","Unknown",IF(AL72<10,"<10 years",IF(AL72<20,"10-19 years",IF(AL72<30,"20-29 years","30+ years")))) -> 30+ years | AZ72: =IF(AQ72="","Missing",IF(AQ72>=EDA_Performance!$B$7,"High Growth",IF(AQ72<=EDA_Performance!$B$5,"Low Growth","Middle"))) -> Middle
A73: 1614300 | B73: Northern | C73: Small | D73: 9 | E73: 2511 | F73: 25 | G73: Manufacture of fabricated metal products | H73: 2010 | I73: 16 | J73: 18.668732 | K73: 86500000 | L73: 41300000 | M73: 60 | N73: 4 | O73: 3 | P73: 8530000 | Q73: 39540000 | R73: 200570000 | S73: 0 | T73: Not asked (survey skip: screener employment <20) | U73: No | V73: No | W73: 70 | X73: 0 | Y73: 10 | Z73: No | AB73: No | AC73: No | AD73: Yes | AE73: 7 | AF73: Moderate obstacle | AG73: Minor obstacle | AH73: No obstacle | AI73: No obstacle | AJ73: Tax administration | AK73: Are estimates computed with some precision | AL73: =IF(H73="","",2024-H73) -> 14 | AM73: =IFERROR(IF(Z73="No",0,IF(Z73="Yes",AA73,"")),"") -> 0 | AN73: =IFERROR(IF(AD73="No",0,IF(AD73="Yes",AE73,"")),"") -> 7 | AO73: =IF(S73>0,"Yes","No") -> No | AP73: =IF(OR(K73="",L73="",L73<=0),"",K73/L73-1) -> 1.094431 | AQ73: =IF(OR(K73="",L73="",L73<=0),"",(K73/L73)^(1/2)-1) -> 0.44721491 | AR73: =IF(OR(N73="",O73="",O73<=0),"",N73/O73-1) -> 0.33333333 | AS73: =IF(OR(K73="",N73="",N73<=0),"",K73/N73) -> 21625000 | AT73: =IF(OR(P73="",K73="",K73<=0),"",P73/K73) -> 0.098612717 | AU73: =IF(OR(Q73="",K73="",K73<=0),"",Q73/K73) -> 0.45710983 | AV73: =IF(OR(R73="",N73="",N73<=0),"",R73/N73) -> 50142500 | AW73: =IFERROR(IF(Z73="No",0,IF(Z73="Yes",AM73/K73,"")),"") -> 0 | AX73: =IF(OR(K73<Outlier_Audit!$H$2,K73>Outlier_Audit!$I$2),"Review","Normal") -> Normal | AY73: =IF(AL73="","Unknown",IF(AL73<10,"<10 years",IF(AL73<20,"10-19 years",IF(AL73<30,"20-29 years","30+ years")))) -> 10-19 years | AZ73: =IF(AQ73="","Missing",IF(AQ73>=EDA_Performance!$B$7,"High Growth",IF(AQ73<=EDA_Performance!$B$5,"Low Growth","Middle"))) -> High Growth
A74: 1614305 | B74: Central | C74: Large | D74: 24 | E74: 1071 | F74: 10 | G74: Manufacture of food products | H74: 2008 | J74: 3.8174868 | K74: 650000000 | L74: 430000000 | M74: 100 | N74: 24 | O74: 21 | P74: 162500000 | Q74: 350000000 | S74: 0 | T74: No | U74: No | V74: No | W74: 70 | X74: 0 | Y74: 30 | Z74: No | AB74: No | AC74: No | AD74: Yes | AE74: 1 | AF74: Minor obstacle | AG74: Minor obstacle | AH74: No obstacle | AI74: Moderate obstacle | AJ74: Practices of competitors in the informal sector | AK74: Are in some case taken from books and in some case estimates | AL74: =IF(H74="","",2024-H74) -> 16 | AM74: =IFERROR(IF(Z74="No",0,IF(Z74="Yes",AA74,"")),"") -> 0 | AN74: =IFERROR(IF(AD74="No",0,IF(AD74="Yes",AE74,"")),"") -> 1 | AO74: =IF(S74>0,"Yes","No") -> No | AP74: =IF(OR(K74="",L74="",L74<=0),"",K74/L74-1) -> 0.51162791 | AQ74: =IF(OR(K74="",L74="",L74<=0),"",(K74/L74)^(1/2)-1) -> 0.22948278 | AR74: =IF(OR(N74="",O74="",O74<=0),"",N74/O74-1) -> 0.14285714 | AS74: =IF(OR(K74="",N74="",N74<=0),"",K74/N74) -> 27083333 | AT74: =IF(OR(P74="",K74="",K74<=0),"",P74/K74) -> 0.25 | AU74: =IF(OR(Q74="",K74="",K74<=0),"",Q74/K74) -> 0.53846154 | AV74: =IF(OR(R74="",N74="",N74<=0),"",R74/N74) | AW74: =IFERROR(IF(Z74="No",0,IF(Z74="Yes",AM74/K74,"")),"") -> 0 | AX74: =IF(OR(K74<Outlier_Audit!$H$2,K74>Outlier_Audit!$I$2),"Review","Normal") -> Normal | AY74: =IF(AL74="","Unknown",IF(AL74<10,"<10 years",IF(AL74<20,"10-19 years",IF(AL74<30,"20-29 years","30+ years")))) -> 10-19 years | AZ74: =IF(AQ74="","Missing",IF(AQ74>=EDA_Performance!$B$7,"High Growth",IF(AQ74<=EDA_Performance!$B$5,"Low Growth","Middle"))) -> Middle
A75: 1614307 | B75: Central | C75: Medium | D75: 5 | E75: 3312 | F75: 33 | G75: Repair and installation of machinery and equipment | H75: 2002 | I75: 40 | J75: 416.63913 | K75: 600000000 | L75: 700000000 | M75: 70 | N75: 4 | O75: 6 | P75: 50000000 | Q75: 200000000 | R75: 500000000 | S75: 0 | T75: Not asked (survey skip: screener employment <20) | U75: No | V75: No | W75: 70 | X75: 30 | Y75: 0 | Z75: Yes | AA75: 100000000 | AB75: Yes | AC75: Yes | AD75: Yes | AE75: 2 | AF75: Minor obstacle | AG75: Minor obstacle | AH75: No obstacle | AI75: Minor obstacle | AJ75: Practices of competitors in the informal sector | AK75: Are taken directly from establishment records | AL75: =IF(H75="","",2024-H75) -> 22 | AM75: =IFERROR(IF(Z75="No",0,IF(Z75="Yes",AA75,"")),"") -> 100000000 | AN75: =IFERROR(IF(AD75="No",0,IF(AD75="Yes",AE75,"")),"") -> 2 | AO75: =IF(S75>0,"Yes","No") -> No | AP75: =IF(OR(K75="",L75="",L75<=0),"",K75/L75-1) -> -0.14285714 | AQ75: =IF(OR(K75="",L75="",L75<=0),"",(K75/L75)^(1/2)-1) -> -0.0741799 | AR75: =IF(OR(N75="",O75="",O75<=0),"",N75/O75-1) -> -0.33333333 | AS75: =IF(OR(K75="",N75="",N75<=0),"",K75/N75) -> 150000000 | AT75: =IF(OR(P75="",K75="",K75<=0),"",P75/K75) -> 0.083333333 | AU75: =IF(OR(Q75="",K75="",K75<=0),"",Q75/K75) -> 0.33333333 | AV75: =IF(OR(R75="",N75="",N75<=0),"",R75/N75) -> 125000000 | AW75: =IFERROR(IF(Z75="No",0,IF(Z75="Yes",AM75/K75,"")),"") -> 0.16666667 | AX75: =IF(OR(K75<Outlier_Audit!$H$2,K75>Outlier_Audit!$I$2),"Review","Normal") -> Normal | AY75: =IF(AL75="","Unknown",IF(AL75<10,"<10 years",IF(AL75<20,"10-19 years",IF(AL75<30,"20-29 years","30+ years")))) -> 20-29 years | AZ75: =IF(AQ75="","Missing",IF(AQ75>=EDA_Performance!$B$7,"High Growth",IF(AQ75<=EDA_Performance!$B$5,"Low Growth","Middle"))) -> Low Growth
A76: 1614309 | B76: Western | C76: Small | D76: 9 | E76: 1061 | F76: 10 | G76: Manufacture of food products | H76: 2002 | J76: 11.033947 | K76: 48000000 | M76: 80 | N76: 9 | P76: 24000000 | Q76: 10000000 | R76: 50000000 | S76: 0 | T76: Not asked (survey skip: screener employment <20) | U76: No | V76: Yes | W76: 90 | X76: 0 | Y76: 0 | Z76: No | AB76: No | AC76: No | AD76: Yes | AE76: 2 | AF76: Minor obstacle | AG76: Minor obstacle | AH76: Minor obstacle | AI76: Minor obstacle | AJ76: Tax rates | AK76: Are estimates computed with some precision | AL76: =IF(H76="","",2024-H76) -> 22 | AM76: =IFERROR(IF(Z76="No",0,IF(Z76="Yes",AA76,"")),"") -> 0 | AN76: =IFERROR(IF(AD76="No",0,IF(AD76="Yes",AE76,"")),"") -> 2 | AO76: =IF(S76>0,"Yes","No") -> No | AP76: =IF(OR(K76="",L76="",L76<=0),"",K76/L76-1) | AQ76: =IF(OR(K76="",L76="",L76<=0),"",(K76/L76)^(1/2)-1) | AR76: =IF(OR(N76="",O76="",O76<=0),"",N76/O76-1) | AS76: =IF(OR(K76="",N76="",N76<=0),"",K76/N76) -> 5333333.3 | AT76: =IF(OR(P76="",K76="",K76<=0),"",P76/K76) -> 0.5 | AU76: =IF(OR(Q76="",K76="",K76<=0),"",Q76/K76) -> 0.20833333 | AV76: =IF(OR(R76="",N76="",N76<=0),"",R76/N76) -> 5555555.6 | AW76: =IFERROR(IF(Z76="No",0,IF(Z76="Yes",AM76/K76,"")),"") -> 0 | AX76: =IF(OR(K76<Outlier_Audit!$H$2,K76>Outlier_Audit!$I$2),"Review","Normal") -> Normal | AY76: =IF(AL76="","Unknown",IF(AL76<10,"<10 years",IF(AL76<20,"10-19 years",IF(AL76<30,"20-29 years","30+ years")))) -> 20-29 years | AZ76: =IF(AQ76="","Missing",IF(AQ76>=EDA_Performance!$B$7,"High Growth",IF(AQ76<=EDA_Performance!$B$5,"Low Growth","Middle"))) -> Missing
A77: 1614310 | B77: Eastern | C77: Medium | D77: 80 | E77: 1511 | F77: 15 | G77: Manufacture of leather and related products | H77: 1995 | I77: 20 | J77: 1.2895221 | K77: 5483616000 | L77: 2000000000 | M77: 30 | N77: 200 | O77: 150 | P77: 300000000 | Q77: 500000000 | R77: 300000000 | S77: 100 | T77: No | U77: No | V77: No | W77: 0 | X77: 0 | Y77: 0 | Z77: No | AB77: Yes | AC77: No | AD77: Yes | AE77: 5 | AF77: Major obstacle | AG77: Moderate obstacle | AH77: Major obstacle | AI77: Very severe obstacle | AJ77: Corruption | AK77: Are in some case taken from books and in some case estimates | AL77: =IF(H77="","",2024-H77) -> 29 | AM77: =IFERROR(IF(Z77="No",0,IF(Z77="Yes",AA77,"")),"") -> 0 | AN77: =IFERROR(IF(AD77="No",0,IF(AD77="Yes",AE77,"")),"") -> 5 | AO77: =IF(S77>0,"Yes","No") -> Yes | AP77: =IF(OR(K77="",L77="",L77<=0),"",K77/L77-1) -> 1.741808 | AQ77: =IF(OR(K77="",L77="",L77<=0),"",(K77/L77)^(1/2)-1) -> 0.65584057 | AR77: =IF(OR(N77="",O77="",O77<=0),"",N77/O77-1) -> 0.33333333 | AS77: =IF(OR(K77="",N77="",N77<=0),"",K77/N77) -> 27418080 | AT77: =IF(OR(P77="",K77="",K77<=0),"",P77/K77) -> 0.054708426 | AU77: =IF(OR(Q77="",K77="",K77<=0),"",Q77/K77) -> 0.09118071 | AV77: =IF(OR(R77="",N77="",N77<=0),"",R77/N77) -> 1500000 | AW77: =IFERROR(IF(Z77="No",0,IF(Z77="Yes",AM77/K77,"")),"") -> 0 | AX77: =IF(OR(K77<Outlier_Audit!$H$2,K77>Outlier_Audit!$I$2),"Review","Normal") -> Normal | AY77: =IF(AL77="","Unknown",IF(AL77<10,"<10 years",IF(AL77<20,"10-19 years",IF(AL77<30,"20-29 years","30+ years")))) -> 20-29 years | AZ77: =IF(AQ77="","Missing",IF(AQ77>=EDA_Performance!$B$7,"High Growth",IF(AQ77<=EDA_Performance!$B$5,"Low Growth","Middle"))) -> High Growth
A78: 1614312 | B78: Eastern | C78: Small | D78: 13 | E78: 1071 | F78: 10 | G78: Manufacture of food products | H78: 2010 | I78: 15 | J78: 7.8370919 | K78: 400000000 | L78: 350000000 | M78: 90 | N78: 7 | O78: 7 | P78: 39000000 | Q78: 80000000 | R78: 90000000 | S78: 0 | T78: Not asked (survey skip: screener employment <20) | U78: Yes | V78: No | W78: 80 | X78: 0 | Y78: 0 | Z78: No | AB78: No | AC78: No | AD78: Yes | AE78: 5 | AF78: Major obstacle | AG78: Major obstacle | AH78: Moderate obstacle | AI78: Major obstacle | AJ78: Electricity | AK78: Are taken directly from establishment records | AL78: =IF(H78="","",2024-H78) -> 14 | AM78: =IFERROR(IF(Z78="No",0,IF(Z78="Yes",AA78,"")),"") -> 0 | AN78: =IFERROR(IF(AD78="No",0,IF(AD78="Yes",AE78,"")),"") -> 5 | AO78: =IF(S78>0,"Yes","No") -> No | AP78: =IF(OR(K78="",L78="",L78<=0),"",K78/L78-1) -> 0.14285714 | AQ78: =IF(OR(K78="",L78="",L78<=0),"",(K78/L78)^(1/2)-1) -> 0.069044968 | AR78: =IF(OR(N78="",O78="",O78<=0),"",N78/O78-1) -> 0 | AS78: =IF(OR(K78="",N78="",N78<=0),"",K78/N78) -> 57142857 | AT78: =IF(OR(P78="",K78="",K78<=0),"",P78/K78) -> 0.0975 | AU78: =IF(OR(Q78="",K78="",K78<=0),"",Q78/K78) -> 0.2 | AV78: =IF(OR(R78="",N78="",N78<=0),"",R78/N78) -> 12857143 | AW78: =IFERROR(IF(Z78="No",0,IF(Z78="Yes",AM78/K78,"")),"") -> 0 | AX78: =IF(OR(K78<Outlier_Audit!$H$2,K78>Outlier_Audit!$I$2),"Review","Normal") -> Normal | AY78: =IF(AL78="","Unknown",IF(AL78<10,"<10 years",IF(AL78<20,"10-19 years",IF(AL78<30,"20-29 years","30+ years")))) -> 10-19 years | AZ78: =IF(AQ78="","Missing",IF(AQ78>=EDA_Performance!$B$7,"High Growth",IF(AQ78<=EDA_Performance!$B$5,"Low Growth","Middle"))) -> Middle
A79: 1614314 | B79: Central | C79: Small | D79: 6 | E79: 2591 | F79: 25 | G79: Manufacture of fabricated metal products | H79: 2004 | I79: 21 | J79: 157.86736 | K79: 10000000 | L79: 4000000 | M79: 100 | N79: 6 | O79: 8 | P79: 4000000 | R79: 25000000 | S79: 0 | T79: Not asked (survey skip: screener employment <20) | U79: Yes | V79: Yes | W79: 68 | X79: 0 | Y79: 0 | Z79: Yes | AA79: 15000000 | AB79: No | AC79: Yes | AD79: Yes | AE79: 8 | AF79: Very severe obstacle | AG79: Major obstacle | AH79: Moderate obstacle | AI79: Moderate obstacle | AJ79: Access to finance | AK79: Are taken directly from establishment records | AL79: =IF(H79="","",2024-H79) -> 20 | AM79: =IFERROR(IF(Z79="No",0,IF(Z79="Yes",AA79,"")),"") -> 15000000 | AN79: =IFERROR(IF(AD79="No",0,IF(AD79="Yes",AE79,"")),"") -> 8 | AO79: =IF(S79>0,"Yes","No") -> No | AP79: =IF(OR(K79="",L79="",L79<=0),"",K79/L79-1) -> 1.5 | AQ79: =IF(OR(K79="",L79="",L79<=0),"",(K79/L79)^(1/2)-1) -> 0.58113883 | AR79: =IF(OR(N79="",O79="",O79<=0),"",N79/O79-1) -> -0.25 | AS79: =IF(OR(K79="",N79="",N79<=0),"",K79/N79) -> 1666666.7 | AT79: =IF(OR(P79="",K79="",K79<=0),"",P79/K79) -> 0.4 | AU79: =IF(OR(Q79="",K79="",K79<=0),"",Q79/K79) | AV79: =IF(OR(R79="",N79="",N79<=0),"",R79/N79) -> 4166666.7 | AW79: =IFERROR(IF(Z79="No",0,IF(Z79="Yes",AM79/K79,"")),"") -> 1.5 | AX79: =IF(OR(K79<Outlier_Audit!$H$2,K79>Outlier_Audit!$I$2),"Review","Normal") -> Normal | AY79: =IF(AL79="","Unknown",IF(AL79<10,"<10 years",IF(AL79<20,"10-19 years",IF(AL79<30,"20-29 years","30+ years")))) -> 20-29 years | AZ79: =IF(AQ79="","Missing",IF(AQ79>=EDA_Performance!$B$7,"High Growth",IF(AQ79<=EDA_Performance!$B$5,"Low Growth","Middle"))) -> High Growth
A80: 1614316 | B80: Western | C80: Medium | D80: 20 | E80: 1050 | F80: 10 | G80: Manufacture of food products | H80: 2016 | J80: 1.5243006 | M80: 80 | N80: 15 | P80: 142800000 | R80: 500000000 | S80: 0 | T80: Yes | U80: Yes | V80: Yes | W80: 100 | X80: 0 | Y80: 0 | Z80: Yes | AA80: 6000000 | AB80: No | AC80: No | AD80: Yes | AE80: 4 | AF80: Moderate obstacle | AG80: Minor obstacle | AH80: Minor obstacle | AI80: Major obstacle | AJ80: Access to finance | AK80: Are estimates computed with some precision | AL80: =IF(H80="","",2024-H80) -> 8 | AM80: =IFERROR(IF(Z80="No",0,IF(Z80="Yes",AA80,"")),"") -> 6000000 | AN80: =IFERROR(IF(AD80="No",0,IF(AD80="Yes",AE80,"")),"") -> 4 | AO80: =IF(S80>0,"Yes","No") -> No | AP80: =IF(OR(K80="",L80="",L80<=0),"",K80/L80-1) | AQ80: =IF(OR(K80="",L80="",L80<=0),"",(K80/L80)^(1/2)-1) | AR80: =IF(OR(N80="",O80="",O80<=0),"",N80/O80-1) | AS80: =IF(OR(K80="",N80="",N80<=0),"",K80/N80) | AT80: =IF(OR(P80="",K80="",K80<=0),"",P80/K80) | AU80: =IF(OR(Q80="",K80="",K80<=0),"",Q80/K80) | AV80: =IF(OR(R80="",N80="",N80<=0),"",R80/N80) -> 33333333 | AW80: =IFERROR(IF(Z80="No",0,IF(Z80="Yes",AM80/K80,"")),"") | AX80: =IF(OR(K80<Outlier_Audit!$H$2,K80>Outlier_Audit!$I$2),"Review","Normal") -> Normal | AY80: =IF(AL80="","Unknown",IF(AL80<10,"<10 years",IF(AL80<20,"10-19 years",IF(AL80<30,"20-29 years","30+ years")))) -> <10 years | AZ80: =IF(AQ80="","Missing",IF(AQ80>=EDA_Performance!$B$7,"High Growth",IF(AQ80<=EDA_Performance!$B$5,"Low Growth","Middle"))) -> Missing
A81: 1614317 | B81: Eastern | C81: Small | D81: 7 | E81: 1062 | F81: 10 | G81: Manufacture of food products | H81: 2019 | I81: 5 | J81: 1.7984211 | K81: 24000000 | L81: 20000000 | M81: 70 | N81: 7 | O81: 4 | P81: 10000000 | Q81: 5000000 | R81: 15000000 | S81: 0 | T81: Not asked (survey skip: screener employment <20) | U81: No | V81: No | W81: 30 | X81: 70 | Y81: 0 | Z81: No | AB81: Yes | AC81: No | AD81: Yes | AE81: 4 | AF81: Major obstacle | AG81: Major obstacle | AH81: No obstacle | AI81: Major obstacle | AJ81: Electricity | AK81: Are taken directly from establishment records | AL81: =IF(H81="","",2024-H81) -> 5 | AM81: =IFERROR(IF(Z81="No",0,IF(Z81="Yes",AA81,"")),"") -> 0 | AN81: =IFERROR(IF(AD81="No",0,IF(AD81="Yes",AE81,"")),"") -> 4 | AO81: =IF(S81>0,"Yes","No") -> No | AP81: =IF(OR(K81="",L81="",L81<=0),"",K81/L81-1) -> 0.2 | AQ81: =IF(OR(K81="",L81="",L81<=0),"",(K81/L81)^(1/2)-1) -> 0.095445115 | AR81: =IF(OR(N81="",O81="",O81<=0),"",N81/O81-1) -> 0.75 | AS81: =IF(OR(K81="",N81="",N81<=0),"",K81/N81) -> 3428571.4 | AT81: =IF(OR(P81="",K81="",K81<=0),"",P81/K81) -> 0.41666667 | AU81: =IF(OR(Q81="",K81="",K81<=0),"",Q81/K81) -> 0.20833333 | AV81: =IF(OR(R81="",N81="",N81<=0),"",R81/N81) -> 2142857.1 | AW81: =IFERROR(IF(Z81="No",0,IF(Z81="Yes",AM81/K81,"")),"") -> 0 | AX81: =IF(OR(K81<Outlier_Audit!$H$2,K81>Outlier_Audit!$I$2),"Review","Normal") -> Normal | AY81: =IF(AL81="","Unknown",IF(AL81<10,"<10 years",IF(AL81<20,"10-19 years",IF(AL81<30,"20-29 years","30+ years")))) -> <10 years | AZ81: =IF(AQ81="","Missing",IF(AQ81>=EDA_Performance!$B$7,"High Growth",IF(AQ81<=EDA_Performance!$B$5,"Low Growth","Middle"))) -> Middle
A82: 1614319 | B82: Western | C82: Medium | D82: 20 | E82: 2022 | F82: 20 | G82: Manufacture of chemicals and chemical products | H82: 2017 | I82: 6 | J82: 2.6198342 | K82: 210000000 | L82: 180000000 | M82: 40 | N82: 10 | O82: 5 | P82: 50000000 | Q82: 150000000 | R82: 100000000 | S82: 0 | T82: Yes | U82: Yes | V82: Yes | W82: 20 | X82: 20 | Y82: 10 | Z82: Yes | AA82: 0 | AB82: Yes | AC82: Yes | AD82: Yes | AE82: 3 | AF82: Moderate obstacle | AG82: Major obstacle | AH82: Moderate obstacle | AI82: Very severe obstacle | AJ82: Practices of competitors in the informal sector | AK82: Are estimates computed with some precision | AL82: =IF(H82="","",2024-H82) -> 7 | AM82: =IFERROR(IF(Z82="No",0,IF(Z82="Yes",AA82,"")),"") -> 0 | AN82: =IFERROR(IF(AD82="No",0,IF(AD82="Yes",AE82,"")),"") -> 3 | AO82: =IF(S82>0,"Yes","No") -> No | AP82: =IF(OR(K82="",L82="",L82<=0),"",K82/L82-1) -> 0.16666667 | AQ82: =IF(OR(K82="",L82="",L82<=0),"",(K82/L82)^(1/2)-1) -> 0.08012345 | AR82: =IF(OR(N82="",O82="",O82<=0),"",N82/O82-1) -> 1 | AS82: =IF(OR(K82="",N82="",N82<=0),"",K82/N82) -> 21000000 | AT82: =IF(OR(P82="",K82="",K82<=0),"",P82/K82) -> 0.23809524 | AU82: =IF(OR(Q82="",K82="",K82<=0),"",Q82/K82) -> 0.71428571 | AV82: =IF(OR(R82="",N82="",N82<=0),"",R82/N82) -> 10000000 | AW82: =IFERROR(IF(Z82="No",0,IF(Z82="Yes",AM82/K82,"")),"") -> 0 | AX82: =IF(OR(K82<Outlier_Audit!$H$2,K82>Outlier_Audit!$I$2),"Review","Normal") -> Normal | AY82: =IF(AL82="","Unknown",IF(AL82<10,"<10 years",IF(AL82<20,"10-19 years",IF(AL82<30,"20-29 years","30+ years")))) -> <10 years | AZ82: =IF(AQ82="","Missing",IF(AQ82>=EDA_Performance!$B$7,"High Growth",IF(AQ82<=EDA_Performance!$B$5,"Low Growth","Middle"))) -> Middle
A83: 1614321 | B83: Eastern | C83: Medium | D83: 150 | E83: 1061 | F83: 10 | G83: Manufacture of food products | H83: 2005 | I83: 20 | J83: 1.6103765 | K83: 15000000000 | L83: 25000000000 | M83: 50 | N83: 100 | O83: 150 | P83: 300000000 | Q83: 11000000000 | R83: 80000000 | S83: 0 | T83: Yes | U83: No | V83: No | W83: 100 | X83: 0 | Y83: 0 | Z83: No | AB83: Yes | AC83: No | AD83: Yes | AE83: 1 | AF83: No obstacle | AG83: Minor obstacle | AH83: No obstacle | AI83: Minor obstacle | AJ83: Customs and trade regulations | AK83: Are in some case taken from books and in some case estimates | AL83: =IF(H83="","",2024-H83) -> 19 | AM83: =IFERROR(IF(Z83="No",0,IF(Z83="Yes",AA83,"")),"") -> 0 | AN83: =IFERROR(IF(AD83="No",0,IF(AD83="Yes",AE83,"")),"") -> 1 | AO83: =IF(S83>0,"Yes","No") -> No | AP83: =IF(OR(K83="",L83="",L83<=0),"",K83/L83-1) -> -0.4 | AQ83: =IF(OR(K83="",L83="",L83<=0),"",(K83/L83)^(1/2)-1) -> -0.22540333 | AR83: =IF(OR(N83="",O83="",O83<=0),"",N83/O83-1) -> -0.33333333 | AS83: =IF(OR(K83="",N83="",N83<=0),"",K83/N83) -> 150000000 | AT83: =IF(OR(P83="",K83="",K83<=0),"",P83/K83) -> 0.02 | AU83: =IF(OR(Q83="",K83="",K83<=0),"",Q83/K83) -> 0.73333333 | AV83: =IF(OR(R83="",N83="",N83<=0),"",R83/N83) -> 800000 | AW83: =IFERROR(IF(Z83="No",0,IF(Z83="Yes",AM83/K83,"")),"") -> 0 | AX83: =IF(OR(K83<Outlier_Audit!$H$2,K83>Outlier_Audit!$I$2),"Review","Normal") -> Review | AY83: =IF(AL83="","Unknown",IF(AL83<10,"<10 years",IF(AL83<20,"10-19 years",IF(AL83<30,"20-29 years","30+ years")))) -> 10-19 years | AZ83: =IF(AQ83="","Missing",IF(AQ83>=EDA_Performance!$B$7,"High Growth",IF(AQ83<=EDA_Performance!$B$5,"Low Growth","Middle"))) -> Low Growth
A84: 1614322 | B84: Eastern | C84: Large | D84: 350 | E84: 2394 | F84: 23 | G84: Manufacture of other non-metallic mineral products | H84: 2018 | I84: 37 | J84: 1 | K84: 12000000000 | L84: 10000000000 | M84: 40 | N84: 350 | O84: 350 | P84: 1000000000 | Q84: 2500000000 | R84: 4000000000 | S84: 0 | T84: Yes | U84: No | V84: No | W84: 100 | X84: 0 | Y84: 0 | Z84: No | AB84: No | AC84: No | AD84: Yes | AE84: 4 | AF84: Major obstacle | AG84: Minor obstacle | AH84: No obstacle | AI84: No obstacle | AJ84: Electricity | AK84: Are estimates computed with some precision | AL84: =IF(H84="","",2024-H84) -> 6 | AM84: =IFERROR(IF(Z84="No",0,IF(Z84="Yes",AA84,"")),"") -> 0 | AN84: =IFERROR(IF(AD84="No",0,IF(AD84="Yes",AE84,"")),"") -> 4 | AO84: =IF(S84>0,"Yes","No") -> No | AP84: =IF(OR(K84="",L84="",L84<=0),"",K84/L84-1) -> 0.2 | AQ84: =IF(OR(K84="",L84="",L84<=0),"",(K84/L84)^(1/2)-1) -> 0.095445115 | AR84: =IF(OR(N84="",O84="",O84<=0),"",N84/O84-1) -> 0 | AS84: =IF(OR(K84="",N84="",N84<=0),"",K84/N84) -> 34285714 | AT84: =IF(OR(P84="",K84="",K84<=0),"",P84/K84) -> 0.083333333 | AU84: =IF(OR(Q84="",K84="",K84<=0),"",Q84/K84) -> 0.20833333 | AV84: =IF(OR(R84="",N84="",N84<=0),"",R84/N84) -> 11428571 | AW84: =IFERROR(IF(Z84="No",0,IF(Z84="Yes",AM84/K84,"")),"") -> 0 | AX84: =IF(OR(K84<Outlier_Audit!$H$2,K84>Outlier_Audit!$I$2),"Review","Normal") -> Review | AY84: =IF(AL84="","Unknown",IF(AL84<10,"<10 years",IF(AL84<20,"10-19 years",IF(AL84<30,"20-29 years","30+ years")))) -> <10 years | AZ84: =IF(AQ84="","Missing",IF(AQ84>=EDA_Performance!$B$7,"High Growth",IF(AQ84<=EDA_Performance!$B$5,"Low Growth","Middle"))) -> Middle
A85: 1614327 | B85: Central | C85: Medium | D85: 10 | E85: 1811 | F85: 18 | G85: Printing and reproduction of recorded media | H85: 2000 | I85: 20 | J85: 48.349552 | K85: 30000000 | L85: 8000000 | M85: 89 | N85: 8 | O85: 2 | P85: 15000000 | Q85: 6000000 | R85: 50000000 | S85: 0 | T85: Not asked (survey skip: screener employment <20) | U85: Yes | V85: No | W85: 50 | X85: 0 | Y85: 2 | Z85: No | AB85: No | AC85: No | AD85: No | AF85: No obstacle | AG85: Minor obstacle | AH85: No obstacle | AI85: Minor obstacle | AJ85: Corruption | AK85: Are in some case taken from books and in some case estimates | AL85: =IF(H85="","",2024-H85) -> 24 | AM85: =IFERROR(IF(Z85="No",0,IF(Z85="Yes",AA85,"")),"") -> 0 | AN85: =IFERROR(IF(AD85="No",0,IF(AD85="Yes",AE85,"")),"") -> 0 | AO85: =IF(S85>0,"Yes","No") -> No | AP85: =IF(OR(K85="",L85="",L85<=0),"",K85/L85-1) -> 2.75 | AQ85: =IF(OR(K85="",L85="",L85<=0),"",(K85/L85)^(1/2)-1) -> 0.93649167 | AR85: =IF(OR(N85="",O85="",O85<=0),"",N85/O85-1) -> 3 | AS85: =IF(OR(K85="",N85="",N85<=0),"",K85/N85) -> 3750000 | AT85: =IF(OR(P85="",K85="",K85<=0),"",P85/K85) -> 0.5 | AU85: =IF(OR(Q85="",K85="",K85<=0),"",Q85/K85) -> 0.2 | AV85: =IF(OR(R85="",N85="",N85<=0),"",R85/N85) -> 6250000 | AW85: =IFERROR(IF(Z85="No",0,IF(Z85="Yes",AM85/K85,"")),"") -> 0 | AX85: =IF(OR(K85<Outlier_Audit!$H$2,K85>Outlier_Audit!$I$2),"Review","Normal") -> Normal | AY85: =IF(AL85="","Unknown",IF(AL85<10,"<10 years",IF(AL85<20,"10-19 years",IF(AL85<30,"20-29 years","30+ years")))) -> 20-29 years | AZ85: =IF(AQ85="","Missing",IF(AQ85>=EDA_Performance!$B$7,"High Growth",IF(AQ85<=EDA_Performance!$B$5,"Low Growth","Middle"))) -> High Growth
A86: 1614329 | B86: Eastern | C86: Medium | D86: 6 | E86: 3100 | F86: 31 | G86: Manufacture of furniture | H86: 2010 | I86: 15 | J86: 1.6637996 | K86: 250000000 | L86: 230000000 | M86: 90 | N86: 5 | O86: 5 | P86: 25200000 | Q86: 30000000 | R86: 60000000 | S86: 0 | T86: Not asked (survey skip: screener employment <20) | U86: No | V86: No | W86: 90 | X86: 0 | Y86: 0 | Z86: No | AB86: No | AC86: No | AD86: No | AF86: Moderate obstacle | AG86: Moderate obstacle | AH86: No obstacle | AI86: Major obstacle | AJ86: Practices of competitors in the informal sector | AK86: Are taken directly from establishment records | AL86: =IF(H86="","",2024-H86) -> 14 | AM86: =IFERROR(IF(Z86="No",0,IF(Z86="Yes",AA86,"")),"") -> 0 | AN86: =IFERROR(IF(AD86="No",0,IF(AD86="Yes",AE86,"")),"") -> 0 | AO86: =IF(S86>0,"Yes","No") -> No | AP86: =IF(OR(K86="",L86="",L86<=0),"",K86/L86-1) -> 0.086956522 | AQ86: =IF(OR(K86="",L86="",L86<=0),"",(K86/L86)^(1/2)-1) -> 0.04257207 | AR86: =IF(OR(N86="",O86="",O86<=0),"",N86/O86-1) -> 0 | AS86: =IF(OR(K86="",N86="",N86<=0),"",K86/N86) -> 50000000 | AT86: =IF(OR(P86="",K86="",K86<=0),"",P86/K86) -> 0.1008 | AU86: =IF(OR(Q86="",K86="",K86<=0),"",Q86/K86) -> 0.12 | AV86: =IF(OR(R86="",N86="",N86<=0),"",R86/N86) -> 12000000 | AW86: =IFERROR(IF(Z86="No",0,IF(Z86="Yes",AM86/K86,"")),"") -> 0 | AX86: =IF(OR(K86<Outlier_Audit!$H$2,K86>Outlier_Audit!$I$2),"Review","Normal") -> Normal | AY86: =IF(AL86="","Unknown",IF(AL86<10,"<10 years",IF(AL86<20,"10-19 years",IF(AL86<30,"20-29 years","30+ years")))) -> 10-19 years | AZ86: =IF(AQ86="","Missing",IF(AQ86>=EDA_Performance!$B$7,"High Growth",IF(AQ86<=EDA_Performance!$B$5,"Low Growth","Middle"))) -> Middle
A87: 1614330 | B87: Western | C87: Medium | D87: 11 | E87: 2511 | F87: 25 | G87: Manufacture of fabricated metal products | H87: 2007 | I87: 18 | J87: 2.6198342 | K87: 650000000 | L87: 470000000 | M87: 90 | N87: 7 | O87: 7 | P87: 85800000 | Q87: 50000000 | R87: 70000000 | S87: 0 | T87: Not asked (survey skip: screener employment <20) | U87: Yes | V87: Yes | W87: 80 | X87: 0 | Y87: 0 | Z87: No | AB87: No | AC87: No | AD87: Yes | AE87: 4 | AF87: Very severe obstacle | AG87: Major obstacle | AH87: Moderate obstacle | AI87: Moderate obstacle | AJ87: Electricity | AK87: Are taken directly from establishment records | AL87: =IF(H87="","",2024-H87) -> 17 | AM87: =IFERROR(IF(Z87="No",0,IF(Z87="Yes",AA87,"")),"") -> 0 | AN87: =IFERROR(IF(AD87="No",0,IF(AD87="Yes",AE87,"")),"") -> 4 | AO87: =IF(S87>0,"Yes","No") -> No | AP87: =IF(OR(K87="",L87="",L87<=0),"",K87/L87-1) -> 0.38297872 | AQ87: =IF(OR(K87="",L87="",L87<=0),"",(K87/L87)^(1/2)-1) -> 0.17600116 | AR87: =IF(OR(N87="",O87="",O87<=0),"",N87/O87-1) -> 0 | AS87: =IF(OR(K87="",N87="",N87<=0),"",K87/N87) -> 92857143 | AT87: =IF(OR(P87="",K87="",K87<=0),"",P87/K87) -> 0.132 | AU87: =IF(OR(Q87="",K87="",K87<=0),"",Q87/K87) -> 0.076923077 | AV87: =IF(OR(R87="",N87="",N87<=0),"",R87/N87) -> 10000000 | AW87: =IFERROR(IF(Z87="No",0,IF(Z87="Yes",AM87/K87,"")),"") -> 0 | AX87: =IF(OR(K87<Outlier_Audit!$H$2,K87>Outlier_Audit!$I$2),"Review","Normal") -> Normal | AY87: =IF(AL87="","Unknown",IF(AL87<10,"<10 years",IF(AL87<20,"10-19 years",IF(AL87<30,"20-29 years","30+ years")))) -> 10-19 years | AZ87: =IF(AQ87="","Missing",IF(AQ87>=EDA_Performance!$B$7,"High Growth",IF(AQ87<=EDA_Performance!$B$5,"Low Growth","Middle"))) -> Middle
A88: 1614332 | B88: Central | C88: Large | D88: 51 | E88: 2720 | F88: 27 | G88: Manufacture of electrical equipment | H88: 1967 | I88: 28 | J88: 1.574964 | K88: 500000000 | L88: 300000000 | M88: 95 | N88: 51 | O88: 15 | P88: 150000000 | Q88: 250000000 | R88: 700000000 | S88: 0 | T88: Yes | U88: No | V88: No | W88: 50 | X88: 0 | Y88: 35 | Z88: No | AB88: No | AC88: No | AD88: Yes | AE88: 2 | AF88: Minor obstacle | AG88: Minor obstacle | AH88: Minor obstacle | AI88: No obstacle | AJ88: Tax rates | AK88: Are in some case taken from books and in some case estimates | AL88: =IF(H88="","",2024-H88) -> 57 | AM88: =IFERROR(IF(Z88="No",0,IF(Z88="Yes",AA88,"")),"") -> 0 | AN88: =IFERROR(IF(AD88="No",0,IF(AD88="Yes",AE88,"")),"") -> 2 | AO88: =IF(S88>0,"Yes","No") -> No | AP88: =IF(OR(K88="",L88="",L88<=0),"",K88/L88-1) -> 0.66666667 | AQ88: =IF(OR(K88="",L88="",L88<=0),"",(K88/L88)^(1/2)-1) -> 0.29099445 | AR88: =IF(OR(N88="",O88="",O88<=0),"",N88/O88-1) -> 2.4 | AS88: =IF(OR(K88="",N88="",N88<=0),"",K88/N88) -> 9803921.6 | AT88: =IF(OR(P88="",K88="",K88<=0),"",P88/K88) -> 0.3 | AU88: =IF(OR(Q88="",K88="",K88<=0),"",Q88/K88) -> 0.5 | AV88: =IF(OR(R88="",N88="",N88<=0),"",R88/N88) -> 13725490 | AW88: =IFERROR(IF(Z88="No",0,IF(Z88="Yes",AM88/K88,"")),"") -> 0 | AX88: =IF(OR(K88<Outlier_Audit!$H$2,K88>Outlier_Audit!$I$2),"Review","Normal") -> Normal | AY88: =IF(AL88="","Unknown",IF(AL88<10,"<10 years",IF(AL88<20,"10-19 years",IF(AL88<30,"20-29 years","30+ years")))) -> 30+ years | AZ88: =IF(AQ88="","Missing",IF(AQ88>=EDA_Performance!$B$7,"High Growth",IF(AQ88<=EDA_Performance!$B$5,"Low Growth","Middle"))) -> High Growth
A89: 1614337 | B89: Central | C89: Large | D89: 1500 | E89: 1410 | F89: 14 | G89: Manufacture of wearing apparel | H89: 2015 | I89: 8 | J89: 1.574964 | K89: 32000000000 | L89: 30000000000 | M89: 76 | N89: 1500 | O89: 1350 | P89: 300000000 | Q89: 21000000000 | R89: 55000000000 | S89: 30 | T89: Yes | U89: Yes | V89: No | W89: 40 | X89: 20 | Y89: 10 | Z89: No | AB89: Yes | AC89: No | AD89: Yes | AE89: 5 | AF89: Very severe obstacle | AG89: Major obstacle | AH89: Minor obstacle | AI89: No obstacle | AJ89: Electricity | AK89: Are in some case taken from books and in some case estimates | AL89: =IF(H89="","",2024-H89) -> 9 | AM89: =IFERROR(IF(Z89="No",0,IF(Z89="Yes",AA89,"")),"") -> 0 | AN89: =IFERROR(IF(AD89="No",0,IF(AD89="Yes",AE89,"")),"") -> 5 | AO89: =IF(S89>0,"Yes","No") -> Yes | AP89: =IF(OR(K89="",L89="",L89<=0),"",K89/L89-1) -> 0.066666667 | AQ89: =IF(OR(K89="",L89="",L89<=0),"",(K89/L89)^(1/2)-1) -> 0.032795559 | AR89: =IF(OR(N89="",O89="",O89<=0),"",N89/O89-1) -> 0.11111111 | AS89: =IF(OR(K89="",N89="",N89<=0),"",K89/N89) -> 21333333 | AT89: =IF(OR(P89="",K89="",K89<=0),"",P89/K89) -> 0.009375 | AU89: =IF(OR(Q89="",K89="",K89<=0),"",Q89/K89) -> 0.65625 | AV89: =IF(OR(R89="",N89="",N89<=0),"",R89/N89) -> 36666667 | AW89: =IFERROR(IF(Z89="No",0,IF(Z89="Yes",AM89/K89,"")),"") -> 0 | AX89: =IF(OR(K89<Outlier_Audit!$H$2,K89>Outlier_Audit!$I$2),"Review","Normal") -> Review | AY89: =IF(AL89="","Unknown",IF(AL89<10,"<10 years",IF(AL89<20,"10-19 years",IF(AL89<30,"20-29 years","30+ years")))) -> <10 years | AZ89: =IF(AQ89="","Missing",IF(AQ89>=EDA_Performance!$B$7,"High Growth",IF(AQ89<=EDA_Performance!$B$5,"Low Growth","Middle"))) -> Low Growth
A90: 1614340 | B90: Eastern | C90: Medium | D90: 40 | E90: 1079 | F90: 10 | G90: Manufacture of food products | H90: 1988 | I90: 39 | J90: 1.6103765 | K90: 120000000 | L90: 90000000 | M90: 60 | N90: 30 | O90: 25 | P90: 36000000 | Q90: 31000000 | R90: 200000000 | S90: 0 | T90: Yes | U90: No | V90: No | W90: 80 | X90: 20 | Y90: 0 | Z90: Yes | AA90: 20000000 | AB90: Yes | AC90: No | AD90: Yes | AE90: 4 | AF90: Very severe obstacle | AG90: Major obstacle | AH90: Minor obstacle | AI90: Major obstacle | AJ90: Practices of competitors in the informal sector | AK90: Are taken directly from establishment records | AL90: =IF(H90="","",2024-H90) -> 36 | AM90: =IFERROR(IF(Z90="No",0,IF(Z90="Yes",AA90,"")),"") -> 20000000 | AN90: =IFERROR(IF(AD90="No",0,IF(AD90="Yes",AE90,"")),"") -> 4 | AO90: =IF(S90>0,"Yes","No") -> No | AP90: =IF(OR(K90="",L90="",L90<=0),"",K90/L90-1) -> 0.33333333 | AQ90: =IF(OR(K90="",L90="",L90<=0),"",(K90/L90)^(1/2)-1) -> 0.15470054 | AR90: =IF(OR(N90="",O90="",O90<=0),"",N90/O90-1) -> 0.2 | AS90: =IF(OR(K90="",N90="",N90<=0),"",K90/N90) -> 4000000 | AT90: =IF(OR(P90="",K90="",K90<=0),"",P90/K90) -> 0.3 | AU90: =IF(OR(Q90="",K90="",K90<=0),"",Q90/K90) -> 0.25833333 | AV90: =IF(OR(R90="",N90="",N90<=0),"",R90/N90) -> 6666666.7 | AW90: =IFERROR(IF(Z90="No",0,IF(Z90="Yes",AM90/K90,"")),"") -> 0.16666667 | AX90: =IF(OR(K90<Outlier_Audit!$H$2,K90>Outlier_Audit!$I$2),"Review","Normal") -> Normal | AY90: =IF(AL90="","Unknown",IF(AL90<10,"<10 years",IF(AL90<20,"10-19 years",IF(AL90<30,"20-29 years","30+ years")))) -> 30+ years | AZ90: =IF(AQ90="","Missing",IF(AQ90>=EDA_Performance!$B$7,"High Growth",IF(AQ90<=EDA_Performance!$B$5,"Low Growth","Middle"))) -> Middle
A91: 1614341 | B91: Central | C91: Large | D91: 43 | E91: 2220 | F91: 22 | G91: Manufacture of rubber and plastics products | H91: 1997 | I91: 27 | J91: 1.574964 | K91: 650000000 | L91: 450000000 | M91: 95 | N91: 35 | O91: 20 | P91: 25000000 | Q91: 300000000 | R91: 180000000 | S91: 20 | T91: Yes | U91: No | V91: Yes | W91: 60 | X91: 40 | Y91: 0 | Z91: Yes | AA91: 180000000 | AB91: Yes | AC91: No | AD91: Yes | AE91: 9 | AF91: No obstacle | AG91: No obstacle | AH91: No obstacle | AI91: Moderate obstacle | AJ91: Tax administration | AK91: Are taken directly from establishment records | AL91: =IF(H91="","",2024-H91) -> 27 | AM91: =IFERROR(IF(Z91="No",0,IF(Z91="Yes",AA91,"")),"") -> 180000000 | AN91: =IFERROR(IF(AD91="No",0,IF(AD91="Yes",AE91,"")),"") -> 9 | AO91: =IF(S91>0,"Yes","No") -> Yes | AP91: =IF(OR(K91="",L91="",L91<=0),"",K91/L91-1) -> 0.44444444 | AQ91: =IF(OR(K91="",L91="",L91<=0),"",(K91/L91)^(1/2)-1) -> 0.20185043 | AR91: =IF(OR(N91="",O91="",O91<=0),"",N91/O91-1) -> 0.75 | AS91: =IF(OR(K91="",N91="",N91<=0),"",K91/N91) -> 18571429 | AT91: =IF(OR(P91="",K91="",K91<=0),"",P91/K91) -> 0.038461538 | AU91: =IF(OR(Q91="",K91="",K91<=0),"",Q91/K91) -> 0.46153846 | AV91: =IF(OR(R91="",N91="",N91<=0),"",R91/N91) -> 5142857.1 | AW91: =IFERROR(IF(Z91="No",0,IF(Z91="Yes",AM91/K91,"")),"") -> 0.27692308 | AX91: =IF(OR(K91<Outlier_Audit!$H$2,K91>Outlier_Audit!$I$2),"Review","Normal") -> Normal | AY91: =IF(AL91="","Unknown",IF(AL91<10,"<10 years",IF(AL91<20,"10-19 years",IF(AL91<30,"20-29 years","30+ years")))) -> 20-29 years | AZ91: =IF(AQ91="","Missing",IF(AQ91>=EDA_Performance!$B$7,"High Growth",IF(AQ91<=EDA_Performance!$B$5,"Low Growth","Middle"))) -> Middle
A92: 1614342 | B92: Western | C92: Medium | D92: 150 | E92: 1030 | F92: 10 | G92: Manufacture of food products | H92: 2008 | I92: 17 | J92: 2.6198342 | K92: 36000000000 | L92: 35000000000 | M92: 80 | N92: 45 | O92: 45 | P92: 900000000 | S92: 0 | T92: Yes | U92: Yes | V92: No | Z92: No | AB92: Yes | AC92: No | AD92: Yes | AF92: No obstacle | AH92: Minor obstacle | AJ92: Electricity | AK92: Are in some case taken from books and in some case estimates | AL92: =IF(H92="","",2024-H92) -> 16 | AM92: =IFERROR(IF(Z92="No",0,IF(Z92="Yes",AA92,"")),"") -> 0 | AN92: =IFERROR(IF(AD92="No",0,IF(AD92="Yes",AE92,"")),"") -> 0 | AO92: =IF(S92>0,"Yes","No") -> No | AP92: =IF(OR(K92="",L92="",L92<=0),"",K92/L92-1) -> 0.028571429 | AQ92: =IF(OR(K92="",L92="",L92<=0),"",(K92/L92)^(1/2)-1) -> 0.014185106 | AR92: =IF(OR(N92="",O92="",O92<=0),"",N92/O92-1) -> 0 | AS92: =IF(OR(K92="",N92="",N92<=0),"",K92/N92) -> 800000000 | AT92: =IF(OR(P92="",K92="",K92<=0),"",P92/K92) -> 0.025 | AU92: =IF(OR(Q92="",K92="",K92<=0),"",Q92/K92) | AV92: =IF(OR(R92="",N92="",N92<=0),"",R92/N92) | AW92: =IFERROR(IF(Z92="No",0,IF(Z92="Yes",AM92/K92,"")),"") -> 0 | AX92: =IF(OR(K92<Outlier_Audit!$H$2,K92>Outlier_Audit!$I$2),"Review","Normal") -> Review | AY92: =IF(AL92="","Unknown",IF(AL92<10,"<10 years",IF(AL92<20,"10-19 years",IF(AL92<30,"20-29 years","30+ years")))) -> 10-19 years | AZ92: =IF(AQ92="","Missing",IF(AQ92>=EDA_Performance!$B$7,"High Growth",IF(AQ92<=EDA_Performance!$B$5,"Low Growth","Middle"))) -> Low Growth
A93: 1614344 | B93: Central | C93: Medium | D93: 15 | E93: 1080 | F93: 10 | G93: Manufacture of food products | H93: 2013 | I93: 20 | J93: 23.458492 | K93: 80000000 | L93: 65000000 | M93: 75 | N93: 15 | O93: 5 | P93: 25000000 | Q93: 40000000 | R93: 200000000 | S93: 0 | T93: Not asked (survey skip: screener employment <20) | U93: No | V93: No | W93: 70 | X93: 0 | Y93: 30 | Z93: No | AB93: No | AC93: No | AD93: Yes | AE93: 3 | AF93: Minor obstacle | AG93: No obstacle | AH93: No obstacle | AI93: Minor obstacle | AJ93: Tax rates | AK93: Are in some case taken from books and in some case estimates | AL93: =IF(H93="","",2024-H93) -> 11 | AM93: =IFERROR(IF(Z93="No",0,IF(Z93="Yes",AA93,"")),"") -> 0 | AN93: =IFERROR(IF(AD93="No",0,IF(AD93="Yes",AE93,"")),"") -> 3 | AO93: =IF(S93>0,"Yes","No") -> No | AP93: =IF(OR(K93="",L93="",L93<=0),"",K93/L93-1) -> 0.23076923 | AQ93: =IF(OR(K93="",L93="",L93<=0),"",(K93/L93)^(1/2)-1) -> 0.10940039 | AR93: =IF(OR(N93="",O93="",O93<=0),"",N93/O93-1) -> 2 | AS93: =IF(OR(K93="",N93="",N93<=0),"",K93/N93) -> 5333333.3 | AT93: =IF(OR(P93="",K93="",K93<=0),"",P93/K93) -> 0.3125 | AU93: =IF(OR(Q93="",K93="",K93<=0),"",Q93/K93) -> 0.5 | AV93: =IF(OR(R93="",N93="",N93<=0),"",R93/N93) -> 13333333 | AW93: =IFERROR(IF(Z93="No",0,IF(Z93="Yes",AM93/K93,"")),"") -> 0 | AX93: =IF(OR(K93<Outlier_Audit!$H$2,K93>Outlier_Audit!$I$2),"Review","Normal") -> Normal | AY93: =IF(AL93="","Unknown",IF(AL93<10,"<10 years",IF(AL93<20,"10-19 years",IF(AL93<30,"20-29 years","30+ years")))) -> 10-19 years | AZ93: =IF(AQ93="","Missing",IF(AQ93>=EDA_Performance!$B$7,"High Growth",IF(AQ93<=EDA_Performance!$B$5,"Low Growth","Middle"))) -> Middle
A94: 1614346 | B94: Western | C94: Large | D94: 520 | E94: 1079 | F94: 10 | G94: Manufacture of food products | H94: 1969 | I94: 15 | J94: 1.3089461 | K94: 9400000000 | L94: 21000000000 | M94: 100 | N94: 266 | O94: 316 | P94: 750000000 | Q94: 2600000000 | R94: 15000000000 | S94: 90 | T94: Yes | U94: No | V94: No | W94: 70 | X94: 0 | Y94: 30 | Z94: No | AB94: Yes | AC94: No | AD94: Yes | AE94: 8 | AF94: Very severe obstacle | AG94: Major obstacle | AH94: Minor obstacle | AJ94: Electricity | AK94: Are taken directly from establishment records | AL94: =IF(H94="","",2024-H94) -> 55 | AM94: =IFERROR(IF(Z94="No",0,IF(Z94="Yes",AA94,"")),"") -> 0 | AN94: =IFERROR(IF(AD94="No",0,IF(AD94="Yes",AE94,"")),"") -> 8 | AO94: =IF(S94>0,"Yes","No") -> Yes | AP94: =IF(OR(K94="",L94="",L94<=0),"",K94/L94-1) -> -0.55238095 | AQ94: =IF(OR(K94="",L94="",L94<=0),"",(K94/L94)^(1/2)-1) -> -0.33095662 | AR94: =IF(OR(N94="",O94="",O94<=0),"",N94/O94-1) -> -0.15822785 | AS94: =IF(OR(K94="",N94="",N94<=0),"",K94/N94) -> 35338346 | AT94: =IF(OR(P94="",K94="",K94<=0),"",P94/K94) -> 0.079787234 | AU94: =IF(OR(Q94="",K94="",K94<=0),"",Q94/K94) -> 0.27659574 | AV94: =IF(OR(R94="",N94="",N94<=0),"",R94/N94) -> 56390977 | AW94: =IFERROR(IF(Z94="No",0,IF(Z94="Yes",AM94/K94,"")),"") -> 0 | AX94: =IF(OR(K94<Outlier_Audit!$H$2,K94>Outlier_Audit!$I$2),"Review","Normal") -> Review | AY94: =IF(AL94="","Unknown",IF(AL94<10,"<10 years",IF(AL94<20,"10-19 years",IF(AL94<30,"20-29 years","30+ years")))) -> 30+ years | AZ94: =IF(AQ94="","Missing",IF(AQ94>=EDA_Performance!$B$7,"High Growth",IF(AQ94<=EDA_Performance!$B$5,"Low Growth","Middle"))) -> Low Growth
A95: 1614348 | B95: Western | C95: Large | D95: 300 | E95: 1050 | F95: 10 | G95: Manufacture of food products | H95: 2014 | I95: 26 | J95: 1.261686 | K95: 82800000000 | M95: 25 | N95: 20 | O95: 20 | Q95: 46800000000 | R95: 50000000000 | S95: 20 | T95: Yes | U95: No | V95: Yes | W95: 100 | X95: 0 | Y95: 0 | Z95: Yes | AA95: 0 | AB95: No | AC95: No | AD95: Yes | AE95: 4 | AF95: Minor obstacle | AG95: Minor obstacle | AH95: Moderate obstacle | AJ95: Tax rates | AK95: Are estimates computed with some precision | AL95: =IF(H95="","",2024-H95) -> 10 | AM95: =IFERROR(IF(Z95="No",0,IF(Z95="Yes",AA95,"")),"") -> 0 | AN95: =IFERROR(IF(AD95="No",0,IF(AD95="Yes",AE95,"")),"") -> 4 | AO95: =IF(S95>0,"Yes","No") -> Yes | AP95: =IF(OR(K95="",L95="",L95<=0),"",K95/L95-1) | AQ95: =IF(OR(K95="",L95="",L95<=0),"",(K95/L95)^(1/2)-1) | AR95: =IF(OR(N95="",O95="",O95<=0),"",N95/O95-1) -> 0 | AS95: =IF(OR(K95="",N95="",N95<=0),"",K95/N95) -> 4140000000 | AT95: =IF(OR(P95="",K95="",K95<=0),"",P95/K95) | AU95: =IF(OR(Q95="",K95="",K95<=0),"",Q95/K95) -> 0.56521739 | AV95: =IF(OR(R95="",N95="",N95<=0),"",R95/N95) -> 2500000000 | AW95: =IFERROR(IF(Z95="No",0,IF(Z95="Yes",AM95/K95,"")),"") -> 0 | AX95: =IF(OR(K95<Outlier_Audit!$H$2,K95>Outlier_Audit!$I$2),"Review","Normal") -> Review | AY95: =IF(AL95="","Unknown",IF(AL95<10,"<10 years",IF(AL95<20,"10-19 years",IF(AL95<30,"20-29 years","30+ years")))) -> 10-19 years | AZ95: =IF(AQ95="","Missing",IF(AQ95>=EDA_Performance!$B$7,"High Growth",IF(AQ95<=EDA_Performance!$B$5,"Low Growth","Middle"))) -> Missing
A96: 1614349 | B96: Eastern | C96: Small | D96: 15 | E96: 1629 | F96: 16 | G96: Manufacture of wood and products of wood/cork | H96: 2017 | I96: 17 | J96: 68.513817 | K96: 6000000 | L96: 2000000 | M96: 40 | N96: 15 | O96: 9 | P96: 3000000 | Q96: 4000000 | R96: 28000000 | S96: 0 | T96: Not asked (survey skip: screener employment <20) | U96: No | V96: Yes | W96: 100 | X96: 0 | Y96: 0 | Z96: No | AB96: No | AC96: No | AD96: Yes | AE96: 10 | AF96: Major obstacle | AG96: Moderate obstacle | AH96: No obstacle | AI96: Very severe obstacle | AJ96: Electricity | AK96: Are in some case taken from books and in some case estimates | AL96: =IF(H96="","",2024-H96) -> 7 | AM96: =IFERROR(IF(Z96="No",0,IF(Z96="Yes",AA96,"")),"") -> 0 | AN96: =IFERROR(IF(AD96="No",0,IF(AD96="Yes",AE96,"")),"") -> 10 | AO96: =IF(S96>0,"Yes","No") -> No | AP96: =IF(OR(K96="",L96="",L96<=0),"",K96/L96-1) -> 2 | AQ96: =IF(OR(K96="",L96="",L96<=0),"",(K96/L96)^(1/2)-1) -> 0.73205081 | AR96: =IF(OR(N96="",O96="",O96<=0),"",N96/O96-1) -> 0.66666667 | AS96: =IF(OR(K96="",N96="",N96<=0),"",K96/N96) -> 400000 | AT96: =IF(OR(P96="",K96="",K96<=0),"",P96/K96) -> 0.5 | AU96: =IF(OR(Q96="",K96="",K96<=0),"",Q96/K96) -> 0.66666667 | AV96: =IF(OR(R96="",N96="",N96<=0),"",R96/N96) -> 1866666.7 | AW96: =IFERROR(IF(Z96="No",0,IF(Z96="Yes",AM96/K96,"")),"") -> 0 | AX96: =IF(OR(K96<Outlier_Audit!$H$2,K96>Outlier_Audit!$I$2),"Review","Normal") -> Normal | AY96: =IF(AL96="","Unknown",IF(AL96<10,"<10 years",IF(AL96<20,"10-19 years",IF(AL96<30,"20-29 years","30+ years")))) -> <10 years | AZ96: =IF(AQ96="","Missing",IF(AQ96>=EDA_Performance!$B$7,"High Growth",IF(AQ96<=EDA_Performance!$B$5,"Low Growth","Middle"))) -> High Growth
A97: 1614352 | B97: Western | C97: Medium | D97: 7 | E97: 2511 | F97: 25 | G97: Manufacture of fabricated metal products | H97: 2013 | I97: 12 | J97: 2.6198342 | K97: 575000000 | L97: 300000000 | M97: 90 | N97: 9 | O97: 9 | P97: 42000000 | Q97: 45000000 | R97: 30000000 | S97: 0 | T97: Not asked (survey skip: screener employment <20) | U97: Yes | V97: No | W97: 70 | X97: 0 | Y97: 0 | Z97: No | AB97: No | AC97: No | AD97: Yes | AE97: 3 | AF97: Very severe obstacle | AG97: Very severe obstacle | AH97: Moderate obstacle | AI97: Major obstacle | AJ97: Electricity | AK97: Are taken directly from establishment records | AL97: =IF(H97="","",2024-H97) -> 11 | AM97: =IFERROR(IF(Z97="No",0,IF(Z97="Yes",AA97,"")),"") -> 0 | AN97: =IFERROR(IF(AD97="No",0,IF(AD97="Yes",AE97,"")),"") -> 3 | AO97: =IF(S97>0,"Yes","No") -> No | AP97: =IF(OR(K97="",L97="",L97<=0),"",K97/L97-1) -> 0.91666667 | AQ97: =IF(OR(K97="",L97="",L97<=0),"",(K97/L97)^(1/2)-1) -> 0.38443731 | AR97: =IF(OR(N97="",O97="",O97<=0),"",N97/O97-1) -> 0 | AS97: =IF(OR(K97="",N97="",N97<=0),"",K97/N97) -> 63888889 | AT97: =IF(OR(P97="",K97="",K97<=0),"",P97/K97) -> 0.073043478 | AU97: =IF(OR(Q97="",K97="",K97<=0),"",Q97/K97) -> 0.07826087 | AV97: =IF(OR(R97="",N97="",N97<=0),"",R97/N97) -> 3333333.3 | AW97: =IFERROR(IF(Z97="No",0,IF(Z97="Yes",AM97/K97,"")),"") -> 0 | AX97: =IF(OR(K97<Outlier_Audit!$H$2,K97>Outlier_Audit!$I$2),"Review","Normal") -> Normal | AY97: =IF(AL97="","Unknown",IF(AL97<10,"<10 years",IF(AL97<20,"10-19 years",IF(AL97<30,"20-29 years","30+ years")))) -> 10-19 years | AZ97: =IF(AQ97="","Missing",IF(AQ97>=EDA_Performance!$B$7,"High Growth",IF(AQ97<=EDA_Performance!$B$5,"Low Growth","Middle"))) -> High Growth
A98: 1614354 | B98: Eastern | C98: Medium | D98: 140 | E98: 2511 | F98: 25 | G98: Manufacture of fabricated metal products | H98: 2010 | I98: 25 | J98: 1.6637996 | K98: 900000000 | L98: 1100000000 | M98: 60 | N98: 140 | O98: 132 | P98: 300000000 | Q98: 500000000 | R98: 150000000 | S98: 0 | T98: Yes | U98: No | V98: No | W98: 98 | X98: 0 | Y98: 2 | Z98: No | AB98: No | AC98: No | AD98: Yes | AE98: 8 | AF98: Major obstacle | AG98: Moderate obstacle | AH98: No obstacle | AI98: Minor obstacle | AJ98: Electricity | AK98: Are in some case taken from books and in some case estimates | AL98: =IF(H98="","",2024-H98) -> 14 | AM98: =IFERROR(IF(Z98="No",0,IF(Z98="Yes",AA98,"")),"") -> 0 | AN98: =IFERROR(IF(AD98="No",0,IF(AD98="Yes",AE98,"")),"") -> 8 | AO98: =IF(S98>0,"Yes","No") -> No | AP98: =IF(OR(K98="",L98="",L98<=0),"",K98/L98-1) -> -0.18181818 | AQ98: =IF(OR(K98="",L98="",L98<=0),"",(K98/L98)^(1/2)-1) -> -0.095465966 | AR98: =IF(OR(N98="",O98="",O98<=0),"",N98/O98-1) -> 0.060606061 | AS98: =IF(OR(K98="",N98="",N98<=0),"",K98/N98) -> 6428571.4 | AT98: =IF(OR(P98="",K98="",K98<=0),"",P98/K98) -> 0.33333333 | AU98: =IF(OR(Q98="",K98="",K98<=0),"",Q98/K98) -> 0.55555556 | AV98: =IF(OR(R98="",N98="",N98<=0),"",R98/N98) -> 1071428.6 | AW98: =IFERROR(IF(Z98="No",0,IF(Z98="Yes",AM98/K98,"")),"") -> 0 | AX98: =IF(OR(K98<Outlier_Audit!$H$2,K98>Outlier_Audit!$I$2),"Review","Normal") -> Normal | AY98: =IF(AL98="","Unknown",IF(AL98<10,"<10 years",IF(AL98<20,"10-19 years",IF(AL98<30,"20-29 years","30+ years")))) -> 10-19 years | AZ98: =IF(AQ98="","Missing",IF(AQ98>=EDA_Performance!$B$7,"High Growth",IF(AQ98<=EDA_Performance!$B$5,"Low Growth","Middle"))) -> Low Growth
A99: 1614355 | B99: Northern | C99: Medium | D99: 15 | E99: 2599 | F99: 25 | G99: Manufacture of fabricated metal products | H99: 2013 | I99: 12 | J99: 2.6425691 | K99: 2700000000 | L99: 1300000000 | M99: 60 | N99: 15 | O99: 15 | P99: 500000000 | Q99: 800000000 | R99: 3000000000 | S99: 0 | T99: Not asked (survey skip: screener employment <20) | U99: No | V99: No | W99: 95 | X99: 0 | Y99: 0 | Z99: No | AB99: No | AC99: No | AD99: No | AF99: Moderate obstacle | AG99: No obstacle | AH99: No obstacle | AI99: No obstacle | AJ99: Electricity | AK99: Are in some case taken from books and in some case estimates | AL99: =IF(H99="","",2024-H99) -> 11 | AM99: =IFERROR(IF(Z99="No",0,IF(Z99="Yes",AA99,"")),"") -> 0 | AN99: =IFERROR(IF(AD99="No",0,IF(AD99="Yes",AE99,"")),"") -> 0 | AO99: =IF(S99>0,"Yes","No") -> No | AP99: =IF(OR(K99="",L99="",L99<=0),"",K99/L99-1) -> 1.0769231 | AQ99: =IF(OR(K99="",L99="",L99<=0),"",(K99/L99)^(1/2)-1) -> 0.44115338 | AR99: =IF(OR(N99="",O99="",O99<=0),"",N99/O99-1) -> 0 | AS99: =IF(OR(K99="",N99="",N99<=0),"",K99/N99) -> 180000000 | AT99: =IF(OR(P99="",K99="",K99<=0),"",P99/K99) -> 0.18518519 | AU99: =IF(OR(Q99="",K99="",K99<=0),"",Q99/K99) -> 0.2962963 | AV99: =IF(OR(R99="",N99="",N99<=0),"",R99/N99) -> 200000000 | AW99: =IFERROR(IF(Z99="No",0,IF(Z99="Yes",AM99/K99,"")),"") -> 0 | AX99: =IF(OR(K99<Outlier_Audit!$H$2,K99>Outlier_Audit!$I$2),"Review","Normal") -> Normal | AY99: =IF(AL99="","Unknown",IF(AL99<10,"<10 years",IF(AL99<20,"10-19 years",IF(AL99<30,"20-29 years","30+ years")))) -> 10-19 years | AZ99: =IF(AQ99="","Missing",IF(AQ99>=EDA_Performance!$B$7,"High Growth",IF(AQ99<=EDA_Performance!$B$5,"Low Growth","Middle"))) -> High Growth
